Workbook

Sheet 结论
A1: 中证红利量化更新：10月13日板块位置与性价比 | B1: 中证红利量化更新：10月13日板块位置与性价比 | C1: 中证红利量化更新：10月13日板块位置与性价比 | D1: 中证红利量化更新：10月13日板块位置与性价比 | E1: 中证红利量化更新：10月13日板块位置与性价比 | F1: 中证红利量化更新：10月13日板块位置与性价比 | G1: 中证红利量化更新：10月13日板块位置与性价比 | H1: 中证红利量化更新：10月13日板块位置与性价比 | I1: 中证红利量化更新：10月13日板块位置与性价比 | J1: 中证红利量化更新：10月13日板块位置与性价比 | K1: 中证红利量化更新：10月13日板块位置与性价比 | L1: 中证红利量化更新：10月13日板块位置与性价比 | M1: 中证红利量化更新：10月13日板块位置与性价比 | N1: 中证红利量化更新：10月13日板块位置与性价比 | O1: 中证红利量化更新：10月13日板块位置与性价比 | P1: 中证红利量化更新：10月13日板块位置与性价比 | Q1: 中证红利量化更新：10月13日板块位置与性价比 | R1: 中证红利量化更新：10月13日板块位置与性价比 | S1: 中证红利量化更新：10月13日板块位置与性价比 | T1: 中证红利量化更新：10月13日板块位置与性价比
A2: 结论：5332—5420点的半年报修正底部已被9月29日5386点低位验证；当前位置已反弹，但银行与煤炭并非同一种“高”，需要把短线强势、绝对估值和盈利质量分开。 | B2: 结论：5332—5420点的半年报修正底部已被9月29日5386点低位验证；当前位置已反弹，但银行与煤炭并非同一种“高”，需要把短线强势、绝对估值和盈利质量分开。 | C2: 结论：5332—5420点的半年报修正底部已被9月29日5386点低位验证；当前位置已反弹，但银行与煤炭并非同一种“高”，需要把短线强势、绝对估值和盈利质量分开。 | D2: 结论：5332—5420点的半年报修正底部已被9月29日5386点低位验证；当前位置已反弹，但银行与煤炭并非同一种“高”，需要把短线强势、绝对估值和盈利质量分开。 | E2: 结论：5332—5420点的半年报修正底部已被9月29日5386点低位验证；当前位置已反弹，但银行与煤炭并非同一种“高”，需要把短线强势、绝对估值和盈利质量分开。 | F2: 结论：5332—5420点的半年报修正底部已被9月29日5386点低位验证；当前位置已反弹，但银行与煤炭并非同一种“高”，需要把短线强势、绝对估值和盈利质量分开。 | G2: 结论：5332—5420点的半年报修正底部已被9月29日5386点低位验证；当前位置已反弹，但银行与煤炭并非同一种“高”，需要把短线强势、绝对估值和盈利质量分开。 | H2: 结论：5332—5420点的半年报修正底部已被9月29日5386点低位验证；当前位置已反弹，但银行与煤炭并非同一种“高”，需要把短线强势、绝对估值和盈利质量分开。 | I2: 结论：5332—5420点的半年报修正底部已被9月29日5386点低位验证；当前位置已反弹，但银行与煤炭并非同一种“高”，需要把短线强势、绝对估值和盈利质量分开。 | J2: 结论：5332—5420点的半年报修正底部已被9月29日5386点低位验证；当前位置已反弹，但银行与煤炭并非同一种“高”，需要把短线强势、绝对估值和盈利质量分开。 | K2: 结论：5332—5420点的半年报修正底部已被9月29日5386点低位验证；当前位置已反弹，但银行与煤炭并非同一种“高”，需要把短线强势、绝对估值和盈利质量分开。 | L2: 结论：5332—5420点的半年报修正底部已被9月29日5386点低位验证；当前位置已反弹，但银行与煤炭并非同一种“高”，需要把短线强势、绝对估值和盈利质量分开。 | M2: 结论：5332—5420点的半年报修正底部已被9月29日5386点低位验证；当前位置已反弹，但银行与煤炭并非同一种“高”，需要把短线强势、绝对估值和盈利质量分开。 | N2: 结论：5332—5420点的半年报修正底部已被9月29日5386点低位验证；当前位置已反弹，但银行与煤炭并非同一种“高”，需要把短线强势、绝对估值和盈利质量分开。 | O2: 结论：5332—5420点的半年报修正底部已被9月29日5386点低位验证；当前位置已反弹，但银行与煤炭并非同一种“高”，需要把短线强势、绝对估值和盈利质量分开。 | P2: 结论：5332—5420点的半年报修正底部已被9月29日5386点低位验证；当前位置已反弹，但银行与煤炭并非同一种“高”，需要把短线强势、绝对估值和盈利质量分开。 | Q2: 结论：5332—5420点的半年报修正底部已被9月29日5386点低位验证；当前位置已反弹，但银行与煤炭并非同一种“高”，需要把短线强势、绝对估值和盈利质量分开。 | R2: 结论：5332—5420点的半年报修正底部已被9月29日5386点低位验证；当前位置已反弹，但银行与煤炭并非同一种“高”，需要把短线强势、绝对估值和盈利质量分开。 | S2: 结论：5332—5420点的半年报修正底部已被9月29日5386点低位验证；当前位置已反弹，但银行与煤炭并非同一种“高”，需要把短线强势、绝对估值和盈利质量分开。 | T2: 结论：5332—5420点的半年报修正底部已被9月29日5386点低位验证；当前位置已反弹，但银行与煤炭并非同一种“高”，需要把短线强势、绝对估值和盈利质量分开。
A4: 数据日期（手填） | C4: 中证红利收盘（手填） | E4: 区间最低 | G4: 低点后反弹 | I4: 8/31至今
A5: 46308 | C5: 5624.5 | E5: =MIN('10.13行情明细'!$E$110:$E$135) -> 5386.04 | G5: =IF(OR(C5="",C5<=0),"",C5/E5-1) -> 0.044273715 | I5: =IF(OR(C5="",C5<=0),"",C5/'10.13行情明细'!C110-1) -> -0.016424117
A6: 黄色单元格可手工更新。仅刷新指数层指标；板块评分仍需更新成分股行情。 | E6: =INDEX('10.13行情明细'!$A$110:$A$135,MATCH(E5,'10.13行情明细'!$E$110:$E$135,0)) -> 46294 | G6: =IF(OR(C5="",C5<=0),"指数状态：请输入有效收盘","指数状态："&IF(C5<B10,"低于保守底部",IF(C5<=B12,"处于模型底部区间",IF(C5<F10,"位于底部与顶部之间",IF(C5<=F12,"进入模型顶部区间","高于积极顶部"))))) -> 指数状态：位于底部与顶部之间
A8: 原策略验证：实际低点是否进入半年报修正底部 | B8: ="" | C8: 原策略验证：实际低点是否进入半年报修正底部 | D8: 原策略验证：实际低点是否进入半年报修正底部 | E8: 原策略验证：实际低点是否进入半年报修正底部 | F8: 原策略验证：实际低点是否进入半年报修正底部 | G8: 原策略验证：实际低点是否进入半年报修正底部 | H8: 原策略验证：实际低点是否进入半年报修正底部
A9: 场景 | B9: ="模型底部" -> 模型底部 | C9: 实际低点 | D9: 低点距模型底部 | E9: ±1.2%验证 | F9: 模型顶部 | G9: 当前距顶部
A10: 保守 | B10: ='10.13方法'!C13 -> 5332.3325 | C10: =$E$5 -> 5386.04 | D10: =$C10/$B10-1 -> 0.010072052 | E10: =IF(ABS(D10)<=1.2%,"命中","接近") -> 命中 | F10: ='10.13方法'!D13 -> 6377.8879 | G10: =IF(OR($C$5="",$C$5<=0),"",F10/$C$5-1) -> 0.13394753
A11: 中枢 | B11: ='10.13方法'!C14 -> 5376.294 | C11: =$E$5 -> 5386.04 | D11: =$C11/$B11-1 -> 0.0018127695 | E11: =IF(ABS(D11)<=1.2%,"命中","接近") -> 命中 | F11: ='10.13方法'!D14 -> 6430.4693 | G11: =IF(OR($C$5="",$C$5<=0),"",F11/$C$5-1) -> 0.14329617
A12: 积极 | B12: ='10.13方法'!C15 -> 5420.2556 | C12: =$E$5 -> 5386.04 | D12: =$C12/$B12-1 -> -0.0063125377 | E12: =IF(ABS(D12)<=1.2%,"命中","接近") -> 命中 | F12: ='10.13方法'!D15 -> 6483.0508 | G12: =IF(OR($C$5="",$C$5<=0),"",F12/$C$5-1) -> 0.15264482
B13: =""
A14: 10月13日结论 | B14: 10月13日结论 | C14: 10月13日结论 | D14: 10月13日结论 | E14: 10月13日结论 | F14: 10月13日结论 | G14: 10月13日结论 | H14: 10月13日结论 | I14: 10月13日结论 | J14: 10月13日结论
A15: 底部判断 | C15: 9月29日最低5386.04点，处于模型5332—5420点区间；5300—5400仍是被验证过的支撑带，不宜把一次命中理解为永久有效。
A16: 银行 | B16: ="" | C16: ="8/31以来加权上涨3.5%，位置分约45；加权PE约6.5倍、PB约0.63倍、TTM股息率约4.7%，绝对估值仍低，但靠近区间高位，适合等回撤而不是追涨。" -> 8/31以来加权上涨3.5%，位置分约45；加权PE约6.5倍、PB约0.63倍、TTM股息率约4.7%，绝对估值仍低，但靠近区间高位，适合等回撤而不是追涨。 | D16: ="" | E16: ="" | F16: =""
A17: 煤炭 | B17: ="" | C17: ="8/31以来仍下跌约8.3%，从各自区间低点反弹约5.4%；H1利润池同比约+18.9%，但当前TTM股息率约2.1%，结论是“中低位置、盈利改善、股息吸引力下降”。" -> 8/31以来仍下跌约8.3%，从各自区间低点反弹约5.4%；H1利润池同比约+18.9%，但当前TTM股息率约2.1%，结论是“中低位置、盈利改善、股息吸引力下降”。 | D17: ="" | E17: ="" | F17: =""
A18: 相对高位 | B18: ="" | C18: ="油气炼化、出版医药、交通物流的位置分居前；油气盈利强但涨得快，出版医药与交通物流则出现价格强、利润弱的背离，追涨风险更高。" -> 油气炼化、出版医药、交通物流的位置分居前；油气盈利强但涨得快，出版医药与交通物流则出现价格强、利润弱的背离，追涨风险更高。 | D18: ="" | E18: ="" | F18: =""
A19: 相对低位 | C19: 有色、化工、建材家居、机械汽车位置较低；有色盈利强但股息率低，更像周期弹性，后三者盈利偏弱，不能只因价格低就买入。
A21: 板块量化：位置分越高越接近相对高位，综合性价比分越高越值得继续跟踪 | B21: 板块量化：位置分越高越接近相对高位，综合性价比分越高越值得继续跟踪 | C21: 板块量化：位置分越高越接近相对高位，综合性价比分越高越值得继续跟踪 | D21: 板块量化：位置分越高越接近相对高位，综合性价比分越高越值得继续跟踪 | E21: 板块量化：位置分越高越接近相对高位，综合性价比分越高越值得继续跟踪 | F21: 板块量化：位置分越高越接近相对高位，综合性价比分越高越值得继续跟踪 | G21: 板块量化：位置分越高越接近相对高位，综合性价比分越高越值得继续跟踪 | H21: 板块量化：位置分越高越接近相对高位，综合性价比分越高越值得继续跟踪 | I21: 板块量化：位置分越高越接近相对高位，综合性价比分越高越值得继续跟踪 | J21: 板块量化：位置分越高越接近相对高位，综合性价比分越高越值得继续跟踪 | K21: 板块量化：位置分越高越接近相对高位，综合性价比分越高越值得继续跟踪 | L21: 板块量化：位置分越高越接近相对高位，综合性价比分越高越值得继续跟踪 | M21: 板块量化：位置分越高越接近相对高位，综合性价比分越高越值得继续跟踪 | N21: 板块量化：位置分越高越接近相对高位，综合性价比分越高越值得继续跟踪 | O21: 板块量化：位置分越高越接近相对高位，综合性价比分越高越值得继续跟踪 | P21: 板块量化：位置分越高越接近相对高位，综合性价比分越高越值得继续跟踪 | Q21: 板块量化：位置分越高越接近相对高位，综合性价比分越高越值得继续跟踪 | R21: 板块量化：位置分越高越接近相对高位，综合性价比分越高越值得继续跟踪 | S21: 板块量化：位置分越高越接近相对高位，综合性价比分越高越值得继续跟踪 | T21: 板块量化：位置分越高越接近相对高位，综合性价比分越高越值得继续跟踪
A22: 板块 | B22: 样本 | C22: 权重 | D22: 8/31至10/13 | E22: 国庆后 | F22: 低点后反弹 | G22: 距高点 | H22: H1营收同比 | I22: H1利润池同比 | J22: 利润增长权重 | K22: TTM股息率 | L22: PE(TTM)加权 | M22: PB加权 | N22: 连续3年分红 | O22: 位置分 | P22: 相对位置 | Q22: 基本面分 | R22: 综合性价比分 | S22: 综合结论 | T22: 利润评分值
A23: 油气炼化 | B23: =COUNTIF('10.13行情明细'!$C$4:$C$103,$A23) -> 3 | C23: =SUMIF('10.13行情明细'!$C$4:$C$103,$A23,'10.13行情明细'!$E$4:$E$103) -> 0.03296 | D23: =SUMPRODUCT(--('10.13行情明细'!$C$4:$C$103=$A23),'10.13行情明细'!$E$4:$E$103,'10.13行情明细'!$I$4:$I$103)/$C23 -> 0.038151936 | E23: =SUMPRODUCT(--('10.13行情明细'!$C$4:$C$103=$A23),'10.13行情明细'!$E$4:$E$103,'10.13行情明细'!$K$4:$K$103)/$C23 -> 0.053153824 | F23: =SUMPRODUCT(--('10.13行情明细'!$C$4:$C$103=$A23),'10.13行情明细'!$E$4:$E$103,'10.13行情明细'!$N$4:$N$103)/$C23 -> 0.11906291 | G23: =SUMPRODUCT(--('10.13行情明细'!$C$4:$C$103=$A23),'10.13行情明细'!$E$4:$E$103,'10.13行情明细'!$Q$4:$Q$103)/$C23 -> -0.017745919 | H23: =SUMPRODUCT(--('10.13行情明细'!$C$4:$C$103=$A23),'10.13行情明细'!$E$4:$E$103,'10.13行情明细'!$R$4:$R$103)/$C23 -> 0.0829495 | I23: =SUMIF('10.13行情明细'!$C$4:$C$103,$A23,'10.13行情明细'!$S$4:$S$103)/SUMIF('10.13行情明细'!$C$4:$C$103,$A23,'10.13行情明细'!$T$4:$T$103)-1 -> 0.22244547 | J23: =SUMPRODUCT(--('10.13行情明细'!$C$4:$C$103=$A23),'10.13行情明细'!$E$4:$E$103,'10.13行情明细'!$W$4:$W$103)/$C23 -> 1 | K23: =SUMPRODUCT(--('10.13行情明细'!$C$4:$C$103=$A23),'10.13行情明细'!$E$4:$E$103,'10.13行情明细'!$Y$4:$Y$103)/SUMPRODUCT(--('10.13行情明细'!$C$4:$C$103=$A23),'10.13行情明细'!$E$4:$E$103,--('10.13行情明细'!$Y$4:$Y$103>0)) -> 0.038417146 | L23: =SUMPRODUCT(--('10.13行情明细'!$C$4:$C$103=$A23),'10.13行情明细'!$E$4:$E$103,'10.13行情明细'!$AC$4:$AC$103)/SUMPRODUCT(--('10.13行情明细'!$C$4:$C$103=$A23),'10.13行情明细'!$E$4:$E$103,'10.13行情明细'!$AD$4:$AD$103) -> 13.90818 | M23: =SUMPRODUCT(--('10.13行情明细'!$C$4:$C$103=$A23),'10.13行情明细'!$E$4:$E$103,'10.13行情明细'!$AE$4:$AE$103)/SUMPRODUCT(--('10.13行情明细'!$C$4:$C$103=$A23),'10.13行情明细'!$E$4:$E$103,'10.13行情明细'!$AF$4:$AF$103) -> 1.4064806 | N23: =SUMPRODUCT(--('10.13行情明细'!$C$4:$C$103=$A23),'10.13行情明细'!$E$4:$E$103,--('10.13行情明细'!$Z$4:$Z$103=3))/$C23 -> 1 | O23: =100*(20%*(RANK(D23,$D$23:$D$36,1)-1)/13+25%*(RANK(E23,$E$23:$E$36,1)-1)/13+15%*(RANK(F23,$F$23:$F$36,1)-1)/13+10%*(RANK(G23,$G$23:$G$36,1)-1)/13+15%*(RANK(K23,$K$23:$K$36,0)-1)/13+15%*(RANK(M23,$M$23:$M$36,1)-1)/13) -> 84.615385 | P23: =IF(O23>=65,"偏高",IF(O23>=55,"中高",IF(O23>=45,"中性",IF(O23>=35,"中低","偏低")))) -> 偏高 | Q23: =100*(20%*(RANK(H23,$H$23:$H$36,1)-1)/13+30%*(RANK(T23,$T$23:$T$36,1)-1)/13+15%*(RANK(J23,$J$23:$J$36,1)-1)/13+20%*(RANK(K23,$K$23:$K$36,1)-1)/13+15%*(RANK(N23,$N$23:$N$36,1)-1)/13) -> 62.692308 | R23: =55%*Q23+45%*(100-O23) -> 41.403846 | S23: =IF(R23>=65,"较高",IF(R23>=55,"中上",IF(R23>=45,"中性",IF(R23>=35,"中下","较低")))) -> 中下 | T23: =MAX(-50%,MIN(50%,I23)) -> 0.22244547
A24: 出版医药 | B24: =COUNTIF('10.13行情明细'!$C$4:$C$103,$A24) -> 6 | C24: =SUMIF('10.13行情明细'!$C$4:$C$103,$A24,'10.13行情明细'!$E$4:$E$103) -> 0.04219 | D24: =SUMPRODUCT(--('10.13行情明细'!$C$4:$C$103=$A24),'10.13行情明细'!$E$4:$E$103,'10.13行情明细'!$I$4:$I$103)/$C24 -> 0.052518668 | E24: =SUMPRODUCT(--('10.13行情明细'!$C$4:$C$103=$A24),'10.13行情明细'!$E$4:$E$103,'10.13行情明细'!$K$4:$K$103)/$C24 -> 0.053567747 | F24: =SUMPRODUCT(--('10.13行情明细'!$C$4:$C$103=$A24),'10.13行情明细'!$E$4:$E$103,'10.13行情明细'!$N$4:$N$103)/$C24 -> 0.089087707 | G24: =SUMPRODUCT(--('10.13行情明细'!$C$4:$C$103=$A24),'10.13行情明细'!$E$4:$E$103,'10.13行情明细'!$Q$4:$Q$103)/$C24 -> -0.023217961 | H24: =SUMPRODUCT(--('10.13行情明细'!$C$4:$C$103=$A24),'10.13行情明细'!$E$4:$E$103,'10.13行情明细'!$R$4:$R$103)/$C24 -> -0.09125548 | I24: =SUMIF('10.13行情明细'!$C$4:$C$103,$A24,'10.13行情明细'!$S$4:$S$103)/SUMIF('10.13行情明细'!$C$4:$C$103,$A24,'10.13行情明细'!$T$4:$T$103)-1 -> -0.18821392 | J24: =SUMPRODUCT(--('10.13行情明细'!$C$4:$C$103=$A24),'10.13行情明细'!$E$4:$E$103,'10.13行情明细'!$W$4:$W$103)/$C24 -> 0 | K24: =SUMPRODUCT(--('10.13行情明细'!$C$4:$C$103=$A24),'10.13行情明细'!$E$4:$E$103,'10.13行情明细'!$Y$4:$Y$103)/SUMPRODUCT(--('10.13行情明细'!$C$4:$C$103=$A24),'10.13行情明细'!$E$4:$E$103,--('10.13行情明细'!$Y$4:$Y$103>0)) -> 0.042656074 | L24: =SUMPRODUCT(--('10.13行情明细'!$C$4:$C$103=$A24),'10.13行情明细'!$E$4:$E$103,'10.13行情明细'!$AC$4:$AC$103)/SUMPRODUCT(--('10.13行情明细'!$C$4:$C$103=$A24),'10.13行情明细'!$E$4:$E$103,'10.13行情明细'!$AD$4:$AD$103) -> 18.348898 | M24: =SUMPRODUCT(--('10.13行情明细'!$C$4:$C$103=$A24),'10.13行情明细'!$E$4:$E$103,'10.13行情明细'!$AE$4:$AE$103)/SUMPRODUCT(--('10.13行情明细'!$C$4:$C$103=$A24),'10.13行情明细'!$E$4:$E$103,'10.13行情明细'!$AF$4:$AF$103) -> 1.0618369 | N24: =SUMPRODUCT(--('10.13行情明细'!$C$4:$C$103=$A24),'10.13行情明细'!$E$4:$E$103,--('10.13行情明细'!$Z$4:$Z$103=3))/$C24 -> 1 | O24: =100*(20%*(RANK(D24,$D$23:$D$36,1)-1)/13+25%*(RANK(E24,$E$23:$E$36,1)-1)/13+15%*(RANK(F24,$F$23:$F$36,1)-1)/13+10%*(RANK(G24,$G$23:$G$36,1)-1)/13+15%*(RANK(K24,$K$23:$K$36,0)-1)/13+15%*(RANK(M24,$M$23:$M$36,1)-1)/13) -> 81.153846 | P24: =IF(O24>=65,"偏高",IF(O24>=55,"中高",IF(O24>=45,"中性",IF(O24>=35,"中低","偏低")))) -> 偏高 | Q24: =100*(20%*(RANK(H24,$H$23:$H$36,1)-1)/13+30%*(RANK(T24,$T$23:$T$36,1)-1)/13+15%*(RANK(J24,$J$23:$J$36,1)-1)/13+20%*(RANK(K24,$K$23:$K$36,1)-1)/13+15%*(RANK(N24,$N$23:$N$36,1)-1)/13) -> 16.538462 | R24: =55%*Q24+45%*(100-O24) -> 17.576923 | S24: =IF(R24>=65,"较高",IF(R24>=55,"中上",IF(R24>=45,"中性",IF(R24>=35,"中下","较低")))) -> 较低 | T24: =MAX(-50%,MIN(50%,I24)) -> -0.18821392
A25: 交通物流 | B25: =COUNTIF('10.13行情明细'!$C$4:$C$103,$A25) -> 12 | C25: =SUMIF('10.13行情明细'!$C$4:$C$103,$A25,'10.13行情明细'!$E$4:$E$103) -> 0.14445 | D25: =SUMPRODUCT(--('10.13行情明细'!$C$4:$C$103=$A25),'10.13行情明细'!$E$4:$E$103,'10.13行情明细'!$I$4:$I$103)/$C25 -> 0.014062525 | E25: =SUMPRODUCT(--('10.13行情明细'!$C$4:$C$103=$A25),'10.13行情明细'!$E$4:$E$103,'10.13行情明细'!$K$4:$K$103)/$C25 -> 0.043831967 | F25: =SUMPRODUCT(--('10.13行情明细'!$C$4:$C$103=$A25),'10.13行情明细'!$E$4:$E$103,'10.13行情明细'!$N$4:$N$103)/$C25 -> 0.086706874 | G25: =SUMPRODUCT(--('10.13行情明细'!$C$4:$C$103=$A25),'10.13行情明细'!$E$4:$E$103,'10.13行情明细'!$Q$4:$Q$103)/$C25 -> -0.027687157 | H25: =SUMPRODUCT(--('10.13行情明细'!$C$4:$C$103=$A25),'10.13行情明细'!$E$4:$E$103,'10.13行情明细'!$R$4:$R$103)/$C25 -> 0.035968044 | I25: =SUMIF('10.13行情明细'!$C$4:$C$103,$A25,'10.13行情明细'!$S$4:$S$103)/SUMIF('10.13行情明细'!$C$4:$C$103,$A25,'10.13行情明细'!$T$4:$T$103)-1 -> -0.13284469 | J25: =SUMPRODUCT(--('10.13行情明细'!$C$4:$C$103=$A25),'10.13行情明细'!$E$4:$E$103,'10.13行情明细'!$W$4:$W$103)/$C25 -> 0.5037037 | K25: =SUMPRODUCT(--('10.13行情明细'!$C$4:$C$103=$A25),'10.13行情明细'!$E$4:$E$103,'10.13行情明细'!$Y$4:$Y$103)/SUMPRODUCT(--('10.13行情明细'!$C$4:$C$103=$A25),'10.13行情明细'!$E$4:$E$103,--('10.13行情明细'!$Y$4:$Y$103>0)) -> 0.045127794 | L25: =SUMPRODUCT(--('10.13行情明细'!$C$4:$C$103=$A25),'10.13行情明细'!$E$4:$E$103,'10.13行情明细'!$AC$4:$AC$103)/SUMPRODUCT(--('10.13行情明细'!$C$4:$C$103=$A25),'10.13行情明细'!$E$4:$E$103,'10.13行情明细'!$AD$4:$AD$103) -> 14.643639 | M25: =SUMPRODUCT(--('10.13行情明细'!$C$4:$C$103=$A25),'10.13行情明细'!$E$4:$E$103,'10.13行情明细'!$AE$4:$AE$103)/SUMPRODUCT(--('10.13行情明细'!$C$4:$C$103=$A25),'10.13行情明细'!$E$4:$E$103,'10.13行情明细'!$AF$4:$AF$103) -> 1.4681468 | N25: =SUMPRODUCT(--('10.13行情明细'!$C$4:$C$103=$A25),'10.13行情明细'!$E$4:$E$103,--('10.13行情明细'!$Z$4:$Z$103=3))/$C25 -> 1 | O25: =100*(20%*(RANK(D25,$D$23:$D$36,1)-1)/13+25%*(RANK(E25,$E$23:$E$36,1)-1)/13+15%*(RANK(F25,$F$23:$F$36,1)-1)/13+10%*(RANK(G25,$G$23:$G$36,1)-1)/13+15%*(RANK(K25,$K$23:$K$36,0)-1)/13+15%*(RANK(M25,$M$23:$M$36,1)-1)/13) -> 72.307692 | P25: =IF(O25>=65,"偏高",IF(O25>=55,"中高",IF(O25>=45,"中性",IF(O25>=35,"中低","偏低")))) -> 偏高 | Q25: =100*(20%*(RANK(H25,$H$23:$H$36,1)-1)/13+30%*(RANK(T25,$T$23:$T$36,1)-1)/13+15%*(RANK(J25,$J$23:$J$36,1)-1)/13+20%*(RANK(K25,$K$23:$K$36,1)-1)/13+15%*(RANK(N25,$N$23:$N$36,1)-1)/13) -> 40 | R25: =55%*Q25+45%*(100-O25) -> 34.461538 | S25: =IF(R25>=65,"较高",IF(R25>=55,"中上",IF(R25>=45,"中性",IF(R25>=35,"中下","较低")))) -> 较低 | T25: =MAX(-50%,MIN(50%,I25)) -> -0.13284469
A26: 钢铁 | B26: =COUNTIF('10.13行情明细'!$C$4:$C$103,$A26) -> 2 | C26: =SUMIF('10.13行情明细'!$C$4:$C$103,$A26,'10.13行情明细'!$E$4:$E$103) -> 0.02431 | D26: =SUMPRODUCT(--('10.13行情明细'!$C$4:$C$103=$A26),'10.13行情明细'!$E$4:$E$103,'10.13行情明细'!$I$4:$I$103)/$C26 -> -0.0021624933 | E26: =SUMPRODUCT(--('10.13行情明细'!$C$4:$C$103=$A26),'10.13行情明细'!$E$4:$E$103,'10.13行情明细'!$K$4:$K$103)/$C26 -> 0.041132116 | F26: =SUMPRODUCT(--('10.13行情明细'!$C$4:$C$103=$A26),'10.13行情明细'!$E$4:$E$103,'10.13行情明细'!$N$4:$N$103)/$C26 -> 0.082950191 | G26: =SUMPRODUCT(--('10.13行情明细'!$C$4:$C$103=$A26),'10.13行情明细'!$E$4:$E$103,'10.13行情明细'!$Q$4:$Q$103)/$C26 -> -0.053779958 | H26: =SUMPRODUCT(--('10.13行情明细'!$C$4:$C$103=$A26),'10.13行情明细'!$E$4:$E$103,'10.13行情明细'!$R$4:$R$103)/$C26 -> 0.065471907 | I26: =SUMIF('10.13行情明细'!$C$4:$C$103,$A26,'10.13行情明细'!$S$4:$S$103)/SUMIF('10.13行情明细'!$C$4:$C$103,$A26,'10.13行情明细'!$T$4:$T$103)-1 -> 0.11666997 | J26: =SUMPRODUCT(--('10.13行情明细'!$C$4:$C$103=$A26),'10.13行情明细'!$E$4:$E$103,'10.13行情明细'!$W$4:$W$103)/$C26 -> 0.60222131 | K26: =SUMPRODUCT(--('10.13行情明细'!$C$4:$C$103=$A26),'10.13行情明细'!$E$4:$E$103,'10.13行情明细'!$Y$4:$Y$103)/SUMPRODUCT(--('10.13行情明细'!$C$4:$C$103=$A26),'10.13行情明细'!$E$4:$E$103,--('10.13行情明细'!$Y$4:$Y$103>0)) -> 0.051590123 | L26: =SUMPRODUCT(--('10.13行情明细'!$C$4:$C$103=$A26),'10.13行情明细'!$E$4:$E$103,'10.13行情明细'!$AC$4:$AC$103)/SUMPRODUCT(--('10.13行情明细'!$C$4:$C$103=$A26),'10.13行情明细'!$E$4:$E$103,'10.13行情明细'!$AD$4:$AD$103) -> 12.49153 | M26: =SUMPRODUCT(--('10.13行情明细'!$C$4:$C$103=$A26),'10.13行情明细'!$E$4:$E$103,'10.13行情明细'!$AE$4:$AE$103)/SUMPRODUCT(--('10.13行情明细'!$C$4:$C$103=$A26),'10.13行情明细'!$E$4:$E$103,'10.13行情明细'!$AF$4:$AF$103) -> 1.501666 | N26: =SUMPRODUCT(--('10.13行情明细'!$C$4:$C$103=$A26),'10.13行情明细'!$E$4:$E$103,--('10.13行情明细'!$Z$4:$Z$103=3))/$C26 -> 1 | O26: =100*(20%*(RANK(D26,$D$23:$D$36,1)-1)/13+25%*(RANK(E26,$E$23:$E$36,1)-1)/13+15%*(RANK(F26,$F$23:$F$36,1)-1)/13+10%*(RANK(G26,$G$23:$G$36,1)-1)/13+15%*(RANK(K26,$K$23:$K$36,0)-1)/13+15%*(RANK(M26,$M$23:$M$36,1)-1)/13) -> 58.076923 | P26: =IF(O26>=65,"偏高",IF(O26>=55,"中高",IF(O26>=45,"中性",IF(O26>=35,"中低","偏低")))) -> 中高 | Q26: =100*(20%*(RANK(H26,$H$23:$H$36,1)-1)/13+30%*(RANK(T26,$T$23:$T$36,1)-1)/13+15%*(RANK(J26,$J$23:$J$36,1)-1)/13+20%*(RANK(K26,$K$23:$K$36,1)-1)/13+15%*(RANK(N26,$N$23:$N$36,1)-1)/13) -> 59.615385 | R26: =55%*Q26+45%*(100-O26) -> 51.653846 | S26: =IF(R26>=65,"较高",IF(R26>=55,"中上",IF(R26>=45,"中性",IF(R26>=35,"中下","较低")))) -> 中性 | T26: =MAX(-50%,MIN(50%,I26)) -> 0.11666997
A27: 消费 | B27: =COUNTIF('10.13行情明细'!$C$4:$C$103,$A27) -> 10 | C27: =SUMIF('10.13行情明细'!$C$4:$C$103,$A27,'10.13行情明细'!$E$4:$E$103) -> 0.09281 | D27: =SUMPRODUCT(--('10.13行情明细'!$C$4:$C$103=$A27),'10.13行情明细'!$E$4:$E$103,'10.13行情明细'!$I$4:$I$103)/$C27 -> 0.0081575518 | E27: =SUMPRODUCT(--('10.13行情明细'!$C$4:$C$103=$A27),'10.13行情明细'!$E$4:$E$103,'10.13行情明细'!$K$4:$K$103)/$C27 -> 0.034066303 | F27: =SUMPRODUCT(--('10.13行情明细'!$C$4:$C$103=$A27),'10.13行情明细'!$E$4:$E$103,'10.13行情明细'!$N$4:$N$103)/$C27 -> 0.068394024 | G27: =SUMPRODUCT(--('10.13行情明细'!$C$4:$C$103=$A27),'10.13行情明细'!$E$4:$E$103,'10.13行情明细'!$Q$4:$Q$103)/$C27 -> -0.055331631 | H27: =SUMPRODUCT(--('10.13行情明细'!$C$4:$C$103=$A27),'10.13行情明细'!$E$4:$E$103,'10.13行情明细'!$R$4:$R$103)/$C27 -> -0.016508038 | I27: =SUMIF('10.13行情明细'!$C$4:$C$103,$A27,'10.13行情明细'!$S$4:$S$103)/SUMIF('10.13行情明细'!$C$4:$C$103,$A27,'10.13行情明细'!$T$4:$T$103)-1 -> -0.047446429 | J27: =SUMPRODUCT(--('10.13行情明细'!$C$4:$C$103=$A27),'10.13行情明细'!$E$4:$E$103,'10.13行情明细'!$W$4:$W$103)/$C27 -> 0.38088568 | K27: =SUMPRODUCT(--('10.13行情明细'!$C$4:$C$103=$A27),'10.13行情明细'!$E$4:$E$103,'10.13行情明细'!$Y$4:$Y$103)/SUMPRODUCT(--('10.13行情明细'!$C$4:$C$103=$A27),'10.13行情明细'!$E$4:$E$103,--('10.13行情明细'!$Y$4:$Y$103>0)) -> 0.060758481 | L27: =SUMPRODUCT(--('10.13行情明细'!$C$4:$C$103=$A27),'10.13行情明细'!$E$4:$E$103,'10.13行情明细'!$AC$4:$AC$103)/SUMPRODUCT(--('10.13行情明细'!$C$4:$C$103=$A27),'10.13行情明细'!$E$4:$E$103,'10.13行情明细'!$AD$4:$AD$103) -> 17.155108 | M27: =SUMPRODUCT(--('10.13行情明细'!$C$4:$C$103=$A27),'10.13行情明细'!$E$4:$E$103,'10.13行情明细'!$AE$4:$AE$103)/SUMPRODUCT(--('10.13行情明细'!$C$4:$C$103=$A27),'10.13行情明细'!$E$4:$E$103,'10.13行情明细'!$AF$4:$AF$103) -> 1.8987577 | N27: =SUMPRODUCT(--('10.13行情明细'!$C$4:$C$103=$A27),'10.13行情明细'!$E$4:$E$103,--('10.13行情明细'!$Z$4:$Z$103=3))/$C27 -> 1 | O27: =100*(20%*(RANK(D27,$D$23:$D$36,1)-1)/13+25%*(RANK(E27,$E$23:$E$36,1)-1)/13+15%*(RANK(F27,$F$23:$F$36,1)-1)/13+10%*(RANK(G27,$G$23:$G$36,1)-1)/13+15%*(RANK(K27,$K$23:$K$36,0)-1)/13+15%*(RANK(M27,$M$23:$M$36,1)-1)/13) -> 56.153846 | P27: =IF(O27>=65,"偏高",IF(O27>=55,"中高",IF(O27>=45,"中性",IF(O27>=35,"中低","偏低")))) -> 中高 | Q27: =100*(20%*(RANK(H27,$H$23:$H$36,1)-1)/13+30%*(RANK(T27,$T$23:$T$36,1)-1)/13+15%*(RANK(J27,$J$23:$J$36,1)-1)/13+20%*(RANK(K27,$K$23:$K$36,1)-1)/13+15%*(RANK(N27,$N$23:$N$36,1)-1)/13) -> 50 | R27: =55%*Q27+45%*(100-O27) -> 47.230769 | S27: =IF(R27>=65,"较高",IF(R27>=55,"中上",IF(R27>=45,"中性",IF(R27>=35,"中下","较低")))) -> 中性 | T27: =MAX(-50%,MIN(50%,I27)) -> -0.047446429
A28: 保险金融 | B28: =COUNTIF('10.13行情明细'!$C$4:$C$103,$A28) -> 2 | C28: =SUMIF('10.13行情明细'!$C$4:$C$103,$A28,'10.13行情明细'!$E$4:$E$103) -> 0.01903 | D28: =SUMPRODUCT(--('10.13行情明细'!$C$4:$C$103=$A28),'10.13行情明细'!$E$4:$E$103,'10.13行情明细'!$I$4:$I$103)/$C28 -> 0.045170997 | E28: =SUMPRODUCT(--('10.13行情明细'!$C$4:$C$103=$A28),'10.13行情明细'!$E$4:$E$103,'10.13行情明细'!$K$4:$K$103)/$C28 -> 0.019393706 | F28: =SUMPRODUCT(--('10.13行情明细'!$C$4:$C$103=$A28),'10.13行情明细'!$E$4:$E$103,'10.13行情明细'!$N$4:$N$103)/$C28 -> 0.074735654 | G28: =SUMPRODUCT(--('10.13行情明细'!$C$4:$C$103=$A28),'10.13行情明细'!$E$4:$E$103,'10.13行情明细'!$Q$4:$Q$103)/$C28 -> -0.043984748 | H28: =SUMPRODUCT(--('10.13行情明细'!$C$4:$C$103=$A28),'10.13行情明细'!$E$4:$E$103,'10.13行情明细'!$R$4:$R$103)/$C28 -> 0.16119073 | I28: =SUMIF('10.13行情明细'!$C$4:$C$103,$A28,'10.13行情明细'!$S$4:$S$103)/SUMIF('10.13行情明细'!$C$4:$C$103,$A28,'10.13行情明细'!$T$4:$T$103)-1 -> 0.35458474 | J28: =SUMPRODUCT(--('10.13行情明细'!$C$4:$C$103=$A28),'10.13行情明细'!$E$4:$E$103,'10.13行情明细'!$W$4:$W$103)/$C28 -> 1 | K28: =SUMPRODUCT(--('10.13行情明细'!$C$4:$C$103=$A28),'10.13行情明细'!$E$4:$E$103,'10.13行情明细'!$Y$4:$Y$103)/SUMPRODUCT(--('10.13行情明细'!$C$4:$C$103=$A28),'10.13行情明细'!$E$4:$E$103,--('10.13行情明细'!$Y$4:$Y$103>0)) -> 0.053354258 | L28: =SUMPRODUCT(--('10.13行情明细'!$C$4:$C$103=$A28),'10.13行情明细'!$E$4:$E$103,'10.13行情明细'!$AC$4:$AC$103)/SUMPRODUCT(--('10.13行情明细'!$C$4:$C$103=$A28),'10.13行情明细'!$E$4:$E$103,'10.13行情明细'!$AD$4:$AD$103) -> 9.7231529 | M28: =SUMPRODUCT(--('10.13行情明细'!$C$4:$C$103=$A28),'10.13行情明细'!$E$4:$E$103,'10.13行情明细'!$AE$4:$AE$103)/SUMPRODUCT(--('10.13行情明细'!$C$4:$C$103=$A28),'10.13行情明细'!$E$4:$E$103,'10.13行情明细'!$AF$4:$AF$103) -> 1.343195 | N28: =SUMPRODUCT(--('10.13行情明细'!$C$4:$C$103=$A28),'10.13行情明细'!$E$4:$E$103,--('10.13行情明细'!$Z$4:$Z$103=3))/$C28 -> 1 | O28: =100*(20%*(RANK(D28,$D$23:$D$36,1)-1)/13+25%*(RANK(E28,$E$23:$E$36,1)-1)/13+15%*(RANK(F28,$F$23:$F$36,1)-1)/13+10%*(RANK(G28,$G$23:$G$36,1)-1)/13+15%*(RANK(K28,$K$23:$K$36,0)-1)/13+15%*(RANK(M28,$M$23:$M$36,1)-1)/13) -> 53.846154 | P28: =IF(O28>=65,"偏高",IF(O28>=55,"中高",IF(O28>=45,"中性",IF(O28>=35,"中低","偏低")))) -> 中性 | Q28: =100*(20%*(RANK(H28,$H$23:$H$36,1)-1)/13+30%*(RANK(T28,$T$23:$T$36,1)-1)/13+15%*(RANK(J28,$J$23:$J$36,1)-1)/13+20%*(RANK(K28,$K$23:$K$36,1)-1)/13+15%*(RANK(N28,$N$23:$N$36,1)-1)/13) -> 78.846154 | R28: =55%*Q28+45%*(100-O28) -> 64.134615 | S28: =IF(R28>=65,"较高",IF(R28>=55,"中上",IF(R28>=45,"中性",IF(R28>=35,"中下","较低")))) -> 中上 | T28: =MAX(-50%,MIN(50%,I28)) -> 0.35458474
A29: 建筑地产 | B29: =COUNTIF('10.13行情明细'!$C$4:$C$103,$A29) -> 5 | C29: =SUMIF('10.13行情明细'!$C$4:$C$103,$A29,'10.13行情明细'!$E$4:$E$103) -> 0.03596 | D29: =SUMPRODUCT(--('10.13行情明细'!$C$4:$C$103=$A29),'10.13行情明细'!$E$4:$E$103,'10.13行情明细'!$I$4:$I$103)/$C29 -> 0.017974836 | E29: =SUMPRODUCT(--('10.13行情明细'!$C$4:$C$103=$A29),'10.13行情明细'!$E$4:$E$103,'10.13行情明细'!$K$4:$K$103)/$C29 -> 0.020482791 | F29: =SUMPRODUCT(--('10.13行情明细'!$C$4:$C$103=$A29),'10.13行情明细'!$E$4:$E$103,'10.13行情明细'!$N$4:$N$103)/$C29 -> 0.065448407 | G29: =SUMPRODUCT(--('10.13行情明细'!$C$4:$C$103=$A29),'10.13行情明细'!$E$4:$E$103,'10.13行情明细'!$Q$4:$Q$103)/$C29 -> -0.034734229 | H29: =SUMPRODUCT(--('10.13行情明细'!$C$4:$C$103=$A29),'10.13行情明细'!$E$4:$E$103,'10.13行情明细'!$R$4:$R$103)/$C29 -> -0.056844664 | I29: =SUMIF('10.13行情明细'!$C$4:$C$103,$A29,'10.13行情明细'!$S$4:$S$103)/SUMIF('10.13行情明细'!$C$4:$C$103,$A29,'10.13行情明细'!$T$4:$T$103)-1 -> -0.21551861 | J29: =SUMPRODUCT(--('10.13行情明细'!$C$4:$C$103=$A29),'10.13行情明细'!$E$4:$E$103,'10.13行情明细'!$W$4:$W$103)/$C29 -> 0.44632925 | K29: =SUMPRODUCT(--('10.13行情明细'!$C$4:$C$103=$A29),'10.13行情明细'!$E$4:$E$103,'10.13行情明细'!$Y$4:$Y$103)/SUMPRODUCT(--('10.13行情明细'!$C$4:$C$103=$A29),'10.13行情明细'!$E$4:$E$103,--('10.13行情明细'!$Y$4:$Y$103>0)) -> 0.048226099 | L29: =SUMPRODUCT(--('10.13行情明细'!$C$4:$C$103=$A29),'10.13行情明细'!$E$4:$E$103,'10.13行情明细'!$AC$4:$AC$103)/SUMPRODUCT(--('10.13行情明细'!$C$4:$C$103=$A29),'10.13行情明细'!$E$4:$E$103,'10.13行情明细'!$AD$4:$AD$103) -> 7.8694142 | M29: =SUMPRODUCT(--('10.13行情明细'!$C$4:$C$103=$A29),'10.13行情明细'!$E$4:$E$103,'10.13行情明细'!$AE$4:$AE$103)/SUMPRODUCT(--('10.13行情明细'!$C$4:$C$103=$A29),'10.13行情明细'!$E$4:$E$103,'10.13行情明细'!$AF$4:$AF$103) -> 0.8816713 | N29: =SUMPRODUCT(--('10.13行情明细'!$C$4:$C$103=$A29),'10.13行情明细'!$E$4:$E$103,--('10.13行情明细'!$Z$4:$Z$103=3))/$C29 -> 1 | O29: =100*(20%*(RANK(D29,$D$23:$D$36,1)-1)/13+25%*(RANK(E29,$E$23:$E$36,1)-1)/13+15%*(RANK(F29,$F$23:$F$36,1)-1)/13+10%*(RANK(G29,$G$23:$G$36,1)-1)/13+15%*(RANK(K29,$K$23:$K$36,0)-1)/13+15%*(RANK(M29,$M$23:$M$36,1)-1)/13) -> 49.230769 | P29: =IF(O29>=65,"偏高",IF(O29>=55,"中高",IF(O29>=45,"中性",IF(O29>=35,"中低","偏低")))) -> 中性 | Q29: =100*(20%*(RANK(H29,$H$23:$H$36,1)-1)/13+30%*(RANK(T29,$T$23:$T$36,1)-1)/13+15%*(RANK(J29,$J$23:$J$36,1)-1)/13+20%*(RANK(K29,$K$23:$K$36,1)-1)/13+15%*(RANK(N29,$N$23:$N$36,1)-1)/13) -> 28.076923 | R29: =55%*Q29+45%*(100-O29) -> 38.288462 | S29: =IF(R29>=65,"较高",IF(R29>=55,"中上",IF(R29>=45,"中性",IF(R29>=35,"中下","较低")))) -> 中下 | T29: =MAX(-50%,MIN(50%,I29)) -> -0.21551861
A30: 银行 | B30: =COUNTIF('10.13行情明细'!$C$4:$C$103,$A30) -> 23 | C30: =SUMIF('10.13行情明细'!$C$4:$C$103,$A30,'10.13行情明细'!$E$4:$E$103) -> 0.22922 | D30: =SUMPRODUCT(--('10.13行情明细'!$C$4:$C$103=$A30),'10.13行情明细'!$E$4:$E$103,'10.13行情明细'!$I$4:$I$103)/$C30 -> 0.034532573 | E30: =SUMPRODUCT(--('10.13行情明细'!$C$4:$C$103=$A30),'10.13行情明细'!$E$4:$E$103,'10.13行情明细'!$K$4:$K$103)/$C30 -> 0.016112766 | F30: =SUMPRODUCT(--('10.13行情明细'!$C$4:$C$103=$A30),'10.13行情明细'!$E$4:$E$103,'10.13行情明细'!$N$4:$N$103)/$C30 -> 0.063515298 | G30: =SUMPRODUCT(--('10.13行情明细'!$C$4:$C$103=$A30),'10.13行情明细'!$E$4:$E$103,'10.13行情明细'!$Q$4:$Q$103)/$C30 -> -0.017881399 | H30: =SUMPRODUCT(--('10.13行情明细'!$C$4:$C$103=$A30),'10.13行情明细'!$E$4:$E$103,'10.13行情明细'!$R$4:$R$103)/$C30 -> 0.070372446 | I30: =SUMIF('10.13行情明细'!$C$4:$C$103,$A30,'10.13行情明细'!$S$4:$S$103)/SUMIF('10.13行情明细'!$C$4:$C$103,$A30,'10.13行情明细'!$T$4:$T$103)-1 -> 0.025920702 | J30: =SUMPRODUCT(--('10.13行情明细'!$C$4:$C$103=$A30),'10.13行情明细'!$E$4:$E$103,'10.13行情明细'!$W$4:$W$103)/$C30 -> 0.79255737 | K30: =SUMPRODUCT(--('10.13行情明细'!$C$4:$C$103=$A30),'10.13行情明细'!$E$4:$E$103,'10.13行情明细'!$Y$4:$Y$103)/SUMPRODUCT(--('10.13行情明细'!$C$4:$C$103=$A30),'10.13行情明细'!$E$4:$E$103,--('10.13行情明细'!$Y$4:$Y$103>0)) -> 0.046806509 | L30: =SUMPRODUCT(--('10.13行情明细'!$C$4:$C$103=$A30),'10.13行情明细'!$E$4:$E$103,'10.13行情明细'!$AC$4:$AC$103)/SUMPRODUCT(--('10.13行情明细'!$C$4:$C$103=$A30),'10.13行情明细'!$E$4:$E$103,'10.13行情明细'!$AD$4:$AD$103) -> 6.5226739 | M30: =SUMPRODUCT(--('10.13行情明细'!$C$4:$C$103=$A30),'10.13行情明细'!$E$4:$E$103,'10.13行情明细'!$AE$4:$AE$103)/SUMPRODUCT(--('10.13行情明细'!$C$4:$C$103=$A30),'10.13行情明细'!$E$4:$E$103,'10.13行情明细'!$AF$4:$AF$103) -> 0.62903368 | N30: =SUMPRODUCT(--('10.13行情明细'!$C$4:$C$103=$A30),'10.13行情明细'!$E$4:$E$103,--('10.13行情明细'!$Z$4:$Z$103=3))/$C30 -> 1 | O30: =100*(20%*(RANK(D30,$D$23:$D$36,1)-1)/13+25%*(RANK(E30,$E$23:$E$36,1)-1)/13+15%*(RANK(F30,$F$23:$F$36,1)-1)/13+10%*(RANK(G30,$G$23:$G$36,1)-1)/13+15%*(RANK(K30,$K$23:$K$36,0)-1)/13+15%*(RANK(M30,$M$23:$M$36,1)-1)/13) -> 45.384615 | P30: =IF(O30>=65,"偏高",IF(O30>=55,"中高",IF(O30>=45,"中性",IF(O30>=35,"中低","偏低")))) -> 中性 | Q30: =100*(20%*(RANK(H30,$H$23:$H$36,1)-1)/13+30%*(RANK(T30,$T$23:$T$36,1)-1)/13+15%*(RANK(J30,$J$23:$J$36,1)-1)/13+20%*(RANK(K30,$K$23:$K$36,1)-1)/13+15%*(RANK(N30,$N$23:$N$36,1)-1)/13) -> 53.846154 | R30: =55%*Q30+45%*(100-O30) -> 54.192308 | S30: =IF(R30>=65,"较高",IF(R30>=55,"中上",IF(R30>=45,"中性",IF(R30>=35,"中下","较低")))) -> 中性 | T30: =MAX(-50%,MIN(50%,I30)) -> 0.025920702
A31: 煤炭 | B31: =COUNTIF('10.13行情明细'!$C$4:$C$103,$A31) -> 15 | C31: =SUMIF('10.13行情明细'!$C$4:$C$103,$A31,'10.13行情明细'!$E$4:$E$103) -> 0.20149 | D31: =SUMPRODUCT(--('10.13行情明细'!$C$4:$C$103=$A31),'10.13行情明细'!$E$4:$E$103,'10.13行情明细'!$I$4:$I$103)/$C31 -> -0.082795179 | E31: =SUMPRODUCT(--('10.13行情明细'!$C$4:$C$103=$A31),'10.13行情明细'!$E$4:$E$103,'10.13行情明细'!$K$4:$K$103)/$C31 -> 0.018865395 | F31: =SUMPRODUCT(--('10.13行情明细'!$C$4:$C$103=$A31),'10.13行情明细'!$E$4:$E$103,'10.13行情明细'!$N$4:$N$103)/$C31 -> 0.054485955 | G31: =SUMPRODUCT(--('10.13行情明细'!$C$4:$C$103=$A31),'10.13行情明细'!$E$4:$E$103,'10.13行情明细'!$Q$4:$Q$103)/$C31 -> -0.10720766 | H31: =SUMPRODUCT(--('10.13行情明细'!$C$4:$C$103=$A31),'10.13行情明细'!$E$4:$E$103,'10.13行情明细'!$R$4:$R$103)/$C31 -> 0.074197791 | I31: =SUMIF('10.13行情明细'!$C$4:$C$103,$A31,'10.13行情明细'!$S$4:$S$103)/SUMIF('10.13行情明细'!$C$4:$C$103,$A31,'10.13行情明细'!$T$4:$T$103)-1 -> 0.18932638 | J31: =SUMPRODUCT(--('10.13行情明细'!$C$4:$C$103=$A31),'10.13行情明细'!$E$4:$E$103,'10.13行情明细'!$W$4:$W$103)/$C31 -> 0.91959899 | K31: =SUMPRODUCT(--('10.13行情明细'!$C$4:$C$103=$A31),'10.13行情明细'!$E$4:$E$103,'10.13行情明细'!$Y$4:$Y$103)/SUMPRODUCT(--('10.13行情明细'!$C$4:$C$103=$A31),'10.13行情明细'!$E$4:$E$103,--('10.13行情明细'!$Y$4:$Y$103>0)) -> 0.021337153 | L31: =SUMPRODUCT(--('10.13行情明细'!$C$4:$C$103=$A31),'10.13行情明细'!$E$4:$E$103,'10.13行情明细'!$AC$4:$AC$103)/SUMPRODUCT(--('10.13行情明细'!$C$4:$C$103=$A31),'10.13行情明细'!$E$4:$E$103,'10.13行情明细'!$AD$4:$AD$103) -> 23.616235 | M31: =SUMPRODUCT(--('10.13行情明细'!$C$4:$C$103=$A31),'10.13行情明细'!$E$4:$E$103,'10.13行情明细'!$AE$4:$AE$103)/SUMPRODUCT(--('10.13行情明细'!$C$4:$C$103=$A31),'10.13行情明细'!$E$4:$E$103,'10.13行情明细'!$AF$4:$AF$103) -> 1.5422681 | N31: =SUMPRODUCT(--('10.13行情明细'!$C$4:$C$103=$A31),'10.13行情明细'!$E$4:$E$103,--('10.13行情明细'!$Z$4:$Z$103=3))/$C31 -> 0.97315003 | O31: =100*(20%*(RANK(D31,$D$23:$D$36,1)-1)/13+25%*(RANK(E31,$E$23:$E$36,1)-1)/13+15%*(RANK(F31,$F$23:$F$36,1)-1)/13+10%*(RANK(G31,$G$23:$G$36,1)-1)/13+15%*(RANK(K31,$K$23:$K$36,0)-1)/13+15%*(RANK(M31,$M$23:$M$36,1)-1)/13) -> 41.923077 | P31: =IF(O31>=65,"偏高",IF(O31>=55,"中高",IF(O31>=45,"中性",IF(O31>=35,"中低","偏低")))) -> 中低 | Q31: =100*(20%*(RANK(H31,$H$23:$H$36,1)-1)/13+30%*(RANK(T31,$T$23:$T$36,1)-1)/13+15%*(RANK(J31,$J$23:$J$36,1)-1)/13+20%*(RANK(K31,$K$23:$K$36,1)-1)/13+15%*(RANK(N31,$N$23:$N$36,1)-1)/13) -> 53.846154 | R31: =55%*Q31+45%*(100-O31) -> 55.75 | S31: =IF(R31>=65,"较高",IF(R31>=55,"中上",IF(R31>=45,"中性",IF(R31>=35,"中下","较低")))) -> 中上 | T31: =MAX(-50%,MIN(50%,I31)) -> 0.18932638
A32: 公用环保 | B32: =COUNTIF('10.13行情明细'!$C$4:$C$103,$A32) -> 4 | C32: =SUMIF('10.13行情明细'!$C$4:$C$103,$A32,'10.13行情明细'!$E$4:$E$103) -> 0.02716 | D32: =SUMPRODUCT(--('10.13行情明细'!$C$4:$C$103=$A32),'10.13行情明细'!$E$4:$E$103,'10.13行情明细'!$I$4:$I$103)/$C32 -> 0.0048617049 | E32: =SUMPRODUCT(--('10.13行情明细'!$C$4:$C$103=$A32),'10.13行情明细'!$E$4:$E$103,'10.13行情明细'!$K$4:$K$103)/$C32 -> 0.016454004 | F32: =SUMPRODUCT(--('10.13行情明细'!$C$4:$C$103=$A32),'10.13行情明细'!$E$4:$E$103,'10.13行情明细'!$N$4:$N$103)/$C32 -> 0.045162121 | G32: =SUMPRODUCT(--('10.13行情明细'!$C$4:$C$103=$A32),'10.13行情明细'!$E$4:$E$103,'10.13行情明细'!$Q$4:$Q$103)/$C32 -> -0.033045451 | H32: =SUMPRODUCT(--('10.13行情明细'!$C$4:$C$103=$A32),'10.13行情明细'!$E$4:$E$103,'10.13行情明细'!$R$4:$R$103)/$C32 -> -0.035251444 | I32: =SUMIF('10.13行情明细'!$C$4:$C$103,$A32,'10.13行情明细'!$S$4:$S$103)/SUMIF('10.13行情明细'!$C$4:$C$103,$A32,'10.13行情明细'!$T$4:$T$103)-1 -> -0.06448493 | J32: =SUMPRODUCT(--('10.13行情明细'!$C$4:$C$103=$A32),'10.13行情明细'!$E$4:$E$103,'10.13行情明细'!$W$4:$W$103)/$C32 -> 0.34536082 | K32: =SUMPRODUCT(--('10.13行情明细'!$C$4:$C$103=$A32),'10.13行情明细'!$E$4:$E$103,'10.13行情明细'!$Y$4:$Y$103)/SUMPRODUCT(--('10.13行情明细'!$C$4:$C$103=$A32),'10.13行情明细'!$E$4:$E$103,--('10.13行情明细'!$Y$4:$Y$103>0)) -> 0.046932106 | L32: =SUMPRODUCT(--('10.13行情明细'!$C$4:$C$103=$A32),'10.13行情明细'!$E$4:$E$103,'10.13行情明细'!$AC$4:$AC$103)/SUMPRODUCT(--('10.13行情明细'!$C$4:$C$103=$A32),'10.13行情明细'!$E$4:$E$103,'10.13行情明细'!$AD$4:$AD$103) -> 13.492099 | M32: =SUMPRODUCT(--('10.13行情明细'!$C$4:$C$103=$A32),'10.13行情明细'!$E$4:$E$103,'10.13行情明细'!$AE$4:$AE$103)/SUMPRODUCT(--('10.13行情明细'!$C$4:$C$103=$A32),'10.13行情明细'!$E$4:$E$103,'10.13行情明细'!$AF$4:$AF$103) -> 1.3815722 | N32: =SUMPRODUCT(--('10.13行情明细'!$C$4:$C$103=$A32),'10.13行情明细'!$E$4:$E$103,--('10.13行情明细'!$Z$4:$Z$103=3))/$C32 -> 1 | O32: =100*(20%*(RANK(D32,$D$23:$D$36,1)-1)/13+25%*(RANK(E32,$E$23:$E$36,1)-1)/13+15%*(RANK(F32,$F$23:$F$36,1)-1)/13+10%*(RANK(G32,$G$23:$G$36,1)-1)/13+15%*(RANK(K32,$K$23:$K$36,0)-1)/13+15%*(RANK(M32,$M$23:$M$36,1)-1)/13) -> 40 | P32: =IF(O32>=65,"偏高",IF(O32>=55,"中高",IF(O32>=45,"中性",IF(O32>=35,"中低","偏低")))) -> 中低 | Q32: =100*(20%*(RANK(H32,$H$23:$H$36,1)-1)/13+30%*(RANK(T32,$T$23:$T$36,1)-1)/13+15%*(RANK(J32,$J$23:$J$36,1)-1)/13+20%*(RANK(K32,$K$23:$K$36,1)-1)/13+15%*(RANK(N32,$N$23:$N$36,1)-1)/13) -> 35.769231 | R32: =55%*Q32+45%*(100-O32) -> 46.673077 | S32: =IF(R32>=65,"较高",IF(R32>=55,"中上",IF(R32>=45,"中性",IF(R32>=35,"中下","较低")))) -> 中性 | T32: =MAX(-50%,MIN(50%,I32)) -> -0.06448493
A33: 建材家居 | B33: =COUNTIF('10.13行情明细'!$C$4:$C$103,$A33) -> 5 | C33: =SUMIF('10.13行情明细'!$C$4:$C$103,$A33,'10.13行情明细'!$E$4:$E$103) -> 0.0394 | D33: =SUMPRODUCT(--('10.13行情明细'!$C$4:$C$103=$A33),'10.13行情明细'!$E$4:$E$103,'10.13行情明细'!$I$4:$I$103)/$C33 -> -0.016709243 | E33: =SUMPRODUCT(--('10.13行情明细'!$C$4:$C$103=$A33),'10.13行情明细'!$E$4:$E$103,'10.13行情明细'!$K$4:$K$103)/$C33 -> -0.0050801164 | F33: =SUMPRODUCT(--('10.13行情明细'!$C$4:$C$103=$A33),'10.13行情明细'!$E$4:$E$103,'10.13行情明细'!$N$4:$N$103)/$C33 -> 0.067768818 | G33: =SUMPRODUCT(--('10.13行情明细'!$C$4:$C$103=$A33),'10.13行情明细'!$E$4:$E$103,'10.13行情明细'!$Q$4:$Q$103)/$C33 -> -0.079052156 | H33: =SUMPRODUCT(--('10.13行情明细'!$C$4:$C$103=$A33),'10.13行情明细'!$E$4:$E$103,'10.13行情明细'!$R$4:$R$103)/$C33 -> -0.096872851 | I33: =SUMIF('10.13行情明细'!$C$4:$C$103,$A33,'10.13行情明细'!$S$4:$S$103)/SUMIF('10.13行情明细'!$C$4:$C$103,$A33,'10.13行情明细'!$T$4:$T$103)-1 -> -0.22244924 | J33: =SUMPRODUCT(--('10.13行情明细'!$C$4:$C$103=$A33),'10.13行情明细'!$E$4:$E$103,'10.13行情明细'!$W$4:$W$103)/$C33 -> 0.29060914 | K33: =SUMPRODUCT(--('10.13行情明细'!$C$4:$C$103=$A33),'10.13行情明细'!$E$4:$E$103,'10.13行情明细'!$Y$4:$Y$103)/SUMPRODUCT(--('10.13行情明细'!$C$4:$C$103=$A33),'10.13行情明细'!$E$4:$E$103,--('10.13行情明细'!$Y$4:$Y$103>0)) -> 0.058444256 | L33: =SUMPRODUCT(--('10.13行情明细'!$C$4:$C$103=$A33),'10.13行情明细'!$E$4:$E$103,'10.13行情明细'!$AC$4:$AC$103)/SUMPRODUCT(--('10.13行情明细'!$C$4:$C$103=$A33),'10.13行情明细'!$E$4:$E$103,'10.13行情明细'!$AD$4:$AD$103) -> 13.099952 | M33: =SUMPRODUCT(--('10.13行情明细'!$C$4:$C$103=$A33),'10.13行情明细'!$E$4:$E$103,'10.13行情明细'!$AE$4:$AE$103)/SUMPRODUCT(--('10.13行情明细'!$C$4:$C$103=$A33),'10.13行情明细'!$E$4:$E$103,'10.13行情明细'!$AF$4:$AF$103) -> 1.5190635 | N33: =SUMPRODUCT(--('10.13行情明细'!$C$4:$C$103=$A33),'10.13行情明细'!$E$4:$E$103,--('10.13行情明细'!$Z$4:$Z$103=3))/$C33 -> 1 | O33: =100*(20%*(RANK(D33,$D$23:$D$36,1)-1)/13+25%*(RANK(E33,$E$23:$E$36,1)-1)/13+15%*(RANK(F33,$F$23:$F$36,1)-1)/13+10%*(RANK(G33,$G$23:$G$36,1)-1)/13+15%*(RANK(K33,$K$23:$K$36,0)-1)/13+15%*(RANK(M33,$M$23:$M$36,1)-1)/13) -> 32.307692 | P33: =IF(O33>=65,"偏高",IF(O33>=55,"中高",IF(O33>=45,"中性",IF(O33>=35,"中低","偏低")))) -> 偏低 | Q33: =100*(20%*(RANK(H33,$H$23:$H$36,1)-1)/13+30%*(RANK(T33,$T$23:$T$36,1)-1)/13+15%*(RANK(J33,$J$23:$J$36,1)-1)/13+20%*(RANK(K33,$K$23:$K$36,1)-1)/13+15%*(RANK(N33,$N$23:$N$36,1)-1)/13) -> 23.846154 | R33: =55%*Q33+45%*(100-O33) -> 43.576923 | S33: =IF(R33>=65,"较高",IF(R33>=55,"中上",IF(R33>=45,"中性",IF(R33>=35,"中下","较低")))) -> 中下 | T33: =MAX(-50%,MIN(50%,I33)) -> -0.22244924
A34: 有色矿业 | B34: =COUNTIF('10.13行情明细'!$C$4:$C$103,$A34) -> 5 | C34: =SUMIF('10.13行情明细'!$C$4:$C$103,$A34,'10.13行情明细'!$E$4:$E$103) -> 0.05131 | D34: =SUMPRODUCT(--('10.13行情明细'!$C$4:$C$103=$A34),'10.13行情明细'!$E$4:$E$103,'10.13行情明细'!$I$4:$I$103)/$C34 -> -0.10096503 | E34: =SUMPRODUCT(--('10.13行情明细'!$C$4:$C$103=$A34),'10.13行情明细'!$E$4:$E$103,'10.13行情明细'!$K$4:$K$103)/$C34 -> -0.0072402561 | F34: =SUMPRODUCT(--('10.13行情明细'!$C$4:$C$103=$A34),'10.13行情明细'!$E$4:$E$103,'10.13行情明细'!$N$4:$N$103)/$C34 -> 0.039051208 | G34: =SUMPRODUCT(--('10.13行情明细'!$C$4:$C$103=$A34),'10.13行情明细'!$E$4:$E$103,'10.13行情明细'!$Q$4:$Q$103)/$C34 -> -0.13810209 | H34: =SUMPRODUCT(--('10.13行情明细'!$C$4:$C$103=$A34),'10.13行情明细'!$E$4:$E$103,'10.13行情明细'!$R$4:$R$103)/$C34 -> 0.26030936 | I34: =SUMIF('10.13行情明细'!$C$4:$C$103,$A34,'10.13行情明细'!$S$4:$S$103)/SUMIF('10.13行情明细'!$C$4:$C$103,$A34,'10.13行情明细'!$T$4:$T$103)-1 -> 1.2041296 | J34: =SUMPRODUCT(--('10.13行情明细'!$C$4:$C$103=$A34),'10.13行情明细'!$E$4:$E$103,'10.13行情明细'!$W$4:$W$103)/$C34 -> 0.93510037 | K34: =SUMPRODUCT(--('10.13行情明细'!$C$4:$C$103=$A34),'10.13行情明细'!$E$4:$E$103,'10.13行情明细'!$Y$4:$Y$103)/SUMPRODUCT(--('10.13行情明细'!$C$4:$C$103=$A34),'10.13行情明细'!$E$4:$E$103,--('10.13行情明细'!$Y$4:$Y$103>0)) -> 0.019333147 | L34: =SUMPRODUCT(--('10.13行情明细'!$C$4:$C$103=$A34),'10.13行情明细'!$E$4:$E$103,'10.13行情明细'!$AC$4:$AC$103)/SUMPRODUCT(--('10.13行情明细'!$C$4:$C$103=$A34),'10.13行情明细'!$E$4:$E$103,'10.13行情明细'!$AD$4:$AD$103) -> 15.370548 | M34: =SUMPRODUCT(--('10.13行情明细'!$C$4:$C$103=$A34),'10.13行情明细'!$E$4:$E$103,'10.13行情明细'!$AE$4:$AE$103)/SUMPRODUCT(--('10.13行情明细'!$C$4:$C$103=$A34),'10.13行情明细'!$E$4:$E$103,'10.13行情明细'!$AF$4:$AF$103) -> 3.2080394 | N34: =SUMPRODUCT(--('10.13行情明细'!$C$4:$C$103=$A34),'10.13行情明细'!$E$4:$E$103,--('10.13行情明细'!$Z$4:$Z$103=3))/$C34 -> 0.75716235 | O34: =100*(20%*(RANK(D34,$D$23:$D$36,1)-1)/13+25%*(RANK(E34,$E$23:$E$36,1)-1)/13+15%*(RANK(F34,$F$23:$F$36,1)-1)/13+10%*(RANK(G34,$G$23:$G$36,1)-1)/13+15%*(RANK(K34,$K$23:$K$36,0)-1)/13+15%*(RANK(M34,$M$23:$M$36,1)-1)/13) -> 31.153846 | P34: =IF(O34>=65,"偏高",IF(O34>=55,"中高",IF(O34>=45,"中性",IF(O34>=35,"中低","偏低")))) -> 偏低 | Q34: =100*(20%*(RANK(H34,$H$23:$H$36,1)-1)/13+30%*(RANK(T34,$T$23:$T$36,1)-1)/13+15%*(RANK(J34,$J$23:$J$36,1)-1)/13+20%*(RANK(K34,$K$23:$K$36,1)-1)/13+15%*(RANK(N34,$N$23:$N$36,1)-1)/13) -> 63.846154 | R34: =55%*Q34+45%*(100-O34) -> 66.096154 | S34: =IF(R34>=65,"较高",IF(R34>=55,"中上",IF(R34>=45,"中性",IF(R34>=35,"中下","较低")))) -> 较高 | T34: =MAX(-50%,MIN(50%,I34)) -> 0.5
... A36: 化工 | B36: =COUNTIF('10.13行情明细'!$C$4:$C$103,$A36) -> 4 | C36: =SUMIF('10.13行情明细'!$C$4:$C$103,$A36,'10.13行情明细'!$E$4:$E$103) -> 0.03457 | D36: =SUMPRODUCT(--('10.13行情明细'!$C$4:$C$103=$A36),'10.13行情明细'!$E$4:$E$103,'10.13行情明细'!$I$4:$I$103)/$C36 -> -0.077568961 | E36: =SUMPRODUCT(--('10.13行情明细'!$C$4:$C$103=$A36),'10.13行情明细'!$E$4:$E$103,'10.13行情明细'!$K$4:$K$103)/$C36 -> 0.0062391134 | F36: =SUMPRODUCT(--('10.13行情明细'!$C$4:$C$103=$A36),'10.13行情明细'!$E$4:$E$103,'10.13行情明细'!$N$4:$N$103)/$C36 -> 0.035122008 | G36: =SUMPRODUCT(--('10.13行情明细'!$C$4:$C$103=$A36),'10.13行情明细'!$E$4:$E$103,'10.13行情明细'!$Q$4:$Q$103)/$C36 -> -0.099567902 | H36: =SUMPRODUCT(--('10.13行情明细'!$C$4:$C$103=$A36),'10.13行情明细'!$E$4:$E$103,'10.13行情明细'!$R$4:$R$103)/$C36 -> 0.0027542189 | I36: =SUMIF('10.13行情明细'!$C$4:$C$103,$A36,'10.13行情明细'!$S$4:$S$103)/SUMIF('10.13行情明细'!$C$4:$C$103,$A36,'10.13行情明细'!$T$4:$T$103)-1 -> -0.14834101 | J36: =SUMPRODUCT(--('10.13行情明细'!$C$4:$C$103=$A36),'10.13行情明细'!$E$4:$E$103,'10.13行情明细'!$W$4:$W$103)/$C36 -> 0.26786231 | K36: =SUMPRODUCT(--('10.13行情明细'!$C$4:$C$103=$A36),'10.13行情明细'!$E$4:$E$103,'10.13行情明细'!$Y$4:$Y$103)/SUMPRODUCT(--('10.13行情明细'!$C$4:$C$103=$A36),'10.13行情明细'!$E$4:$E$103,--('10.13行情明细'!$Y$4:$Y$103>0)) -> 0.047551736 | L36: =SUMPRODUCT(--('10.13行情明细'!$C$4:$C$103=$A36),'10.13行情明细'!$E$4:$E$103,'10.13行情明细'!$AC$4:$AC$103)/SUMPRODUCT(--('10.13行情明细'!$C$4:$C$103=$A36),'10.13行情明细'!$E$4:$E$103,'10.13行情明细'!$AD$4:$AD$103) -> 21.238409 | M36: =SUMPRODUCT(--('10.13行情明细'!$C$4:$C$103=$A36),'10.13行情明细'!$E$4:$E$103,'10.13行情明细'!$AE$4:$AE$103)/SUMPRODUCT(--('10.13行情明细'!$C$4:$C$103=$A36),'10.13行情明细'!$E$4:$E$103,'10.13行情明细'!$AF$4:$AF$103) -> 1.4817096 | N36: =SUMPRODUCT(--('10.13行情明细'!$C$4:$C$103=$A36),'10.13行情明细'!$E$4:$E$103,--('10.13行情明细'!$Z$4:$Z$103=3))/$C36 -> 0.74515476 | O36: =100*(20%*(RANK(D36,$D$23:$D$36,1)-1)/13+25%*(RANK(E36,$E$23:$E$36,1)-1)/13+15%*(RANK(F36,$F$23:$F$36,1)-1)/13+10%*(RANK(G36,$G$23:$G$36,1)-1)/13+15%*(RANK(K36,$K$23:$K$36,0)-1)/13+15%*(RANK(M36,$M$23:$M$36,1)-1)/13) -> 24.615385 | P36: =IF(O36>=65,"偏高",IF(O36>=55,"中高",IF(O36>=45,"中性",IF(O36>=35,"中低","偏低")))) -> 偏低 | Q36: =100*(20%*(RANK(H36,$H$23:$H$36,1)-1)/13+30%*(RANK(T36,$T$23:$T$36,1)-1)/13+15%*(RANK(J36,$J$23:$J$36,1)-1)/13+20%*(RANK(K36,$K$23:$K$36,1)-1)/13+15%*(RANK(N36,$N$23:$N$36,1)-1)/13) -> 30 | R36: =55%*Q36+45%*(100-O36) -> 50.423077 | S36: =IF(R36>=65,"较高",IF(R36>=55,"中上",IF(R36>=45,"中性",IF(R36>=35,"中下","较低")))) -> 中性 | T36: =MAX(-50%,MIN(50%,I36)) -> -0.14834101
A37: 中证红利整体 | B37: =SUM(B23:B36) -> 100 | C37: =SUM(C23:C36) -> 1.00004 | D37: =$I$5 -> -0.016424117 | E37: =IF(OR($C$5="",$C$5<=0),"",$C$5/'10.13行情明细'!C131-1) -> 0.023876185 | F37: =$G$5 -> 0.044273715 | G37: =IF(OR($C$5="",$C$5<=0),"",$C$5/MAX('10.13行情明细'!$D$110:$D$135)-1) -> -0.027935722 | H37: ='10.13方法'!B8 -> 0.045555386 | I37: ='10.13方法'!B9 -> 0.062795209 | J37: ='10.13方法'!B10 -> 0.58 | K37: =SUMPRODUCT('10.13行情明细'!$E$4:$E$103,'10.13行情明细'!$Y$4:$Y$103)/SUMPRODUCT('10.13行情明细'!$E$4:$E$103,--('10.13行情明细'!$Y$4:$Y$103>0)) -> 0.042290248 | L37: =SUMPRODUCT('10.13行情明细'!$E$4:$E$103,'10.13行情明细'!$AC$4:$AC$103)/SUMPRODUCT('10.13行情明细'!$E$4:$E$103,'10.13行情明细'!$AD$4:$AD$103) -> 14.457495 | M37: =SUMPRODUCT('10.13行情明细'!$E$4:$E$103,'10.13行情明细'!$AE$4:$AE$103)/SUMPRODUCT('10.13行情明细'!$E$4:$E$103,'10.13行情明细'!$AF$4:$AF$103) -> 1.3697985 | N37: =SUMPRODUCT('10.13行情明细'!$E$4:$E$103,--('10.13行情明细'!$Z$4:$Z$103=3))/SUM('10.13行情明细'!$E$4:$E$103) -> 0.97332107

Sheet 100只成分明细
A1: 中证红利（000922）2026年半年报成分股明细
A2: 成分权重日期：2026-07-31｜财报期间：2026H1 vs 2025H1｜金额单位：亿元｜蓝字为外部导入数据，黑字为公式
A3: 代码 | B3: 名称 | C3: 分析板块 | D3: 指数权重 | E3: 营业收入26H1 | F3: 营业收入25H1 | G3: 营收同比 | H3: 归母净利润26H1 | I3: 归母净利润25H1 | J3: 归母净利润同比 | K3: 利润增量 | L3: 扣非净利润26H1 | M3: 扣非净利润25H1 | N3: 扣非同比 | O3: 经营现金流26H1 | P3: 经营现金流25H1 | Q3: 经营现金流同比 | R3: 正利润可比 | S3: 利润同比截尾 | T3: 权重×截尾增速 | U3: 财务来源
A4: 000090 | B4: 天健集团 | C4: 建筑 | D4: 0.00421 | E4: 65.890535 | F4: 62.623371 | G4: =IFERROR(E4/F4-1,"") -> 0.052171636 | H4: -3.3289642 | I4: 0.41423675 | J4: =IFERROR(H4/I4-1,"") -> -9.0363806 | K4: =H4-I4 -> -3.7432009 | L4: -3.5603691 | M4: 0.2217061 | N4: =IFERROR(L4/M4-1,"") -> -17.058958 | O4: -1.0316958 | P4: -9.7974394 | Q4: =IFERROR(O4/P4-1,"") -> -0.8946974 | R4: =IF(AND(H4>0,I4>0),1,0) -> 0 | S4: =IF(R4=1,MIN(MAX(J4,-50%),50%),"") | T4: =IF(S4="","",D4*S4) | U4: https://emweb.securities.eastmoney.com/PC_HSF10/FinanceAnalysis/Index?type=web&code=SZ000090
A5: 000157 | B5: 中联重科 | C5: 其他 | D5: 0.007 | E5: 271.35031 | F5: 248.54632 | G5: =IFERROR(E5/F5-1,"") -> 0.091749452 | H5: 21.021891 | I5: 27.647786 | J5: =IFERROR(H5/I5-1,"") -> -0.23965372 | K5: =H5-I5 -> -6.6258947 | L5: 8.312838 | M5: 19.251679 | N5: =IFERROR(L5/M5-1,"") -> -0.56820192 | O5: 24.19537 | P5: 17.517803 | Q5: =IFERROR(O5/P5-1,"") -> 0.38118751 | R5: =IF(AND(H5>0,I5>0),1,0) -> 1 | S5: =IF(R5=1,MIN(MAX(J5,-50%),50%),"") -> -0.23965372 | T5: =IF(S5="","",D5*S5) -> -0.001677576 | U5: https://emweb.securities.eastmoney.com/PC_HSF10/FinanceAnalysis/Index?type=web&code=SZ000157
A6: 000408 | B6: 藏格矿业 | C6: 有色矿业 | D6: 0.01246 | E6: 20.64878 | F6: 16.781419 | G6: =IFERROR(E6/F6-1,"") -> 0.23045494 | H6: 36.380814 | I6: 18.002052 | J6: =IFERROR(H6/I6-1,"") -> 1.0209259 | K6: =H6-I6 -> 18.378761 | L6: 37.056932 | M6: 18.08398 | N6: =IFERROR(L6/M6-1,"") -> 1.049158 | O6: 9.8415792 | P6: 8.3407623 | Q6: =IFERROR(O6/P6-1,"") -> 0.17993761 | R6: =IF(AND(H6>0,I6>0),1,0) -> 1 | S6: =IF(R6=1,MIN(MAX(J6,-50%),50%),"") -> 0.5 | T6: =IF(S6="","",D6*S6) -> 0.00623 | U6: https://emweb.securities.eastmoney.com/PC_HSF10/FinanceAnalysis/Index?type=web&code=SZ000408
A7: 000429 | B7: 粤高速A | C7: 交通运输 | D7: 0.01043 | E7: 21.18953 | F7: 21.179628 | G7: =IFERROR(E7/F7-1,"") -> 0.00046754072 | H7: 8.5012926 | I7: 10.571529 | J7: =IFERROR(H7/I7-1,"") -> -0.19583128 | K7: =H7-I7 -> -2.070236 | L7: 8.4688885 | M7: 7.9905938 | N7: =IFERROR(L7/M7-1,"") -> 0.059857214 | O7: 17.085762 | P7: 18.976668 | Q7: =IFERROR(O7/P7-1,"") -> -0.09964371 | R7: =IF(AND(H7>0,I7>0),1,0) -> 1 | S7: =IF(R7=1,MIN(MAX(J7,-50%),50%),"") -> -0.19583128 | T7: =IF(S7="","",D7*S7) -> -0.0020425203 | U7: https://emweb.securities.eastmoney.com/PC_HSF10/FinanceAnalysis/Index?type=web&code=SZ000429
A8: 000651 | B8: 格力电器 | C8: 其他 | D8: 0.01143 | E8: 896.72955 | F8: 976.19383 | G8: =IFERROR(E8/F8-1,"") -> -0.08140215 | H8: 132.77591 | I8: 144.12407 | J8: =IFERROR(H8/I8-1,"") -> -0.078738841 | K8: =H8-I8 -> -11.348162 | L8: 127.06673 | M8: 139.46409 | N8: =IFERROR(L8/M8-1,"") -> -0.088892877 | O8: 188.08832 | P8: 283.28562 | Q8: =IFERROR(O8/P8-1,"") -> -0.33604705 | R8: =IF(AND(H8>0,I8>0),1,0) -> 1 | S8: =IF(R8=1,MIN(MAX(J8,-50%),50%),"") -> -0.078738841 | T8: =IF(S8="","",D8*S8) -> -0.00089998495 | U8: https://emweb.securities.eastmoney.com/PC_HSF10/FinanceAnalysis/Index?type=web&code=SZ000651
A9: 000672 | B9: 上峰材料 | C9: 水泥建材 | D9: 0.01145 | E9: 18.385163 | F9: 22.723334 | G9: =IFERROR(E9/F9-1,"") -> -0.19091262 | H9: 13.640648 | I9: 2.4686948 | J9: =IFERROR(H9/I9-1,"") -> 4.5254493 | K9: =H9-I9 -> 11.171953 | L9: 1.5075244 | M9: 2.8200207 | N9: =IFERROR(L9/M9-1,"") -> -0.46542079 | O9: 3.1147397 | P9: 4.7554007 | Q9: =IFERROR(O9/P9-1,"") -> -0.34501004 | R9: =IF(AND(H9>0,I9>0),1,0) -> 1 | S9: =IF(R9=1,MIN(MAX(J9,-50%),50%),"") -> 0.5 | T9: =IF(S9="","",D9*S9) -> 0.005725 | U9: https://emweb.securities.eastmoney.com/PC_HSF10/FinanceAnalysis/Index?type=web&code=SZ000672
A10: 000895 | B10: 双汇发展 | C10: 其他 | D10: 0.01017 | E10: 281.8435 | F10: 285.0309 | G10: =IFERROR(E10/F10-1,"") -> -0.011182618 | H10: 23.055896 | I10: 23.231623 | J10: =IFERROR(H10/I10-1,"") -> -0.0075641206 | K10: =H10-I10 -> -0.1757268 | L10: 22.86357 | M10: 22.15104 | N10: =IFERROR(L10/M10-1,"") -> 0.03216689 | O10: 16.16936 | P10: 29.142047 | Q10: =IFERROR(O10/P10-1,"") -> -0.44515359 | R10: =IF(AND(H10>0,I10>0),1,0) -> 1 | S10: =IF(R10=1,MIN(MAX(J10,-50%),50%),"") -> -0.0075641206 | T10: =IF(S10="","",D10*S10) -> -7.6927106e-05 | U10: https://emweb.securities.eastmoney.com/PC_HSF10/FinanceAnalysis/Index?type=web&code=SZ000895
A11: 000933 | B11: 神火股份 | C11: 有色矿业 | D11: 0.00853 | E11: 247.90858 | F11: 204.28475 | G11: =IFERROR(E11/F11-1,"") -> 0.21354421 | H11: 47.813773 | I11: 19.044568 | J11: =IFERROR(H11/I11-1,"") -> 1.5106252 | K11: =H11-I11 -> 28.769205 | L11: 47.853112 | M11: 20.100692 | N11: =IFERROR(L11/M11-1,"") -> 1.3806699 | O11: 72.004561 | P11: 44.368336 | Q11: =IFERROR(O11/P11-1,"") -> 0.62288171 | R11: =IF(AND(H11>0,I11>0),1,0) -> 1 | S11: =IF(R11=1,MIN(MAX(J11,-50%),50%),"") -> 0.5 | T11: =IF(S11="","",D11*S11) -> 0.004265 | U11: https://emweb.securities.eastmoney.com/PC_HSF10/FinanceAnalysis/Index?type=web&code=SZ000933
A12: 000983 | B12: 山西焦煤 | C12: 煤炭 | D12: 0.01391 | E12: 180.28068 | F12: 180.53293 | G12: =IFERROR(E12/F12-1,"") -> -0.0013972352 | H12: 12.369695 | I12: 10.136957 | J12: =IFERROR(H12/I12-1,"") -> 0.22025722 | K12: =H12-I12 -> 2.232738 | L12: 10.753406 | M12: 10.265937 | N12: =IFERROR(L12/M12-1,"") -> 0.047484143 | O12: 16.013416 | P12: 33.272869 | Q12: =IFERROR(O12/P12-1,"") -> -0.5187245 | R12: =IF(AND(H12>0,I12>0),1,0) -> 1 | S12: =IF(R12=1,MIN(MAX(J12,-50%),50%),"") -> 0.22025722 | T12: =IF(S12="","",D12*S12) -> 0.0030637779 | U12: https://emweb.securities.eastmoney.com/PC_HSF10/FinanceAnalysis/Index?type=web&code=SZ000983
A13: 002043 | B13: 兔宝宝 | C13: 水泥建材 | D13: 0.00922 | E13: 42.665159 | F13: 36.340756 | G13: =IFERROR(E13/F13-1,"") -> 0.17403058 | H13: 2.4730882 | I13: 2.6784711 | J13: =IFERROR(H13/I13-1,"") -> -0.076679145 | K13: =H13-I13 -> -0.20538287 | L13: 2.6080279 | M13: 2.378151 | N13: =IFERROR(L13/M13-1,"") -> 0.09666202 | O13: 2.1296853 | P13: 1.0737049 | Q13: =IFERROR(O13/P13-1,"") -> 0.98349214 | R13: =IF(AND(H13>0,I13>0),1,0) -> 1 | S13: =IF(R13=1,MIN(MAX(J13,-50%),50%),"") -> -0.076679145 | T13: =IF(S13="","",D13*S13) -> -0.00070698171 | U13: https://emweb.securities.eastmoney.com/PC_HSF10/FinanceAnalysis/Index?type=web&code=SZ002043
A14: 002154 | B14: 报喜鸟 | C14: 其他 | D14: 0.00477 | E14: 26.289292 | F14: 23.907718 | G14: =IFERROR(E14/F14-1,"") -> 0.099615278 | H14: 2.9134168 | I14: 1.9723263 | J14: =IFERROR(H14/I14-1,"") -> 0.47714748 | K14: =H14-I14 -> 0.94109051 | L14: 2.0287818 | M14: 1.6215576 | N14: =IFERROR(L14/M14-1,"") -> 0.25113147 | O14: 3.0611351 | P14: 0.94649802 | Q14: =IFERROR(O14/P14-1,"") -> 2.2341695 | R14: =IF(AND(H14>0,I14>0),1,0) -> 1 | S14: =IF(R14=1,MIN(MAX(J14,-50%),50%),"") -> 0.47714748 | T14: =IF(S14="","",D14*S14) -> 0.0022759935 | U14: https://emweb.securities.eastmoney.com/PC_HSF10/FinanceAnalysis/Index?type=web&code=SZ002154
A15: 002233 | B15: 塔牌集团 | C15: 水泥建材 | D15: 0.00653 | E15: 17.416449 | F15: 20.56248 | G15: =IFERROR(E15/F15-1,"") -> -0.15299864 | H15: 2.1945048 | I15: 4.3539688 | J15: =IFERROR(H15/I15-1,"") -> -0.495976 | K15: =H15-I15 -> -2.159464 | L15: 1.5000975 | M15: 2.418596 | N15: =IFERROR(L15/M15-1,"") -> -0.37976518 | O15: 1.7094921 | P15: 1.3498505 | Q15: =IFERROR(O15/P15-1,"") -> 0.26643067 | R15: =IF(AND(H15>0,I15>0),1,0) -> 1 | S15: =IF(R15=1,MIN(MAX(J15,-50%),50%),"") -> -0.495976 | T15: =IF(S15="","",D15*S15) -> -0.0032387233 | U15: https://emweb.securities.eastmoney.com/PC_HSF10/FinanceAnalysis/Index?type=web&code=SZ002233
... A103: 920599 | B103: 同力股份 | C103: 其他 | D103: 0.00422 | E103: 35.533178 | F103: 31.688394 | G103: =IFERROR(E103/F103-1,"") -> 0.12133099 | H103: 4.0558142 | I103: 3.2122719 | J103: =IFERROR(H103/I103-1,"") -> 0.26259988 | K103: =H103-I103 -> 0.84354221 | L103: 3.9551999 | M103: 3.175479 | N103: =IFERROR(L103/M103-1,"") -> 0.24554432 | O103: 5.1229508 | P103: -6.3166048 | Q103: =IFERROR(O103/P103-1,"") -> -1.8110292 | R103: =IF(AND(H103>0,I103>0),1,0) -> 1 | S103: =IF(R103=1,MIN(MAX(J103,-50%),50%),"") -> 0.26259988 | T103: =IF(S103="","",D103*S103) -> 0.0011081715 | U103: https://emweb.securities.eastmoney.com/PC_HSF10/FinanceAnalysis/Index?type=web&code=BJ920599

Sheet 检查
A1: 数据与模型检查
A3: 检查项 | B3: 实际值 | C3: 期望值 | D3: 差异 | E3: 容差 | F3: 状态 | G3: 说明
A4: 成分股数量 | B4: =COUNTA('100只成分明细'!$A$4:$A$103) -> 100 | C4: 100 | D4: =B4-C4 -> 0 | E4: 0 | F4: =IF(ABS(D4)<=E4,"OK","检查") -> OK | G4: 应为100只成分
A5: 权重合计 | B5: =SUM('100只成分明细'!$D$4:$D$103) -> 1.00004 | C5: 1 | D5: =B5-C5 -> 4e-05 | E5: 0.001 | F5: =IF(ABS(D5)<=E5,"OK","检查") -> OK | G5: 权重四舍五入允许0.1%误差
A6: 缺失半年报 | B6: =COUNTBLANK('100只成分明细'!$H$4:$H$103) -> 0 | C6: 0 | D6: =B6-C6 -> 0 | E6: 0 | F6: =IF(ABS(D6)<=E6,"OK","检查") -> OK | G6: 100家公司均已披露
A7: 利润增长公司数 | B7: =COUNTIF('100只成分明细'!$K$4:$K$103,">0") -> 58 | C7: 58 | D7: =B7-C7 -> 0 | E7: 0 | F7: =IF(ABS(D7)<=E7,"OK","检查") -> OK | G7: 利润同比大于0的公司数
A9: 10月13日新增检查 | B9: 10月13日新增检查 | C9: 10月13日新增检查 | D9: 10月13日新增检查 | E9: 10月13日新增检查 | F9: 10月13日新增检查 | G9: 10月13日新增检查
A10: 检查项 | B10: 实际值 | C10: 期望值 | D10: 差异 | E10: 容差 | F10: 状态 | G10: 说明
A11: 行情样本数 | B11: =COUNTA('10.13行情明细'!$A$4:$A$103) -> 100 | C11: 100 | D11: =B11-C11 -> 0 | E11: 0 | F11: =IF(ABS(D11)<=E11,"OK","检查") -> OK | G11: 应为100只成分
A12: 行情权重合计 | B12: =SUM('10.13行情明细'!$E$4:$E$103) -> 1.00004 | C12: 1 | D12: =B12-C12 -> 4e-05 | E12: 0.001 | F12: =IF(ABS(D12)<=E12,"OK","检查") -> OK | G12: 权重四舍五入允许0.1%误差
A13: 缺失10/13收盘 | B13: =COUNTBLANK('10.13行情明细'!$H$4:$H$103) -> 0 | C13: 0 | D13: =B13-C13 -> 0 | E13: 0 | F13: =IF(ABS(D13)<=E13,"OK","检查") -> OK | G13: 100只股票均应有收盘价
A14: 板块权重合计 | B14: =SUM(结论!$C$23:$C$36) -> 1.00004 | C14: 1 | D14: =B14-C14 -> 4e-05 | E14: 0.001 | F14: =IF(ABS(D14)<=E14,"OK","检查") -> OK | G14: 14个分组应覆盖全部成分
A15: 实际低点进入模型底部区间 | B15: =IF(AND(结论!$E$5>=MIN(结论!$B$10:$B$12),结论!$E$5<=MAX(结论!$B$10:$B$12)),1,0) -> 1 | C15: 1 | D15: =B15-C15 -> 0 | E15: 0 | F15: =IF(ABS(D15)<=E15,"OK","检查") -> OK | G15: 5386.04应落入5332—5420区间

Sheet 来源
A1: 来源与口径
A3: 来源ID | B3: 项目 | C3: 期间/日期 | D3: 来源名称 | E3: URL或路径 | F3: 用途与备注
A4: S1 | B4: 指数编制方法 | C4: V1.3 | D4: 中证指数有限公司 | E4: https://oss-ch.csindex.com.cn/static/html/csindex/public/uploads/indices/detail/files/zh_CN/20231208175433-000922_Index_Methodology_cn.pdf | F4: 100只样本、股息率加权、单只上限等
A5: S2 | B5: 成分与权重 | C5: 2026-07-31 | D5: 中证指数有限公司（经公开接口） | E5: https://www.csindex.com.cn/#/indices/family/detail?indexCode=000922 | F5: 100只成分权重，合计100.004%系小数四舍五入
A6: S3 | B6: 公司半年报财务摘要 | C6: 2026H1/2025H1 | D6: 东方财富F10 | E6: 详见“100只成分明细”U列 | F6: 营业收入、归母净利润、扣非净利润、经营现金流
A7: S4 | B7: 沪市半年报整体综述 | C7: 2026-08-30 | D7: 上海证券交易所 | E7: https://www.sse.com.cn/aboutus/mediacenter/hotandd/c/c_20260830_10830362.shtml | F7: 用于交叉验证披露完成度与市场背景
A8: S5 | B8: 上一期视频理念 | C8: 2026-08 | D8: 用户提供 | E8: C:/Users/Administrator/Desktop/8月全新工作流文件夹/8.17红利指数/红利指数.txt | F8: 5100/6100技术通道与约4.3%趋势斜率
A10: 关键限制：半年报不是全年盈利；指数按股息率加权且12月定期调样；当前价格已部分反映半年报预期。故本表把“历史技术通道”和“等估值基本面修正”并列展示，不把二者重复相乘，也不把结果当作保证触及的点位。
A12: 10月13日新增来源 | B12: 10月13日新增来源 | C12: 10月13日新增来源 | D12: 10月13日新增来源 | E12: 10月13日新增来源 | F12: 10月13日新增来源
A13: S6 | B13: 股票行情、PE、PB与行业 | C13: 2026-10-13 | D13: 东方财富行情接口 | E13: https://push2.eastmoney.com/api/qt/ulist.np/get | F13: 100只成分收盘价、PE(TTM)、PB与行业分类
A14: S7 | B14: 股票与指数历史行情 | C14: 2026-08-31至2026-10-13 | D14: 东方财富历史行情接口 | E14: https://push2his.eastmoney.com/api/qt/stock/kline/get | F14: 前复权日线、区间高低点与阶段涨跌
A15: S8 | B15: 现金分红明细 | C15: 截至2026-10-13的近12个月 | D15: 东方财富数据中心 | E15: https://datacenter-web.eastmoney.com/api/data/v1/get?reportName=RPT_SHAREBONUS_DET | F15: 已实施税前现金分红；TTM股息率按10月13日价格计算
A16: S9 | B16: 2026年8月PPI | C16: 2026-08 | D16: 国家统计局 | E16: https://www.stats.gov.cn/zwfwck/sjfb/202609/t20260909_1965262.html | F16: 上游周期行业价格背景
A17: S10 | B17: 2026年9月PMI | C17: 2026-09 | D17: 国家统计局 | E17: https://www.stats.gov.cn/zwfwck/sjfb/202609/t20260930_1965449.html | F17: 制造业与需求边际背景
A19: 10月13日新增口径：板块为本表自定义的14个红利分组；位置分与综合性价比分都是横截面相对评分。价格收益使用前复权收盘，TTM股息率使用近12个月已实施税前现金分红。评分用于比较，不代表未来收益承诺。 | B19: 10月13日新增口径：板块为本表自定义的14个红利分组；位置分与综合性价比分都是横截面相对评分。价格收益使用前复权收盘，TTM股息率使用近12个月已实施税前现金分红。评分用于比较，不代表未来收益承诺。 | C19: 10月13日新增口径：板块为本表自定义的14个红利分组；位置分与综合性价比分都是横截面相对评分。价格收益使用前复权收盘，TTM股息率使用近12个月已实施税前现金分红。评分用于比较，不代表未来收益承诺。 | D19: 10月13日新增口径：板块为本表自定义的14个红利分组；位置分与综合性价比分都是横截面相对评分。价格收益使用前复权收盘，TTM股息率使用近12个月已实施税前现金分红。评分用于比较，不代表未来收益承诺。 | E19: 10月13日新增口径：板块为本表自定义的14个红利分组；位置分与综合性价比分都是横截面相对评分。价格收益使用前复权收盘，TTM股息率使用近12个月已实施税前现金分红。评分用于比较，不代表未来收益承诺。 | F19: 10月13日新增口径：板块为本表自定义的14个红利分组；位置分与综合性价比分都是横截面相对评分。价格收益使用前复权收盘，TTM股息率使用近12个月已实施税前现金分红。评分用于比较，不代表未来收益承诺。
A20: 10月13日新增口径：板块为本表自定义的14个红利分组；位置分与综合性价比分都是横截面相对评分。价格收益使用前复权收盘，TTM股息率使用近12个月已实施税前现金分红。评分用于比较，不代表未来收益承诺。 | B20: 10月13日新增口径：板块为本表自定义的14个红利分组；位置分与综合性价比分都是横截面相对评分。价格收益使用前复权收盘，TTM股息率使用近12个月已实施税前现金分红。评分用于比较，不代表未来收益承诺。 | C20: 10月13日新增口径：板块为本表自定义的14个红利分组；位置分与综合性价比分都是横截面相对评分。价格收益使用前复权收盘，TTM股息率使用近12个月已实施税前现金分红。评分用于比较，不代表未来收益承诺。 | D20: 10月13日新增口径：板块为本表自定义的14个红利分组；位置分与综合性价比分都是横截面相对评分。价格收益使用前复权收盘，TTM股息率使用近12个月已实施税前现金分红。评分用于比较，不代表未来收益承诺。 | E20: 10月13日新增口径：板块为本表自定义的14个红利分组；位置分与综合性价比分都是横截面相对评分。价格收益使用前复权收盘，TTM股息率使用近12个月已实施税前现金分红。评分用于比较，不代表未来收益承诺。 | F20: 10月13日新增口径：板块为本表自定义的14个红利分组；位置分与综合性价比分都是横截面相对评分。价格收益使用前复权收盘，TTM股息率使用近12个月已实施税前现金分红。评分用于比较，不代表未来收益承诺。

Sheet 10.13行情明细
A1: 中证红利（000922）10月13日行情与板块评分明细 | B1: 中证红利（000922）10月13日行情与板块评分明细 | C1: 中证红利（000922）10月13日行情与板块评分明细 | D1: 中证红利（000922）10月13日行情与板块评分明细 | E1: 中证红利（000922）10月13日行情与板块评分明细 | F1: 中证红利（000922）10月13日行情与板块评分明细 | G1: 中证红利（000922）10月13日行情与板块评分明细 | H1: 中证红利（000922）10月13日行情与板块评分明细 | I1: 中证红利（000922）10月13日行情与板块评分明细 | J1: 中证红利（000922）10月13日行情与板块评分明细 | K1: 中证红利（000922）10月13日行情与板块评分明细 | L1: 中证红利（000922）10月13日行情与板块评分明细 | M1: 中证红利（000922）10月13日行情与板块评分明细 | N1: 中证红利（000922）10月13日行情与板块评分明细 | O1: 中证红利（000922）10月13日行情与板块评分明细 | P1: 中证红利（000922）10月13日行情与板块评分明细 | Q1: 中证红利（000922）10月13日行情与板块评分明细 | R1: 中证红利（000922）10月13日行情与板块评分明细 | S1: 中证红利（000922）10月13日行情与板块评分明细 | T1: 中证红利（000922）10月13日行情与板块评分明细 | U1: 中证红利（000922）10月13日行情与板块评分明细 | V1: 中证红利（000922）10月13日行情与板块评分明细 | W1: 中证红利（000922）10月13日行情与板块评分明细 | X1: 中证红利（000922）10月13日行情与板块评分明细 | Y1: 中证红利（000922）10月13日行情与板块评分明细 | Z1: 中证红利（000922）10月13日行情与板块评分明细 | AA1: 中证红利（000922）10月13日行情与板块评分明细 | AB1: 中证红利（000922）10月13日行情与板块评分明细 | AC1: 中证红利（000922）10月13日行情与板块评分明细 | AD1: 中证红利（000922）10月13日行情与板块评分明细 | AE1: 中证红利（000922）10月13日行情与板块评分明细 | AF1: 中证红利（000922）10月13日行情与板块评分明细 | AG1: 中证红利（000922）10月13日行情与板块评分明细 | AH1: 中证红利（000922）10月13日行情与板块评分明细 | AI1: 中证红利（000922）10月13日行情与板块评分明细
A2: 区间：2026-08-31至2026-10-13｜价格为前复权收盘｜蓝字为市场与映射输入，绿字为原半年报链接，黑字为公式 | B2: 区间：2026-08-31至2026-10-13｜价格为前复权收盘｜蓝字为市场与映射输入，绿字为原半年报链接，黑字为公式 | C2: 区间：2026-08-31至2026-10-13｜价格为前复权收盘｜蓝字为市场与映射输入，绿字为原半年报链接，黑字为公式 | D2: 区间：2026-08-31至2026-10-13｜价格为前复权收盘｜蓝字为市场与映射输入，绿字为原半年报链接，黑字为公式 | E2: 区间：2026-08-31至2026-10-13｜价格为前复权收盘｜蓝字为市场与映射输入，绿字为原半年报链接，黑字为公式 | F2: 区间：2026-08-31至2026-10-13｜价格为前复权收盘｜蓝字为市场与映射输入，绿字为原半年报链接，黑字为公式 | G2: 区间：2026-08-31至2026-10-13｜价格为前复权收盘｜蓝字为市场与映射输入，绿字为原半年报链接，黑字为公式 | H2: 区间：2026-08-31至2026-10-13｜价格为前复权收盘｜蓝字为市场与映射输入，绿字为原半年报链接，黑字为公式 | I2: 区间：2026-08-31至2026-10-13｜价格为前复权收盘｜蓝字为市场与映射输入，绿字为原半年报链接，黑字为公式 | J2: 区间：2026-08-31至2026-10-13｜价格为前复权收盘｜蓝字为市场与映射输入，绿字为原半年报链接，黑字为公式 | K2: 区间：2026-08-31至2026-10-13｜价格为前复权收盘｜蓝字为市场与映射输入，绿字为原半年报链接，黑字为公式 | L2: 区间：2026-08-31至2026-10-13｜价格为前复权收盘｜蓝字为市场与映射输入，绿字为原半年报链接，黑字为公式 | M2: 区间：2026-08-31至2026-10-13｜价格为前复权收盘｜蓝字为市场与映射输入，绿字为原半年报链接，黑字为公式 | N2: 区间：2026-08-31至2026-10-13｜价格为前复权收盘｜蓝字为市场与映射输入，绿字为原半年报链接，黑字为公式 | O2: 区间：2026-08-31至2026-10-13｜价格为前复权收盘｜蓝字为市场与映射输入，绿字为原半年报链接，黑字为公式 | P2: 区间：2026-08-31至2026-10-13｜价格为前复权收盘｜蓝字为市场与映射输入，绿字为原半年报链接，黑字为公式 | Q2: 区间：2026-08-31至2026-10-13｜价格为前复权收盘｜蓝字为市场与映射输入，绿字为原半年报链接，黑字为公式 | R2: 区间：2026-08-31至2026-10-13｜价格为前复权收盘｜蓝字为市场与映射输入，绿字为原半年报链接，黑字为公式 | S2: 区间：2026-08-31至2026-10-13｜价格为前复权收盘｜蓝字为市场与映射输入，绿字为原半年报链接，黑字为公式 | T2: 区间：2026-08-31至2026-10-13｜价格为前复权收盘｜蓝字为市场与映射输入，绿字为原半年报链接，黑字为公式 | U2: 区间：2026-08-31至2026-10-13｜价格为前复权收盘｜蓝字为市场与映射输入，绿字为原半年报链接，黑字为公式 | V2: 区间：2026-08-31至2026-10-13｜价格为前复权收盘｜蓝字为市场与映射输入，绿字为原半年报链接，黑字为公式 | W2: 区间：2026-08-31至2026-10-13｜价格为前复权收盘｜蓝字为市场与映射输入，绿字为原半年报链接，黑字为公式 | X2: 区间：2026-08-31至2026-10-13｜价格为前复权收盘｜蓝字为市场与映射输入，绿字为原半年报链接，黑字为公式 | Y2: 区间：2026-08-31至2026-10-13｜价格为前复权收盘｜蓝字为市场与映射输入，绿字为原半年报链接，黑字为公式 | Z2: 区间：2026-08-31至2026-10-13｜价格为前复权收盘｜蓝字为市场与映射输入，绿字为原半年报链接，黑字为公式 | AA2: 区间：2026-08-31至2026-10-13｜价格为前复权收盘｜蓝字为市场与映射输入，绿字为原半年报链接，黑字为公式 | AB2: 区间：2026-08-31至2026-10-13｜价格为前复权收盘｜蓝字为市场与映射输入，绿字为原半年报链接，黑字为公式 | AC2: 区间：2026-08-31至2026-10-13｜价格为前复权收盘｜蓝字为市场与映射输入，绿字为原半年报链接，黑字为公式 | AD2: 区间：2026-08-31至2026-10-13｜价格为前复权收盘｜蓝字为市场与映射输入，绿字为原半年报链接，黑字为公式 | AE2: 区间：2026-08-31至2026-10-13｜价格为前复权收盘｜蓝字为市场与映射输入，绿字为原半年报链接，黑字为公式 | AF2: 区间：2026-08-31至2026-10-13｜价格为前复权收盘｜蓝字为市场与映射输入，绿字为原半年报链接，黑字为公式 | AG2: 区间：2026-08-31至2026-10-13｜价格为前复权收盘｜蓝字为市场与映射输入，绿字为原半年报链接，黑字为公式 | AH2: 区间：2026-08-31至2026-10-13｜价格为前复权收盘｜蓝字为市场与映射输入，绿字为原半年报链接，黑字为公式 | AI2: 区间：2026-08-31至2026-10-13｜价格为前复权收盘｜蓝字为市场与映射输入，绿字为原半年报链接，黑字为公式
A3: 代码 | B3: 名称 | C3: 细分红利板块 | D3: 原分析板块 | E3: 指数权重 | F3: 东财行业 | G3: 8/31收盘 | H3: 10/13收盘 | I3: 8/31至10/13 | J3: 9/30收盘 | K3: 国庆后涨跌 | L3: 区间低点 | M3: 低点日期 | N3: 低点后反弹 | O3: 区间高点 | P3: 高点日期 | Q3: 距高点 | R3: H1营收同比 | S3: H1归母净利 | T3: H1同期净利 | U3: 利润增量 | V3: 利润同比 | W3: 利润增长标记 | X3: TTM每股分红 | Y3: TTM股息率 | Z3: 连续3年分红次数 | AA3: PE(TTM) | AB3: PB | AC3: PE评分值 | AD3: PE有效 | AE3: PB评分值 | AF3: PB有效 | AG3: H1经营现金流 | AH3: H1同期现金流 | AI3: 现金流改善标记
A4: ='100只成分明细'!A4 -> 000090 | B4: ='100只成分明细'!B4 -> 天健集团 | C4: 建筑地产 | D4: ='100只成分明细'!C4 -> 建筑 | E4: ='100只成分明细'!D4 -> 0.00421 | F4: 房地产开发 | G4: 3.49 | H4: 3.6 | I4: =IF(OR(G4="",H4=""),"",H4/G4-1) -> 0.031518625 | J4: 3.64 | K4: =IF(OR(J4="",H4=""),"",H4/J4-1) -> -0.010989011 | L4: 3.33 | M4: 46281 | N4: =IF(OR(L4="",H4=""),"",H4/L4-1) -> 0.081081081 | O4: 3.71 | P4: 46286 | Q4: =IF(OR(O4="",H4=""),"",H4/O4-1) -> -0.029649596 | R4: ='100只成分明细'!G4 -> 0.052171636 | S4: ='100只成分明细'!H4 -> -3.3289642 | T4: ='100只成分明细'!I4 -> 0.41423675 | U4: =S4-T4 -> -3.7432009 | V4: =IF(T4=0,"",S4/T4-1) -> -9.0363806 | W4: =IF(U4>0,1,0) -> 0 | X4: 0.036 | Y4: =IF(OR(X4="",H4=""),"",X4/H4) -> 0.01 | Z4: 3 | AA4: -44.58 | AB4: 0.61 | AC4: =IF(AND(AA4>0,AA4<100),MIN(AA4,50),"") | AD4: =IF(AC4="",0,1) -> 0 | AE4: =IF(AND(AB4>0,AB4<10),MIN(AB4,5),"") -> 0.61 | AF4: =IF(AE4="",0,1) -> 1 | AG4: ='100只成分明细'!O4 -> -1.0316958 | AH4: ='100只成分明细'!P4 -> -9.7974394 | AI4: =IF(AG4>AH4,1,0) -> 1
A5: ='100只成分明细'!A5 -> 000157 | B5: ='100只成分明细'!B5 -> 中联重科 | C5: 机械汽车 | D5: ='100只成分明细'!C5 -> 其他 | E5: ='100只成分明细'!D5 -> 0.007 | F5: 工程机械 | G5: 6.69 | H5: 6.03 | I5: =IF(OR(G5="",H5=""),"",H5/G5-1) -> -0.098654709 | J5: 5.97 | K5: =IF(OR(J5="",H5=""),"",H5/J5-1) -> 0.010050251 | L5: 5.83 | M5: 46294 | N5: =IF(OR(L5="",H5=""),"",H5/L5-1) -> 0.034305317 | O5: 6.82 | P5: 46265 | Q5: =IF(OR(O5="",H5=""),"",H5/O5-1) -> -0.11583578 | R5: ='100只成分明细'!G5 -> 0.091749452 | S5: ='100只成分明细'!H5 -> 21.021891 | T5: ='100只成分明细'!I5 -> 27.647786 | U5: =S5-T5 -> -6.6258947 | V5: =IF(T5=0,"",S5/T5-1) -> -0.23965372 | W5: =IF(U5>0,1,0) -> 0 | X5: 0.4 | Y5: =IF(OR(X5="",H5=""),"",X5/H5) -> 0.066334992 | Z5: 3 | AA5: 12.43 | AB5: 0.91 | AC5: =IF(AND(AA5>0,AA5<100),MIN(AA5,50),"") -> 12.43 | AD5: =IF(AC5="",0,1) -> 1 | AE5: =IF(AND(AB5>0,AB5<10),MIN(AB5,5),"") -> 0.91 | AF5: =IF(AE5="",0,1) -> 1 | AG5: ='100只成分明细'!O5 -> 24.19537 | AH5: ='100只成分明细'!P5 -> 17.517803 | AI5: =IF(AG5>AH5,1,0) -> 1
A6: ='100只成分明细'!A6 -> 000408 | B6: ='100只成分明细'!B6 -> 藏格矿业 | C6: 有色矿业 | D6: ='100只成分明细'!C6 -> 有色矿业 | E6: ='100只成分明细'!D6 -> 0.01246 | F6: 农化制品 | G6: 77.39 | H6: 71.52 | I6: =IF(OR(G6="",H6=""),"",H6/G6-1) -> -0.075849593 | J6: 70.66 | K6: =IF(OR(J6="",H6=""),"",H6/J6-1) -> 0.01217096 | L6: 69.05 | M6: 46294 | N6: =IF(OR(L6="",H6=""),"",H6/L6-1) -> 0.03577118 | O6: 79.22 | P6: 46266 | Q6: =IF(OR(O6="",H6=""),"",H6/O6-1) -> -0.097197677 | R6: ='100只成分明细'!G6 -> 0.23045494 | S6: ='100只成分明细'!H6 -> 36.380814 | T6: ='100只成分明细'!I6 -> 18.002052 | U6: =S6-T6 -> 18.378761 | V6: =IF(T6=0,"",S6/T6-1) -> 1.0209259 | W6: =IF(U6>0,1,0) -> 1 | X6: 2.5 | Y6: =IF(OR(X6="",H6=""),"",X6/H6) -> 0.034955257 | Z6: 2 | AA6: 19.72 | AB6: 7.18 | AC6: =IF(AND(AA6>0,AA6<100),MIN(AA6,50),"") -> 19.72 | AD6: =IF(AC6="",0,1) -> 1 | AE6: =IF(AND(AB6>0,AB6<10),MIN(AB6,5),"") -> 5 | AF6: =IF(AE6="",0,1) -> 1 | AG6: ='100只成分明细'!O6 -> 9.8415792 | AH6: ='100只成分明细'!P6 -> 8.3407623 | AI6: =IF(AG6>AH6,1,0) -> 1
A7: ='100只成分明细'!A7 -> 000429 | B7: ='100只成分明细'!B7 -> 粤高速A | C7: 交通物流 | D7: ='100只成分明细'!C7 -> 交通运输 | E7: ='100只成分明细'!D7 -> 0.01043 | F7: 铁路公路 | G7: 13.23 | H7: 13.43 | I7: =IF(OR(G7="",H7=""),"",H7/G7-1) -> 0.015117158 | J7: 12.46 | K7: =IF(OR(J7="",H7=""),"",H7/J7-1) -> 0.077849117 | L7: 12.23 | M7: 46294 | N7: =IF(OR(L7="",H7=""),"",H7/L7-1) -> 0.098119379 | O7: 13.53 | P7: 46308 | Q7: =IF(OR(O7="",H7=""),"",H7/O7-1) -> -0.007390983 | R7: ='100只成分明细'!G7 -> 0.00046754072 | S7: ='100只成分明细'!H7 -> 8.5012926 | T7: ='100只成分明细'!I7 -> 10.571529 | U7: =S7-T7 -> -2.070236 | V7: =IF(T7=0,"",S7/T7-1) -> -0.19583128 | W7: =IF(U7>0,1,0) -> 0 | X7: 0.604 | Y7: =IF(OR(X7="",H7=""),"",X7/H7) -> 0.044973939 | Z7: 3 | AA7: 17.61 | AB7: 2.65 | AC7: =IF(AND(AA7>0,AA7<100),MIN(AA7,50),"") -> 17.61 | AD7: =IF(AC7="",0,1) -> 1 | AE7: =IF(AND(AB7>0,AB7<10),MIN(AB7,5),"") -> 2.65 | AF7: =IF(AE7="",0,1) -> 1 | AG7: ='100只成分明细'!O7 -> 17.085762 | AH7: ='100只成分明细'!P7 -> 18.976668 | AI7: =IF(AG7>AH7,1,0) -> 0
A8: ='100只成分明细'!A8 -> 000651 | B8: ='100只成分明细'!B8 -> 格力电器 | C8: 消费 | D8: ='100只成分明细'!C8 -> 其他 | E8: ='100只成分明细'!D8 -> 0.01143 | F8: 白色家电 | G8: 38.95 | H8: 39.77 | I8: =IF(OR(G8="",H8=""),"",H8/G8-1) -> 0.021052632 | J8: 38.28 | K8: =IF(OR(J8="",H8=""),"",H8/J8-1) -> 0.03892372 | L8: 37.81 | M8: 46287 | N8: =IF(OR(L8="",H8=""),"",H8/L8-1) -> 0.051838138 | O8: 40 | P8: 46308 | Q8: =IF(OR(O8="",H8=""),"",H8/O8-1) -> -0.00575 | R8: ='100只成分明细'!G8 -> -0.08140215 | S8: ='100只成分明细'!H8 -> 132.77591 | T8: ='100只成分明细'!I8 -> 144.12407 | U8: =S8-T8 -> -11.348162 | V8: =IF(T8=0,"",S8/T8-1) -> -0.078738841 | W8: =IF(U8>0,1,0) -> 0 | X8: 3 | Y8: =IF(OR(X8="",H8=""),"",X8/H8) -> 0.075433744 | Z8: 3 | AA8: 7.99 | AB8: 1.62 | AC8: =IF(AND(AA8>0,AA8<100),MIN(AA8,50),"") -> 7.99 | AD8: =IF(AC8="",0,1) -> 1 | AE8: =IF(AND(AB8>0,AB8<10),MIN(AB8,5),"") -> 1.62 | AF8: =IF(AE8="",0,1) -> 1 | AG8: ='100只成分明细'!O8 -> 188.08832 | AH8: ='100只成分明细'!P8 -> 283.28562 | AI8: =IF(AG8>AH8,1,0) -> 0
A9: ='100只成分明细'!A9 -> 000672 | B9: ='100只成分明细'!B9 -> 上峰材料 | C9: 建材家居 | D9: ='100只成分明细'!C9 -> 水泥建材 | E9: ='100只成分明细'!D9 -> 0.01145 | F9: 水泥 | G9: 14.43 | H9: 14.38 | I9: =IF(OR(G9="",H9=""),"",H9/G9-1) -> -0.0034650035 | J9: 14.84 | K9: =IF(OR(J9="",H9=""),"",H9/J9-1) -> -0.030997305 | L9: 14.06 | M9: 46308 | N9: =IF(OR(L9="",H9=""),"",H9/L9-1) -> 0.022759602 | O9: 16.03 | P9: 46289 | Q9: =IF(OR(O9="",H9=""),"",H9/O9-1) -> -0.102932 | R9: ='100只成分明细'!G9 -> -0.19091262 | S9: ='100只成分明细'!H9 -> 13.640648 | T9: ='100只成分明细'!I9 -> 2.4686948 | U9: =S9-T9 -> 11.171953 | V9: =IF(T9=0,"",S9/T9-1) -> 4.5254493 | W9: =IF(U9>0,1,0) -> 1 | X9: 0.637 | Y9: =IF(OR(X9="",H9=""),"",X9/H9) -> 0.044297636 | Z9: 3 | AA9: 7.94 | AB9: 1.42 | AC9: =IF(AND(AA9>0,AA9<100),MIN(AA9,50),"") -> 7.94 | AD9: =IF(AC9="",0,1) -> 1 | AE9: =IF(AND(AB9>0,AB9<10),MIN(AB9,5),"") -> 1.42 | AF9: =IF(AE9="",0,1) -> 1 | AG9: ='100只成分明细'!O9 -> 3.1147397 | AH9: ='100只成分明细'!P9 -> 4.7554007 | AI9: =IF(AG9>AH9,1,0) -> 0
A10: ='100只成分明细'!A10 -> 000895 | B10: ='100只成分明细'!B10 -> 双汇发展 | C10: 消费 | D10: ='100只成分明细'!C10 -> 其他 | E10: ='100只成分明细'!D10 -> 0.01017 | F10: 食品加工 | G10: 24.06 | H10: 23.56 | I10: =IF(OR(G10="",H10=""),"",H10/G10-1) -> -0.02078138 | J10: 23.66 | K10: =IF(OR(J10="",H10=""),"",H10/J10-1) -> -0.0042265427 | L10: 23.08 | M10: 46286 | N10: =IF(OR(L10="",H10=""),"",H10/L10-1) -> 0.020797227 | O10: 24.5 | P10: 46265 | Q10: =IF(OR(O10="",H10=""),"",H10/O10-1) -> -0.038367347 | R10: ='100只成分明细'!G10 -> -0.011182618 | S10: ='100只成分明细'!H10 -> 23.055896 | T10: ='100只成分明细'!I10 -> 23.231623 | U10: =S10-T10 -> -0.1757268 | V10: =IF(T10=0,"",S10/T10-1) -> -0.0075641206 | W10: =IF(U10>0,1,0) -> 0 | X10: 0.8 | Y10: =IF(OR(X10="",H10=""),"",X10/H10) -> 0.033955857 | Z10: 3 | AA10: 16.05 | AB10: 3.91 | AC10: =IF(AND(AA10>0,AA10<100),MIN(AA10,50),"") -> 16.05 | AD10: =IF(AC10="",0,1) -> 1 | AE10: =IF(AND(AB10>0,AB10<10),MIN(AB10,5),"") -> 3.91 | AF10: =IF(AE10="",0,1) -> 1 | AG10: ='100只成分明细'!O10 -> 16.16936 | AH10: ='100只成分明细'!P10 -> 29.142047 | AI10: =IF(AG10>AH10,1,0) -> 0
A11: ='100只成分明细'!A11 -> 000933 | B11: ='100只成分明细'!B11 -> 神火股份 | C11: 有色矿业 | D11: ='100只成分明细'!C11 -> 有色矿业 | E11: ='100只成分明细'!D11 -> 0.00853 | F11: 工业金属 | G11: 27.48 | H11: 26.6 | I11: =IF(OR(G11="",H11=""),"",H11/G11-1) -> -0.03202329 | J11: 26.22 | K11: =IF(OR(J11="",H11=""),"",H11/J11-1) -> 0.014492754 | L11: 24.9 | M11: 46294 | N11: =IF(OR(L11="",H11=""),"",H11/L11-1) -> 0.068273092 | O11: 29.06 | P11: 46275 | Q11: =IF(OR(O11="",H11=""),"",H11/O11-1) -> -0.084652443 | R11: ='100只成分明细'!G11 -> 0.21354421 | S11: ='100只成分明细'!H11 -> 47.813773 | T11: ='100只成分明细'!I11 -> 19.044568 | U11: =S11-T11 -> 28.769205 | V11: =IF(T11=0,"",S11/T11-1) -> 1.5106252 | W11: =IF(U11>0,1,0) -> 1 | X11: 0.8 | Y11: =IF(OR(X11="",H11=""),"",X11/H11) -> 0.030075188 | Z11: 3 | AA11: 8.69 | AB11: 2.16 | AC11: =IF(AND(AA11>0,AA11<100),MIN(AA11,50),"") -> 8.69 | AD11: =IF(AC11="",0,1) -> 1 | AE11: =IF(AND(AB11>0,AB11<10),MIN(AB11,5),"") -> 2.16 | AF11: =IF(AE11="",0,1) -> 1 | AG11: ='100只成分明细'!O11 -> 72.004561 | AH11: ='100只成分明细'!P11 -> 44.368336 | AI11: =IF(AG11>AH11,1,0) -> 1
A12: ='100只成分明细'!A12 -> 000983 | B12: ='100只成分明细'!B12 -> 山西焦煤 | C12: 煤炭 | D12: ='100只成分明细'!C12 -> 煤炭 | E12: ='100只成分明细'!D12 -> 0.01391 | F12: 煤炭开采 | G12: 7.42 | H12: 6.46 | I12: =IF(OR(G12="",H12=""),"",H12/G12-1) -> -0.12938005 | J12: 6.48 | K12: =IF(OR(J12="",H12=""),"",H12/J12-1) -> -0.0030864198 | L12: 6.28 | M12: 46294 | N12: =IF(OR(L12="",H12=""),"",H12/L12-1) -> 0.02866242 | O12: 7.6 | P12: 46265 | Q12: =IF(OR(O12="",H12=""),"",H12/O12-1) -> -0.15 | R12: ='100只成分明细'!G12 -> -0.0013972352 | S12: ='100只成分明细'!H12 -> 12.369695 | T12: ='100只成分明细'!I12 -> 10.136957 | U12: =S12-T12 -> 2.232738 | V12: =IF(T12=0,"",S12/T12-1) -> 0.22025722 | W12: =IF(U12>0,1,0) -> 1 | X12: 0.126 | Y12: =IF(OR(X12="",H12=""),"",X12/H12) -> 0.019504644 | Z12: 3 | AA12: 25.75 | AB12: 0.99 | AC12: =IF(AND(AA12>0,AA12<100),MIN(AA12,50),"") -> 25.75 | AD12: =IF(AC12="",0,1) -> 1 | AE12: =IF(AND(AB12>0,AB12<10),MIN(AB12,5),"") -> 0.99 | AF12: =IF(AE12="",0,1) -> 1 | AG12: ='100只成分明细'!O12 -> 16.013416 | AH12: ='100只成分明细'!P12 -> 33.272869 | AI12: =IF(AG12>AH12,1,0) -> 0
A13: ='100只成分明细'!A13 -> 002043 | B13: ='100只成分明细'!B13 -> 兔宝宝 | C13: 建材家居 | D13: ='100只成分明细'!C13 -> 水泥建材 | E13: ='100只成分明细'!D13 -> 0.00922 | F13: 装修建材 | G13: 12.54 | H13: 12.22 | I13: =IF(OR(G13="",H13=""),"",H13/G13-1) -> -0.025518341 | J13: 12.02 | K13: =IF(OR(J13="",H13=""),"",H13/J13-1) -> 0.016638935 | L13: 10.58 | M13: 46281 | N13: =IF(OR(L13="",H13=""),"",H13/L13-1) -> 0.15500945 | O13: 13.4 | P13: 46265 | Q13: =IF(OR(O13="",H13=""),"",H13/O13-1) -> -0.088059701 | R13: ='100只成分明细'!G13 -> 0.17403058 | S13: ='100只成分明细'!H13 -> 2.4730882 | T13: ='100只成分明细'!I13 -> 2.6784711 | U13: =S13-T13 -> -0.20538287 | V13: =IF(T13=0,"",S13/T13-1) -> -0.076679145 | W13: =IF(U13>0,1,0) -> 0 | X13: 0.432 | Y13: =IF(OR(X13="",H13=""),"",X13/H13) -> 0.035351882 | Z13: 3 | AA13: 14.87 | AB13: 3.18 | AC13: =IF(AND(AA13>0,AA13<100),MIN(AA13,50),"") -> 14.87 | AD13: =IF(AC13="",0,1) -> 1 | AE13: =IF(AND(AB13>0,AB13<10),MIN(AB13,5),"") -> 3.18 | AF13: =IF(AE13="",0,1) -> 1 | AG13: ='100只成分明细'!O13 -> 2.1296853 | AH13: ='100只成分明细'!P13 -> 1.0737049 | AI13: =IF(AG13>AH13,1,0) -> 1
A14: ='100只成分明细'!A14 -> 002154 | B14: ='100只成分明细'!B14 -> 报喜鸟 | C14: 消费 | D14: ='100只成分明细'!C14 -> 其他 | E14: ='100只成分明细'!D14 -> 0.00477 | F14: 服装家纺 | G14: 4.08 | H14: 3.8 | I14: =IF(OR(G14="",H14=""),"",H14/G14-1) -> -0.068627451 | J14: 3.85 | K14: =IF(OR(J14="",H14=""),"",H14/J14-1) -> -0.012987013 | L14: 3.74 | M14: 46308 | N14: =IF(OR(L14="",H14=""),"",H14/L14-1) -> 0.016042781 | O14: 4.19 | P14: 46269 | Q14: =IF(OR(O14="",H14=""),"",H14/O14-1) -> -0.093078759 | R14: ='100只成分明细'!G14 -> 0.099615278 | S14: ='100只成分明细'!H14 -> 2.9134168 | T14: ='100只成分明细'!I14 -> 1.9723263 | U14: =S14-T14 -> 0.94109051 | V14: =IF(T14=0,"",S14/T14-1) -> 0.47714748 | W14: =IF(U14>0,1,0) -> 1 | X14: 0.17 | Y14: =IF(OR(X14="",H14=""),"",X14/H14) -> 0.044736842 | Z14: 3 | AA14: 12.72 | AB14: 1.18 | AC14: =IF(AND(AA14>0,AA14<100),MIN(AA14,50),"") -> 12.72 | AD14: =IF(AC14="",0,1) -> 1 | AE14: =IF(AND(AB14>0,AB14<10),MIN(AB14,5),"") -> 1.18 | AF14: =IF(AE14="",0,1) -> 1 | AG14: ='100只成分明细'!O14 -> 3.0611351 | AH14: ='100只成分明细'!P14 -> 0.94649802 | AI14: =IF(AG14>AH14,1,0) -> 1
A15: ='100只成分明细'!A15 -> 002233 | B15: ='100只成分明细'!B15 -> 塔牌集团 | C15: 建材家居 | D15: ='100只成分明细'!C15 -> 水泥建材 | E15: ='100只成分明细'!D15 -> 0.00653 | F15: 水泥 | G15: 7.12 | H15: 7.06 | I15: =IF(OR(G15="",H15=""),"",H15/G15-1) -> -0.0084269663 | J15: 6.86 | K15: =IF(OR(J15="",H15=""),"",H15/J15-1) -> 0.029154519 | L15: 6.61 | M15: 46293 | N15: =IF(OR(L15="",H15=""),"",H15/L15-1) -> 0.068078669 | O15: 7.33 | P15: 46304 | Q15: =IF(OR(O15="",H15=""),"",H15/O15-1) -> -0.036834925 | R15: ='100只成分明细'!G15 -> -0.15299864 | S15: ='100只成分明细'!H15 -> 2.1945048 | T15: ='100只成分明细'!I15 -> 4.3539688 | U15: =S15-T15 -> -2.159464 | V15: =IF(T15=0,"",S15/T15-1) -> -0.495976 | W15: =IF(U15>0,1,0) -> 0 | X15: 0.61 | Y15: =IF(OR(X15="",H15=""),"",X15/H15) -> 0.086402266 | Z15: 3 | AA15: 19.83 | AB15: 0.72 | AC15: =IF(AND(AA15>0,AA15<100),MIN(AA15,50),"") -> 19.83 | AD15: =IF(AC15="",0,1) -> 1 | AE15: =IF(AND(AB15>0,AB15<10),MIN(AB15,5),"") -> 0.72 | AF15: =IF(AE15="",0,1) -> 1 | AG15: ='100只成分明细'!O15 -> 1.7094921 | AH15: ='100只成分明细'!P15 -> 1.3498505 | AI15: =IF(AG15>AH15,1,0) -> 1
... A103: ='100只成分明细'!A103 -> 920599 | B103: ='100只成分明细'!B103 -> 同力股份 | C103: 机械汽车 | D103: ='100只成分明细'!C103 -> 其他 | E103: ='100只成分明细'!D103 -> 0.00422 | F103: 工程机械 | G103: 17.95 | H103: 18.03 | I103: =IF(OR(G103="",H103=""),"",H103/G103-1) -> 0.0044568245 | J103: 17.38 | K103: =IF(OR(J103="",H103=""),"",H103/J103-1) -> 0.03739931 | L103: 16.8 | M103: 46282 | N103: =IF(OR(L103="",H103=""),"",H103/L103-1) -> 0.073214286 | O103: 18.75 | P103: 46267 | Q103: =IF(OR(O103="",H103=""),"",H103/O103-1) -> -0.0384 | R103: ='100只成分明细'!G103 -> 0.12133099 | S103: ='100只成分明细'!H103 -> 4.0558142 | T103: ='100只成分明细'!I103 -> 3.2122719 | U103: =S103-T103 -> 0.84354221 | V103: =IF(T103=0,"",S103/T103-1) -> 0.26259988 | W103: =IF(U103>0,1,0) -> 1 | X103: 0.7 | Y103: =IF(OR(X103="",H103=""),"",X103/H103) -> 0.038824182 | Z103: 3 | AA103: 9.03 | AB103: 2.27 | AC103: =IF(AND(AA103>0,AA103<100),MIN(AA103,50),"") -> 9.03 | AD103: =IF(AC103="",0,1) -> 1 | AE103: =IF(AND(AB103>0,AB103<10),MIN(AB103,5),"") -> 2.27 | AF103: =IF(AE103="",0,1) -> 1 | AG103: ='100只成分明细'!O103 -> 5.1229508 | AH103: ='100只成分明细'!P103 -> -6.3166048 | AI103: =IF(AG103>AH103,1,0) -> 1
A108: 中证红利指数区间行情（000922，前复权） | B108: 中证红利指数区间行情（000922，前复权） | C108: 中证红利指数区间行情（000922，前复权） | D108: 中证红利指数区间行情（000922，前复权） | E108: 中证红利指数区间行情（000922，前复权） | F108: 中证红利指数区间行情（000922，前复权）
A109: 日期 | B109: 开盘 | C109: 收盘 | D109: 最高 | E109: 最低 | F109: 涨跌幅
A110: 46265 | B110: 5704.35 | C110: 5718.42 | D110: 5724.53 | E110: 5667.85 | F110: 0.0047
A111: 46266 | B111: 5701.79 | C111: 5719.05 | D111: 5786.14 | E111: 5701.66 | F111: 0.0001
A112: 46267 | B112: 5738.08 | C112: 5634.58 | D112: 5741.77 | E112: 5626.38 | F112: -0.0148
A113: 46268 | B113: 5631.89 | C113: 5635.06 | D113: 5704.93 | E113: 5626.8 | F113: 0.0001
A114: 46269 | B114: 5638.06 | C114: 5648.28 | D114: 5681.67 | E114: 5630.55 | F114: 0.0023
A115: 46272 | B115: 5642.48 | C115: 5580.21 | D115: 5650.83 | E115: 5555.28 | F115: -0.0121
A116: 46273 | B116: 5588.65 | C116: 5652.8 | D116: 5658.43 | E116: 5588.22 | F116: 0.013
A117: 46274 | B117: 5647.96 | C117: 5716 | D117: 5721.97 | E117: 5627.72 | F117: 0.0112
A118: 46275 | B118: 5714.53 | C118: 5677.09 | D118: 5719.17 | E118: 5670.21 | F118: -0.0068
A119: 46276 | B119: 5665.33 | C119: 5580.28 | D119: 5667.2 | E119: 5570.67 | F119: -0.0171
A120: 46279 | B120: 5572.52 | C120: 5568.76 | D120: 5609.87 | E120: 5552.13 | F120: -0.0021
A121: 46280 | B121: 5568.76 | C121: 5534.25 | D121: 5573.73 | E121: 5525.24 | F121: -0.0062
... A135: 46308 | B135: 5610.45 | C135: 5624.5 | D135: 5645.41 | E135: 5593.94 | F135: 0.001

Sheet 10.13方法
A1: 中证红利10月13日量化方法 | B1: 中证红利10月13日量化方法 | C1: 中证红利10月13日量化方法 | D1: 中证红利10月13日量化方法 | E1: 中证红利10月13日量化方法 | F1: 中证红利10月13日量化方法 | G1: 中证红利10月13日量化方法 | H1: 中证红利10月13日量化方法 | I1: 中证红利10月13日量化方法 | J1: 中证红利10月13日量化方法
A2: 位置分判断相对高低，基本面分判断盈利与分红质量；两者合成综合性价比分。所有评分均为14个板块的横截面相对排名。 | B2: 位置分判断相对高低，基本面分判断盈利与分红质量；两者合成综合性价比分。所有评分均为14个板块的横截面相对排名。 | C2: 位置分判断相对高低，基本面分判断盈利与分红质量；两者合成综合性价比分。所有评分均为14个板块的横截面相对排名。 | D2: 位置分判断相对高低，基本面分判断盈利与分红质量；两者合成综合性价比分。所有评分均为14个板块的横截面相对排名。 | E2: 位置分判断相对高低，基本面分判断盈利与分红质量；两者合成综合性价比分。所有评分均为14个板块的横截面相对排名。 | F2: 位置分判断相对高低，基本面分判断盈利与分红质量；两者合成综合性价比分。所有评分均为14个板块的横截面相对排名。 | G2: 位置分判断相对高低，基本面分判断盈利与分红质量；两者合成综合性价比分。所有评分均为14个板块的横截面相对排名。 | H2: 位置分判断相对高低，基本面分判断盈利与分红质量；两者合成综合性价比分。所有评分均为14个板块的横截面相对排名。 | I2: 位置分判断相对高低，基本面分判断盈利与分红质量；两者合成综合性价比分。所有评分均为14个板块的横截面相对排名。 | J2: 位置分判断相对高低，基本面分判断盈利与分红质量；两者合成综合性价比分。所有评分均为14个板块的横截面相对排名。
A4: 8月31日模型复刻 | B4: 8月31日模型复刻 | C4: 8月31日模型复刻 | D4: 8月31日模型复刻
A5: 参数/结果 | B5: 数值 | C5: 口径
A6: 上一期技术底 | B6: 5100 | C6: 历史技术通道输入
A7: 上一期技术顶 | B7: 6100 | C7: 历史技术通道输入
A8: 按权重营收同比 | B8: =SUMPRODUCT('100只成分明细'!$D$4:$D$103,'100只成分明细'!$G$4:$G$103)/SUM('100只成分明细'!$D$4:$D$103) -> 0.045555386 | C8: 指数权重加权
A9: 利润池同比 | B9: =SUM('100只成分明细'!$H$4:$H$103)/SUM('100只成分明细'!$I$4:$I$103)-1 -> 0.062795209 | C9: 100家公司利润合计
A10: 利润增长公司占比 | B10: =COUNTIF('100只成分明细'!$K$4:$K$103,">0")/COUNT('100只成分明细'!$K$4:$K$103) -> 0.58 | C10: 利润增量为正的公司数占比
A12: 场景 | B12: 修正率 | C12: 底部 | D12: 顶部
A13: 保守：按权重营收 | B13: =MIN($B$8,$B$9) -> 0.045555386 | C13: =$B$6*(1+B13) -> 5332.3325 | D13: =$B$7*(1+B13) -> 6377.8879
A14: 中枢：两口径均值 | B14: =AVERAGE($B$8,$B$9) -> 0.054175298 | C14: =$B$6*(1+B14) -> 5376.294 | D14: =$B$7*(1+B14) -> 6430.4693
A15: 积极：按利润池 | B15: =MAX($B$8,$B$9) -> 0.062795209 | C15: =$B$6*(1+B15) -> 5420.2556 | D15: =$B$7*(1+B15) -> 6483.0508
A18: 位置分（高分代表相对位置更高） | B18: 位置分（高分代表相对位置更高） | C18: 位置分（高分代表相对位置更高） | D18: 位置分（高分代表相对位置更高） | F18: 基本面分（高分代表盈利与分红更强） | G18: 基本面分（高分代表盈利与分红更强） | H18: 基本面分（高分代表盈利与分红更强） | I18: 基本面分（高分代表盈利与分红更强）
A19: 指标 | B19: 权重 | C19: 高分方向 | D19: 含义 | F19: 指标 | G19: 权重 | H19: 高分方向 | I19: 处理
A20: 8/31至10/13涨跌 | B20: 0.2 | C20: 涨幅高 | D20: 中期价格兑现 | F20: H1营收同比 | G20: 0.2 | H20: 增速高 | I20: 按指数权重加权
A21: 国庆后涨跌 | B21: 0.25 | C21: 涨幅高 | D21: 近期资金集中 | F21: H1利润池同比 | G21: 0.3 | H21: 增速高 | I21: 评分时限制在±50%
A22: 低点后反弹 | B22: 0.15 | C22: 反弹高 | D22: 从区间低位修复 | F22: 利润增长权重占比 | G22: 0.15 | H22: 占比高 | I22: 按指数权重统计
A23: 距区间高点 | B23: 0.1 | C23: 越接近0越高 | D23: 接近阶段高位 | F23: TTM股息率 | G23: 0.2 | H23: 股息率高 | I23: 近12个月实施现金分红/现价
A24: TTM股息率 | B24: 0.15 | C24: 股息率低 | D24: 分红收益缓冲较少 | F24: 连续3年分红 | G24: 0.15 | H24: 占比高 | I24: 2023—2025年度均实施现金分红
A25: PB | B25: 0.15 | C25: PB高 | D25: 绝对估值较高
A28: 综合与解释 | B28: 综合与解释 | C28: 综合与解释 | D28: 综合与解释 | E28: 综合与解释 | F28: 综合与解释 | G28: 综合与解释 | H28: 综合与解释 | I28: 综合与解释 | J28: 综合与解释
A29: 综合性价比分 | B29: 55%×基本面分 + 45%×(100-位置分)
A30: 位置分区间 | B30: ≥65 偏高；55—65 中高；45—55 中性；35—45 中低；<35 偏低
A31: 性价比区间 | B31: ≥65 较高；55—65 中上；45—55 中性；35—45 中下；<35 较低
A32: 重要限制 | B32: 板块分数只在本次100只成分、14个分组内比较，不代表绝对估值，也不等同于未来收益预测。
A33: 使用建议 | B33: 先看位置分辨别追涨风险，再用基本面分剔除低位但盈利转弱的板块。
A34: 日常更新 | B34: 在结论页黄色格输入日期与中证红利收盘，可更新指数位置指标；板块评分需同步刷新100只成分行情后重算。
A36: 行业分组映射 | B36: 行业分组映射 | C36: 行业分组映射
A37: 东财行业 | B37: 细分红利板块 | C37: 备注
A38: 银行Ⅱ | B38: 银行
A39: 煤炭开采、焦炭Ⅱ | B39: 煤炭
A40: 油气开采Ⅱ、炼化及贸易 | B40: 油气炼化
A41: 航运港口、铁路公路、物流 | B41: 交通物流
A42: 工业金属、能源金属 | B42: 有色矿业
A43: 农化制品 | B43: 有色矿业/化工 | C43: 藏格矿业按有色，其余按化工
A44: 保险Ⅱ、多元金融 | B44: 保险金融
A45: 基础建设、房屋建设Ⅱ、房地产开发 | B45: 建筑地产
A46: 水泥、装修建材、家居用品 | B46: 建材家居
A47: 化学原料、化学制品 | B47: 化工
A48: 普钢、冶钢原料 | B48: 钢铁
A49: 工程机械、专用设备、汽车零部件 | B49: 机械汽车
A50: 家电、服装、食品、零售、饰品 | B50: 消费
A51: 出版、中药Ⅱ | B51: 出版医药
A52: 环境治理、燃气Ⅱ | B52: 公用环保
