Workbook

Sheet 一图流
A2: 北京银行一图流估值 | B2: 北京银行一图流估值 | C2: 北京银行一图流估值 | D2: 北京银行一图流估值 | E2: 北京银行一图流估值 | F2: 北京银行一图流估值 | G2: 北京银行一图流估值 | H2: 北京银行一图流估值 | I2: 北京银行一图流估值 | J2: 北京银行一图流估值 | K2: 北京银行一图流估值 | L2: 北京银行一图流估值
A3: 601169.SH 经营数据截至 2026-06-30 股价快照 2026-10-14 11:55（盘中） | B3: 601169.SH 经营数据截至 2026-06-30 股价快照 2026-10-14 11:55（盘中） | C3: 601169.SH 经营数据截至 2026-06-30 股价快照 2026-10-14 11:55（盘中） | D3: 601169.SH 经营数据截至 2026-06-30 股价快照 2026-10-14 11:55（盘中） | E3: 601169.SH 经营数据截至 2026-06-30 股价快照 2026-10-14 11:55（盘中） | F3: 601169.SH 经营数据截至 2026-06-30 股价快照 2026-10-14 11:55（盘中） | G3: 601169.SH 经营数据截至 2026-06-30 股价快照 2026-10-14 11:55（盘中） | H3: 601169.SH 经营数据截至 2026-06-30 股价快照 2026-10-14 11:55（盘中） | I3: 601169.SH 经营数据截至 2026-06-30 股价快照 2026-10-14 11:55（盘中） | J3: 601169.SH 经营数据截至 2026-06-30 股价快照 2026-10-14 11:55（盘中） | K3: 601169.SH 经营数据截至 2026-06-30 股价快照 2026-10-14 11:55（盘中） | L3: 601169.SH 经营数据截至 2026-06-30 股价快照 2026-10-14 11:55（盘中）
A5: 当前价（元） | B5: 当前价（元） | C5: 当前价（元） | D5: 合理价值区间（元） | E5: 合理价值区间（元） | F5: 合理价值区间（元） | G5: 组合安全边际 | H5: 组合安全边际 | I5: 组合安全边际 | J5: 保守安全边际 | K5: 保守安全边际 | L5: 保守安全边际
A6: =估值系统!$B$7 -> 5.62 | D6: =TEXT(估值系统!$C$22,"0.00")&" — "&TEXT(估值系统!$B$26,"0.00") -> 5.25 — 6.79 | G6: =估值系统!$B$27 -> 0.17246642 | J6: =估值系统!$B$28 -> -0.070782772
A10: ="有折价、需验证：当前价低于组合中枢 "&TEXT(估值系统!$B$27,"0.0%")&"，但高于保守 DDM "&TEXT(-估值系统!$B$28,"0.0%") -> 有折价、需验证：当前价低于组合中枢 17.2%，但高于保守 DDM 7.1%
A13: 经营与风险指标（2026H1） | B13: 经营与风险指标（2026H1） | C13: 经营与风险指标（2026H1） | D13: 经营与风险指标（2026H1） | E13: 经营与风险指标（2026H1） | F13: 经营与风险指标（2026H1） | G13: 经营与风险指标（2026H1） | H13: 经营与风险指标（2026H1） | I13: 经营与风险指标（2026H1） | J13: 经营与风险指标（2026H1） | K13: 经营与风险指标（2026H1） | L13: 经营与风险指标（2026H1）
A14: 营收增速 | B14: 营收增速 | C14: 归母净利润增速 | D14: 归母净利润增速 | E14: 年化 ROE | F14: 年化 ROE | G14: 净息差 | H14: 净息差 | I14: 不良率 | J14: 不良率 | K14: CET1 | L14: CET1
A15: 0.056 | C15: 0.0563 | E15: 0.106 | G15: 0.0126 | I15: 0.013 | K15: 0.0891
A17: 同比 | B17: 同比 | C17: 同比 | D17: 同比 | E17: 公司披露口径 | F17: 公司披露口径 | G17: 同比 -5bp | H17: 同比 -5bp | I17: 较年初 +1bp | J17: 较年初 +1bp | K17: 较年初 +54bp | L17: 较年初 +54bp
A19: 支持估值的因素 | B19: 支持估值的因素 | C19: 支持估值的因素 | D19: 支持估值的因素 | E19: 支持估值的因素 | F19: 支持估值的因素 | G19: 需要继续验证 | H19: 需要继续验证 | I19: 需要继续验证 | J19: 需要继续验证 | K19: 需要继续验证 | L19: 需要继续验证
A20: 盈利 | B20: 营收与归母净利润均增长约 5.6%，PPOP 增长 9.6%。 | G20: 资产质量 | H20: 信用成本升至 0.89%，关注贷款迁徙率升至 50.72%。
A22: 负债 | B22: 负债成本率降至 1.45%，企业活期存款增长 8.0%。 | G22: 资本 | H22: CET1 为 8.91%，高增长与高支付率不能同时假设。
A24: 估值 | B24: PB 0.42x，低于可比城商行中位数 0.86x。 | G24: 盈利持续性 | H24: NIM 1.26%，个人贷款下降 4.0%，修复仍需后续财报验证。
A27: 六法估值（元/股） | B27: 六法估值（元/股） | C27: 六法估值（元/股） | D27: 六法估值（元/股） | E27: 六法估值（元/股） | F27: 六法估值（元/股） | G27: 六法估值（元/股） | H27: 六法估值（元/股） | I27: 关键监控 | J27: 关键监控 | K27: 关键监控 | L27: 关键监控
A28: 方法 | B28: 价值 | C28: 权重 | I28: 指标 | J28: 当前 | K28: 警戒线 | L28: 下一节点
A29: RIM | B29: =估值系统!C17 -> 8.5906439 | C29: 0.15 | I29: ROE | J29: 10.6% | K29: <8% | L29: 2026Q3
A30: PB–ROE | B30: =估值系统!C18 -> 8.5373333 | C30: 0.15 | I30: 净息差 | J30: 1.26% | K30: <1.15% | L30: 中报/年报
A31: 历史 PB | B31: =估值系统!C19 -> 5.761626 | C31: 0.1 | I31: 信用成本 | J31: 0.89% | K31: >1.0% | L31: 中报/年报
A32: 历史 PE | B32: =估值系统!C20 -> 5.57503 | C32: 0.1 | I32: 不良率 | J32: 1.30% | K32: >1.40% | L32: 2026Q3
A33: 同业调整 PB | B33: =估值系统!C21 -> 7.5692696 | C33: 0.2 | I33: CET1 | J33: 8.91% | K33: <8.5% | L33: 2026Q3
A34: DDM | B34: =估值系统!C22 -> 5.2484968 | C34: 0.3 | I34: 拨备覆盖率 | J34: 199.59% | K34: <180% | L34: 2026Q3
A42: 判断 | B42: 当前估值提供一定缓冲，但保守分红价值没有明显安全垫。重点验证盈利延续、信用成本与资本。
A43: 数据边界 | B43: 2026 年三季报预约 2026-10-31 披露，尚未公开。当前价为盘中快照，非收盘价。
A44: 使用提示 | B44: 黄色单元格为可编辑假设。修改假设后，估值系统、一图流与敏感性结果联动。

Sheet 投资结论
A2: 北京银行投资研究结论 | B2: 北京银行投资研究结论 | C2: 北京银行投资研究结论 | D2: 北京银行投资研究结论 | E2: 北京银行投资研究结论 | F2: 北京银行投资研究结论 | G2: 北京银行投资研究结论 | H2: 北京银行投资研究结论 | I2: 北京银行投资研究结论 | J2: 北京银行投资研究结论
A3: 事实、分析假设与研究判断分色呈现；不构成个性化买卖建议 | B3: 事实、分析假设与研究判断分色呈现；不构成个性化买卖建议 | C3: 事实、分析假设与研究判断分色呈现；不构成个性化买卖建议 | D3: 事实、分析假设与研究判断分色呈现；不构成个性化买卖建议 | E3: 事实、分析假设与研究判断分色呈现；不构成个性化买卖建议 | F3: 事实、分析假设与研究判断分色呈现；不构成个性化买卖建议 | G3: 事实、分析假设与研究判断分色呈现；不构成个性化买卖建议 | H3: 事实、分析假设与研究判断分色呈现；不构成个性化买卖建议 | I3: 事实、分析假设与研究判断分色呈现；不构成个性化买卖建议 | J3: 事实、分析假设与研究判断分色呈现；不构成个性化买卖建议
A4: 结论概览 | B4: 结论概览 | C4: 结论概览 | D4: 结论概览 | E4: 结论概览 | F4: 结论概览 | G4: 结论概览 | H4: 结论概览 | I4: 结论概览 | J4: 结论概览
A5: 当前价 | B5: 5.62 | D5: 类型 | E5: 核心内容 | F5: 证据/假设 | G5: 影响 | H5: 监控 | I5: 触发线 | J5: 结论
A6: 合理价值下沿 | B6: =估值系统!$C$22 -> 5.2484968 | D6: 事实 | E6: 2026H1 营收和归母净利润分别增长 5.60% 和 5.63%。 | F6: 中报 | G6: 盈利恢复 | H6: 2026Q3 | I6: 增速转负 | J6: 正面
A7: 合理价值上沿 | B7: =估值系统!$B$26 -> 6.7912652 | D7: 事实 | E7: PPOP 约 287.85 亿元，同比增长约 9.6%；但信用减值损失增至 100.05 亿元。 | F7: 中报测算 | G7: 经营改善与风险成本并存 | H7: 信用成本 | I7: 高于1% | J7: 中性
A8: 组合中枢 | B8: =估值系统!$B$26 -> 6.7912652 | D8: 事实 | E8: 不良率 1.30%，关注率 1.58%，逾期率 1.96%，CET1 8.91%。 | F8: 中报 | G8: 资本和风险仍约束估值 | H8: 不良/关注/CET1 | I8: 同步恶化 | J8: 谨慎
A9: 组合安全边际 | B9: =估值系统!$B$27 -> 0.17246642 | D9: 假设 | E9: 归一化 ROE 8.5%，Ke 11.5%，长期增长率 2.5%，支付率 32%。 | F9: 可编辑模型 | G9: 决定内生价值 | H9: 敏感性页 | I9: Ke-g 收窄 | J9: 基准
A10: 保守安全边际 | B10: =估值系统!$B$28 -> -0.070782772 | D10: 判断 | E10: 当前价低于组合中枢约 17.2%，但高于保守 DDM 约 7.1%。 | F10: 模型 | G10: 折价不等于深度安全边际 | H10: 股息与资本 | I10: DDM低于价 | J10: 中性偏正面
A11: 研究结论 | B11: 有折价、需验证 | D11: 判断 | E11: 若 ROE 稳定在 9% 以上且 CET1 不低于 8.8%，价值区间可向上沿靠拢。 | F11: 情景 | G11: 需要经营兑现 | H11: ROE/CET1 | I11: 连续两个报告期 | J11: 条件性
A14: 三条核心结论 | B14: 三条核心结论 | C14: 三条核心结论 | D14: 三条核心结论 | E14: 三条核心结论 | G14: 三条核心风险 | H14: 三条核心风险 | I14: 三条核心风险 | J14: 三条核心风险
A15: 1 | B15: 盈利与费用端改善，NIM 降幅收窄，负债成本管理有效。 | G15: 1 | H15: 信用成本与迁徙率上升，核销掩盖点时不良净增。
A16: 2 | B16: 低 PB 有折价，但 ROE 与资本水平解释了部分折价。 | G16: 2 | H16: CET1 较薄，高增长和高支付率不能同时假设。
A17: 3 | B17: 主要价值来自分红与温和 ROE 修复，而非历史估值全面回归。 | G17: 3 | H17: NIM 仍处下行区间，个人贷款收缩，盈利修复可能反复。
A20: 季度监控与估值动作 | B20: 季度监控与估值动作 | C20: 季度监控与估值动作 | D20: 季度监控与估值动作 | E20: 季度监控与估值动作 | F20: 季度监控与估值动作 | G20: 季度监控与估值动作 | H20: 季度监控与估值动作 | I20: 季度监控与估值动作 | J20: 季度监控与估值动作
A21: 指标 | B21: 当前 | C21: 改善条件 | D21: 恶化条件 | E21: 改善时含义 | F21: 恶化时含义 | G21: 数据频率 | H21: 下一节点 | I21: 来源 | J21: 备注
A22: ROE | B22: 0.106 | C22: ≥9%可持续 | D22: <8% | E22: 上调内生估值 | F22: 下调 PB–ROE/RIM | G22: 季度/年度 | H22: 2026Q3 | I22: 定期报告 | J22: H1为年化
A23: 净息差 | B23: 0.0126 | C23: 止跌或回升 | D23: <1.15% | E23: 提高盈利确定性 | F23: 下调 EPS/ROE | G23: 半年/年度 | H23: 2026Q3辅助 | I23: 定期报告 | J23: 季度未必披露
A24: 信用成本 | B24: 0.0089 | C24: ≤0.8% | D24: >1.0% | E24: 风险成本正常化 | F24: 下调盈利与分红 | G24: 半年/年度 | H24: 2026Q3辅助 | I24: 定期报告 | J24: H1年化
A25: 不良率 | B25: 0.013 | C25: ≤1.30% | D25: >1.40% | E25: 维持质量判断 | F25: 提高折价 | G25: 季度 | H25: 2026Q3 | I25: 定期报告 | J25: 结合关注/逾期
A26: CET1 | B26: 0.0891 | C26: ≥8.8% | D26: <8.5% | E26: 支持32%支付率 | F26: 下调支付率 | G26: 季度 | H26: 2026Q3 | I26: 资本披露 | J26: 集团口径
A27: 拨备覆盖率 | B27: 1.9959 | C27: ≥190% | D27: <180% | E27: 风险缓冲稳定 | F27: 估值下沿下移 | G27: 季度 | H27: 2026Q3 | I27: 定期报告 | J27: 结合核销
A29: 边界 | B29: 2026 年三季报预约 2026-10-31 披露，本报告未纳入尚未公开的数据。
A30: 区间 | B30: 主合理价值区间为防守 DDM 至修正组合中枢；条件性上行不并入主区间。
A31: 使用 | B31: 修改黄色假设后，估值系统、一图流与敏感性结果联动。

Sheet 估值系统
A2: 北京银行多模型估值系统 | B2: 北京银行多模型估值系统 | C2: 北京银行多模型估值系统 | D2: 北京银行多模型估值系统 | E2: 北京银行多模型估值系统 | F2: 北京银行多模型估值系统 | G2: 北京银行多模型估值系统 | H2: 北京银行多模型估值系统 | I2: 北京银行多模型估值系统 | J2: 北京银行多模型估值系统
A3: 价格为 2026-10-14 11:55 盘中快照；经营数据截至 2026-06-30 | B3: 价格为 2026-10-14 11:55 盘中快照；经营数据截至 2026-06-30 | C3: 价格为 2026-10-14 11:55 盘中快照；经营数据截至 2026-06-30 | D3: 价格为 2026-10-14 11:55 盘中快照；经营数据截至 2026-06-30 | E3: 价格为 2026-10-14 11:55 盘中快照；经营数据截至 2026-06-30 | F3: 价格为 2026-10-14 11:55 盘中快照；经营数据截至 2026-06-30 | G3: 价格为 2026-10-14 11:55 盘中快照；经营数据截至 2026-06-30 | H3: 价格为 2026-10-14 11:55 盘中快照；经营数据截至 2026-06-30 | I3: 价格为 2026-10-14 11:55 盘中快照；经营数据截至 2026-06-30 | J3: 价格为 2026-10-14 11:55 盘中快照；经营数据截至 2026-06-30
A4: 关键输入 | B4: 关键输入 | C4: 关键输入 | D4: 关键输入
A5: 公司 | B5: 北京银行 | D5: 经营数据截至 | E5: 46203
A6: 代码 | B6: 601169.SH | D6: 股价快照 | E6: 46309.164
A7: 当前价（元） | B7: 5.62 | D7: 长期增长率 | E7: =估值敏感性!$B$7 -> 0.025
A8: BPS（元） | B8: 13.48 | D8: 基础支付率 | E8: =估值敏感性!$B$9 -> 0.32
A9: 归一化 EPS（元） | B9: =估值敏感性!$B$8 -> 1.2 | D9: 同业 β | E9: 0.8
A10: 归一化 ROE | B10: =估值敏感性!$B$5 -> 0.085 | D10: 同业额外折价 | E10: 0.15
A11: 股权成本 Ke | B11: =估值敏感性!$B$6 -> 0.115 | D11: 历史区间 | E11: 2020—2025 年末
A12: PB–ROE 模型折价 | B12: 0.05 | D12: 报告制作日 | E12: 46309
A15: 六种主估值方法 | B15: 六种主估值方法 | C15: 六种主估值方法 | D15: 六种主估值方法 | E15: 六种主估值方法 | F15: 六种主估值方法 | G15: 六种主估值方法 | H15: 六种主估值方法 | I15: 六种主估值方法 | J15: 六种主估值方法
A16: 方法 | B16: 关键输入 | C16: 每股价值 | D16: 权重 | E16: 加权贡献 | F16: 可靠性 | G16: 主要限制 | H16: 模型组 | I16: 当前价折价 | J16: 是否主锚
A17: 剩余收益模型 RIM | B17: 5年 ROE 路径、Ke、终值 | C17: =I42 -> 8.5906439 | D17: 0.15 | E17: =C17*D17 -> 1.2885966 | F17: 中 | G17: 终值受长期 ROE 影响 | H17: ROE内生 | I17: =1-$B$7/C17 -> 0.34579991 | J17: 是
A18: PB–ROE 合理倍数 | B18: ROE、Ke、g、模型折价 | C18: =((B10-E7)/(B11-E7))*B8*(1-B12) -> 8.5373333 | D18: 0.15 | E18: =C18*D18 -> 1.2806 | F18: 中 | G18: 稳定期公式对 Ke-g 敏感 | H18: ROE内生 | I18: =1-$B$7/C18 -> 0.34171482 | J18: 是
A19: 历史 PB | B19: 2020—2025 年末 PB 中位数 | C19: =MEDIAN(财务十年!R9:R14)*B8 -> 5.761626 | D19: 0.1 | E19: =C19*D19 -> 0.5761626 | F19: 中低 | G19: 历史 ROE 下移会压低可比性 | H19: 历史倍数 | I19: =1-$B$7/C19 -> 0.024580915 | J19: 否
A20: 历史 PE | B20: 2020—2025 年末 PE 中位数×归一化EPS | C20: =MEDIAN(财务十年!S9:S14)*B9 -> 5.57503 | D20: 0.1 | E20: =C20*D20 -> 0.557503 | F20: 中低 | G20: 2025 EPS 受大额减值扰动 | H20: 历史倍数 | I20: =1-$B$7/C20 -> -0.0080663221 | J20: 否
A21: 同业 ROE 调整 PB | B21: 同业 PB×ROE 弹性×额外折价 | C21: =同业比较!$E$20 -> 7.5692696 | D21: 0.2 | E21: =C21*D21 -> 1.5138539 | F21: 中 | G21: 同业结构和资本质量不同 | H21: 同业比较 | I21: =1-$B$7/C21 -> 0.25752413 | J21: 是
A22: 两阶段 DDM | B22: 5年股息+稳定增长终值 | C22: =股息估值!$B$33 -> 5.2484968 | D22: 0.3 | E22: =C22*D22 -> 1.5745491 | F22: 中高 | G22: 对支付率与 Ke 最敏感 | H22: 分红模型 | I22: =1-$B$7/C22 -> -0.070782772 | J22: 是
A24: 组合估值 | B24: 历史倍数权重仅 20%；DDM 权重 30%，反映资本与分红约束 | C24: 历史倍数权重仅 20%；DDM 权重 30%，反映资本与分红约束 | D24: 历史倍数权重仅 20%；DDM 权重 30%，反映资本与分红约束 | E24: 历史倍数权重仅 20%；DDM 权重 30%，反映资本与分红约束
A25: 权重合计 | B25: =SUM(D17:D22) -> 1
A26: 修正组合中枢 | B26: =SUM(E17:E22) -> 6.7912652 | C26: 元
A27: 组合安全边际 | B27: =1-B7/B26 -> 0.17246642
A28: 保守安全边际 | B28: =1-B7/C22 -> -0.070782772 | C28: 相对 DDM
A31: 剩余收益模型明细 | B31: 剩余收益模型明细 | C31: 剩余收益模型明细 | D31: 剩余收益模型明细 | E31: 剩余收益模型明细 | F31: 剩余收益模型明细 | G31: 剩余收益模型明细 | H31: 剩余收益模型明细 | I31: 剩余收益模型明细
A32: 年份 | B32: 期初 BPS | C32: ROE | D32: EPS | E32: 支付率 | F32: DPS | G32: 期末 BPS | H32: 剩余收益 | I32: 现值
A33: 1 | B33: =$B$8 -> 13.48 | C33: =估值敏感性!$B$5+1% -> 0.095 | D33: =B33*C33 -> 1.2806 | E33: 0.3 | F33: =D33*E33 -> 0.38418 | G33: =B33+D33-F33 -> 14.37642 | H33: =(C33-$B$11)*B33 -> -0.2696 | I33: =H33/(1+$B$11)^A33 -> -0.24179372
A34: 2 | B34: =G33 -> 14.37642 | C34: =估值敏感性!$B$5+0.7% -> 0.092 | D34: =B34*C34 -> 1.3226306 | E34: 0.31 | F34: =D34*E34 -> 0.4100155 | G34: =B34+D34-F34 -> 15.289035 | H34: =(C34-$B$11)*B34 -> -0.33065766 | I34: =H34/(1+$B$11)^A34 -> -0.26596767
A35: 3 | B35: =G34 -> 15.289035 | C35: =估值敏感性!$B$5+0.4% -> 0.089 | D35: =B35*C35 -> 1.3607241 | E35: 0.32 | F35: =D35*E35 -> 0.43543172 | G35: =B35+D35-F35 -> 16.214328 | H35: =(C35-$B$11)*B35 -> -0.39751491 | I35: =H35/(1+$B$11)^A35 -> -0.28676677
A36: 4 | B36: =G35 -> 16.214328 | C36: =估值敏感性!$B$5+0.2% -> 0.087 | D36: =B36*C36 -> 1.4106465 | E36: 0.33 | F36: =D36*E36 -> 0.46551334 | G36: =B36+D36-F36 -> 17.159461 | H36: =(C36-$B$11)*B36 -> -0.45400117 | I36: =H36/(1+$B$11)^A36 -> -0.29373622
A37: 5 | B37: =G36 -> 17.159461 | C37: =估值敏感性!$B$5 -> 0.085 | D37: =B37*C37 -> 1.4585542 | E37: 0.35 | F37: =D37*E37 -> 0.51049396 | G37: =B37+D37-F37 -> 18.107521 | H37: =(C37-$B$11)*B37 -> -0.51478382 | I37: =H37/(1+$B$11)^A37 -> -0.29871054
H39: 终值现值 | I39: =((C37-$B$11)*G37)/($B$11-$E$7)/(1+$B$11)^5 -> -3.5023811
H40: 残余收益现值合计 | I40: =SUM(I33:I37) -> -1.3869749
H41: 期初 BPS | I41: =$B$8 -> 13.48
H42: RIM 每股价值 | I42: =I39+I40+I41 -> 8.5906439
A44: 结论 | B44: 当前价低于组合中枢，但高于保守 DDM；估值有一定折价，却不是无条件高安全边际。
A45: 解释 | B45: 2026H1 盈利恢复、费用下降和负债成本改善支持 ROE 修复；信用成本、迁徙率和较低 CET1 限制估值上沿。
A46: 估值区间 | B46: 以 DDM 防守价值至修正组合中枢为主区间；历史高估值修复仅作为条件性上行。
A47: 失效条件 | B47: NIM 再降、信用成本持续高于 1%、CET1 低于 8.5%、不良/关注/逾期同步恶化。

Sheet 估值敏感性
A2: 北京银行估值敏感性 | B2: 北京银行估值敏感性 | C2: 北京银行估值敏感性 | D2: 北京银行估值敏感性 | E2: 北京银行估值敏感性 | F2: 北京银行估值敏感性 | G2: 北京银行估值敏感性 | H2: 北京银行估值敏感性 | I2: 北京银行估值敏感性 | J2: 北京银行估值敏感性 | K2: 北京银行估值敏感性 | L2: 北京银行估值敏感性 | M2: 北京银行估值敏感性
A3: ROE 与股权成本为模型的权威可编辑输入；黄色单元格可调整 | B3: ROE 与股权成本为模型的权威可编辑输入；黄色单元格可调整 | C3: ROE 与股权成本为模型的权威可编辑输入；黄色单元格可调整 | D3: ROE 与股权成本为模型的权威可编辑输入；黄色单元格可调整 | E3: ROE 与股权成本为模型的权威可编辑输入；黄色单元格可调整 | F3: ROE 与股权成本为模型的权威可编辑输入；黄色单元格可调整 | G3: ROE 与股权成本为模型的权威可编辑输入；黄色单元格可调整 | H3: ROE 与股权成本为模型的权威可编辑输入；黄色单元格可调整 | I3: ROE 与股权成本为模型的权威可编辑输入；黄色单元格可调整 | J3: ROE 与股权成本为模型的权威可编辑输入；黄色单元格可调整 | K3: ROE 与股权成本为模型的权威可编辑输入；黄色单元格可调整 | L3: ROE 与股权成本为模型的权威可编辑输入；黄色单元格可调整 | M3: ROE 与股权成本为模型的权威可编辑输入；黄色单元格可调整
A4: 核心假设 | B4: 核心假设 | C4: 核心假设 | D4: 核心假设 | G4: RIM：ROE × Ke | H4: RIM：ROE × Ke | I4: RIM：ROE × Ke | J4: RIM：ROE × Ke | K4: RIM：ROE × Ke
A5: 归一化可持续 ROE | B5: 0.085 | C5: 口径 | D5: 分析假设
A6: 股权成本 Ke | B6: 0.115 | C6: 口径 | D6: 分析假设 | G6: =估值系统!$C$17 -> 8.5906439 | H6: 0.095 | I6: 0.105 | J6: 0.115
A7: 长期增长率 g | B7: 0.025 | C7: 口径 | D7: 分析假设 | G7: 0.06 | H7: =TABLE($G$6,$B$5,$G7,$B$6,H$6) -> 6.4746481 | I7: =TABLE($G$6,$B$5,$G7,$B$6,I$6) -> 5.5747139 | J7: =TABLE($G$6,$B$5,$G7,$B$6,J$6) -> 4.8789479
A8: 归一化 EPS（元） | B8: 1.2 | C8: 口径 | D8: 2026H1 年化后审慎下调 | G8: 0.07 | H8: =TABLE($G$6,$B$5,$G8,$B$6,H$6) -> 8.413017 | I8: =TABLE($G$6,$B$5,$G8,$B$6,I$6) -> 7.2224232 | J8: =TABLE($G$6,$B$5,$G8,$B$6,J$6) -> 6.3027891
A9: 基础股利支付率 | B9: 0.32 | C9: 口径 | D9: 参考历史与资本约束 | G9: 0.08 | H9: =TABLE($G$6,$B$5,$G9,$B$6,H$6) -> 10.463312 | I9: =TABLE($G$6,$B$5,$G9,$B$6,I$6) -> 8.9643571 | J9: =TABLE($G$6,$B$5,$G9,$B$6,J$6) -> 7.8072506
G10: 0.09 | H10: =TABLE($G$6,$B$5,$G10,$B$6,H$6) -> 12.629707 | I10: =TABLE($G$6,$B$5,$G10,$B$6,I$6) -> 10.804017 | J10: =TABLE($G$6,$B$5,$G10,$B$6,J$6) -> 9.3953176
A11: 情景 | B11: 悲观 | C11: 基准 | D11: 乐观 | G11: 0.1 | H11: =TABLE($G$6,$B$5,$G11,$B$6,H$6) -> 14.91648 | I11: =TABLE($G$6,$B$5,$G11,$B$6,I$6) -> 12.744991 | J11: =TABLE($G$6,$B$5,$G11,$B$6,J$6) -> 11.07005
A12: 净息差 | B12: 0.0115 | C12: 0.0126 | D12: 0.0135 | G12: 0.105 | H12: =TABLE($G$6,$B$5,$G12,$B$6,H$6) -> 16.106374 | I12: =TABLE($G$6,$B$5,$G12,$B$6,I$6) -> 13.754618 | J12: =TABLE($G$6,$B$5,$G12,$B$6,J$6) -> 11.940894
A13: 营收增速 | B13: -0.02 | C13: 0.04 | D13: 0.08
A14: 信用成本 | B14: 0.011 | C14: 0.0089 | D14: 0.007 | G14: PB–ROE：ROE × Ke | H14: PB–ROE：ROE × Ke | I14: PB–ROE：ROE × Ke | J14: PB–ROE：ROE × Ke | K14: PB–ROE：ROE × Ke
A15: 归一化 ROE | B15: 0.07 | C15: 0.085 | D15: 0.1
A16: Ke | B16: 0.125 | C16: 0.115 | D16: 0.105 | G16: =估值系统!$C$18 -> 8.5373333 | H16: 0.095 | I16: 0.105 | J16: 0.115
A17: 长期增长率 | B17: 0.015 | C17: 0.025 | D17: 0.03 | G17: 0.06 | H17: =TABLE($G$16,$B$5,$G17,$B$6,H$16) -> 6.403 | I17: =TABLE($G$16,$B$5,$G17,$B$6,I$16) -> 5.602625 | J17: =TABLE($G$16,$B$5,$G17,$B$6,J$16) -> 4.9801111
A18: 支付率 | B18: 0.28 | C18: 0.32 | D18: 0.36 | G18: 0.07 | H18: =TABLE($G$16,$B$5,$G18,$B$6,H$16) -> 8.2324286 | I18: =TABLE($G$16,$B$5,$G18,$B$6,I$16) -> 7.203375 | J18: =TABLE($G$16,$B$5,$G18,$B$6,J$16) -> 6.403
A19: 目标股息率 | B19: 0.065 | C19: 0.055 | D19: 0.05 | G19: 0.08 | H19: =TABLE($G$16,$B$5,$G19,$B$6,H$16) -> 10.061857 | I19: =TABLE($G$16,$B$5,$G19,$B$6,I$16) -> 8.804125 | J19: =TABLE($G$16,$B$5,$G19,$B$6,J$16) -> 7.8258889
G20: 0.09 | H20: =TABLE($G$16,$B$5,$G20,$B$6,H$16) -> 11.891286 | I20: =TABLE($G$16,$B$5,$G20,$B$6,I$16) -> 10.404875 | J20: =TABLE($G$16,$B$5,$G20,$B$6,J$16) -> 9.2487778
G21: 0.1 | H21: =TABLE($G$16,$B$5,$G21,$B$6,H$16) -> 13.720714 | I21: =TABLE($G$16,$B$5,$G21,$B$6,I$16) -> 12.005625 | J21: =TABLE($G$16,$B$5,$G21,$B$6,J$16) -> 10.671667
A22: 经营情景估值 | B22: 经营情景估值 | C22: 经营情景估值 | D22: 经营情景估值 | E22: 经营情景估值 | G22: 0.105 | H22: =TABLE($G$16,$B$5,$G22,$B$6,H$16) -> 14.635429 | I22: =TABLE($G$16,$B$5,$G22,$B$6,I$16) -> 12.806 | J22: =TABLE($G$16,$B$5,$G22,$B$6,J$16) -> 11.383111
A23: 指标 | B23: 悲观 | C23: 基准 | D23: 乐观 | E23: 说明
A24: 可持续 EPS（元） | B24: 1.05 | C24: 1.2 | D24: 1.3 | E24: 归一化，不是盈利预测 | G24: 组合中枢：ROE × Ke | H24: 组合中枢：ROE × Ke | I24: 组合中枢：ROE × Ke | J24: 组合中枢：ROE × Ke | K24: 组合中枢：ROE × Ke
A25: 合理 PB（x） | B25: =(B15-B17)/(B16-B17) -> 0.5 | C25: =(C15-C17)/(C16-C17) -> 0.66666667 | D25: =(D15-D17)/(D16-D17) -> 0.93333333 | E25: 稳定期公式
A26: PB–ROE 价值（元） | B26: =B25*估值系统!$B$8*(1-估值系统!$B$12) -> 6.403 | C26: =C25*估值系统!$B$8*(1-估值系统!$B$12) -> 8.5373333 | D26: =D25*估值系统!$B$8*(1-估值系统!$B$12) -> 11.952267 | E26: 含模型折价 | G26: =估值系统!$B$26 -> 6.7912652 | H26: 0.095 | I26: 0.105 | J26: 0.115
A27: 股息率反推价值（元） | B27: =B24*B18/B19 -> 4.5230769 | C27: =C24*C18/C19 -> 6.9818182 | D27: =D24*D18/D19 -> 9.36 | E27: DPS/目标收益率 | G27: 0.06 | H27: =TABLE($G$26,$B$5,$G27,$B$6,H$26) -> 6.627901 | I27: =TABLE($G$26,$B$5,$G27,$B$6,I$26) -> 6.1058888 | J27: =TABLE($G$26,$B$5,$G27,$B$6,J$26) -> 5.7009274
A28: 相对当前价安全边际 | B28: =1-估值系统!$B$7/AVERAGE(B26:B27) -> -0.028731546 | C28: =1-估值系统!$B$7/AVERAGE(C26:C27) -> 0.2757336 | D28: =1-估值系统!$B$7/AVERAGE(D26:D27) -> 0.4726042 | E28: 正数表示折价 | G28: 0.07 | H28: =TABLE($G$26,$B$5,$G28,$B$6,H$26) -> 7.1930706 | I28: =TABLE($G$26,$B$5,$G28,$B$6,I$26) -> 6.5931577 | J28: =TABLE($G$26,$B$5,$G28,$B$6,J$26) -> 6.1279369
G29: 0.08 | H29: =TABLE($G$26,$B$5,$G29,$B$6,H$26) -> 7.7750292 | I29: =TABLE($G$26,$B$5,$G29,$B$6,I$26) -> 7.0945603 | J29: =TABLE($G$26,$B$5,$G29,$B$6,J$26) -> 6.5670395
G30: 0.09 | H30: =TABLE($G$26,$B$5,$G30,$B$6,H$26) -> 8.3744027 | I30: =TABLE($G$26,$B$5,$G30,$B$6,I$26) -> 7.6106218 | J30: =TABLE($G$26,$B$5,$G30,$B$6,J$26) -> 7.0186829
G31: 0.1 | H31: =TABLE($G$26,$B$5,$G31,$B$6,H$26) -> 8.9918329 | I31: =TABLE($G$26,$B$5,$G31,$B$6,I$26) -> 8.1418804 | J31: =TABLE($G$26,$B$5,$G31,$B$6,J$26) -> 7.4833261
G32: 0.105 | H32: =TABLE($G$26,$B$5,$G32,$B$6,H$26) -> 9.3075242 | I32: =TABLE($G$26,$B$5,$G32,$B$6,I$26) -> 8.4133806 | J32: =TABLE($G$26,$B$5,$G32,$B$6,J$26) -> 7.7206693
G34: 解读 | H34: ROE 8% 与 9% 为重点观察行；Ke 越高，RIM、PB–ROE 与组合中枢均下降。
G35: 边界 | H35: 所有测试 Ke 均高于长期增长率 2.5%，避免公式奇点。
G36: 当前价 | H36: 5.62 | I36: 元
G37: 基准组合中枢 | H37: =估值系统!$B$26 -> 6.7912652 | I37: 元
G38: 基准组合安全边际 | H38: =估值系统!$B$27 -> 0.17246642

Sheet 股息估值
A2: 北京银行股息估值 | B2: 北京银行股息估值 | C2: 北京银行股息估值 | D2: 北京银行股息估值 | E2: 北京银行股息估值 | F2: 北京银行股息估值 | G2: 北京银行股息估值 | H2: 北京银行股息估值 | I2: 北京银行股息估值 | J2: 北京银行股息估值 | K2: 北京银行股息估值 | L2: 北京银行股息估值 | M2: 北京银行股息估值 | N2: 北京银行股息估值
A3: 区分已实施年度股息、2026H1 拟派中期股息与可持续情景股息 | B3: 区分已实施年度股息、2026H1 拟派中期股息与可持续情景股息 | C3: 区分已实施年度股息、2026H1 拟派中期股息与可持续情景股息 | D3: 区分已实施年度股息、2026H1 拟派中期股息与可持续情景股息 | E3: 区分已实施年度股息、2026H1 拟派中期股息与可持续情景股息 | F3: 区分已实施年度股息、2026H1 拟派中期股息与可持续情景股息 | G3: 区分已实施年度股息、2026H1 拟派中期股息与可持续情景股息 | H3: 区分已实施年度股息、2026H1 拟派中期股息与可持续情景股息 | I3: 区分已实施年度股息、2026H1 拟派中期股息与可持续情景股息 | J3: 区分已实施年度股息、2026H1 拟派中期股息与可持续情景股息 | K3: 区分已实施年度股息、2026H1 拟派中期股息与可持续情景股息 | L3: 区分已实施年度股息、2026H1 拟派中期股息与可持续情景股息 | M3: 区分已实施年度股息、2026H1 拟派中期股息与可持续情景股息 | N3: 区分已实施年度股息、2026H1 拟派中期股息与可持续情景股息
A4: 历史分红 | B4: 历史分红 | C4: 历史分红 | D4: 历史分红 | E4: 历史分红 | F4: 历史分红 | H4: 股息情景与收益率反推 | I4: 股息情景与收益率反推 | J4: 股息情景与收益率反推 | K4: 股息情景与收益率反推 | L4: 股息情景与收益率反推 | M4: 股息情景与收益率反推 | N4: 股息情景与收益率反推
A5: 年度/期间 | B5: EPS | C5: DPS | D5: 支付率 | E5: 当前价静态收益率 | F5: 状态 | H5: 情景 | I5: 归一化 EPS | J5: 支付率 | K5: 可持续 DPS | L5: 当前股息率 | M5: 目标股息率 | N5: 反推价格
A6: 2016 | B6: 0.96 | C6: 0.25 | D6: =C6/B6 -> 0.26041667 | E6: =C6/估值系统!$B$7 -> 0.044483986 | F6: 已实施 | H6: 保守 | I6: 1.05 | J6: 0.28 | K6: =I6*J6 -> 0.294 | L6: =K6/估值系统!$B$7 -> 0.052313167 | M6: 0.06 | N6: =K6/M6 -> 4.9
A7: 2017 | B7: 0.99 | C7: 0.267 | D7: =C7/B7 -> 0.26969697 | E7: =C7/估值系统!$B$7 -> 0.047508897 | F7: 已实施 | H7: 基准 | I7: 1.2 | J7: 0.32 | K7: =I7*J7 -> 0.384 | L7: =K7/估值系统!$B$7 -> 0.068327402 | M7: 0.055 | N7: =K7/M7 -> 6.9818182
A8: 2018 | B8: 0.91 | C8: 0.286 | D8: =C8/B8 -> 0.31428571 | E8: =C8/估值系统!$B$7 -> 0.05088968 | F8: 已实施 | H8: 条件上限 | I8: 1.3 | J8: 0.36 | K8: =I8*J8 -> 0.468 | L8: =K8/估值系统!$B$7 -> 0.083274021 | M8: 0.05 | N8: =K8/M8 -> 9.36
A9: 2019 | B9: 0.98 | C9: 0.305 | D9: =C9/B9 -> 0.31122449 | E9: =C9/估值系统!$B$7 -> 0.054270463 | F9: 已实施
A10: 2020 | B10: 0.98 | C10: 0.3 | D10: =C10/B10 -> 0.30612245 | E10: =C10/估值系统!$B$7 -> 0.053380783 | F10: 已实施 | H10: 当前价 | I10: =估值系统!$B$7 -> 5.62 | J10: 元
A11: 2021 | B11: 1.02 | C11: 0.305 | D11: =C11/B11 -> 0.29901961 | E11: =C11/估值系统!$B$7 -> 0.054270463 | F11: 已实施 | H11: 2025 年度 DPS | I11: 0.278 | J11: 已实施
A12: 2022 | B12: 1.02 | C12: 0.31 | D12: =C12/B12 -> 0.30392157 | E12: =C12/估值系统!$B$7 -> 0.055160142 | F12: 已实施 | H12: 2026H1 DPS | I12: 0.13 | J12: 预案，未实施
A13: 2023 | B13: 1.06 | C13: 0.32 | D13: =C13/B13 -> 0.30188679 | E13: =C13/估值系统!$B$7 -> 0.056939502 | F13: 已实施 | H13: 已实施静态股息率 | I13: =I11/I10 -> 0.049466192 | J13: 只含最近完整年度
A14: 2024 | B14: 1.09 | C14: 0.32 | D14: =C14/B14 -> 0.29357798 | E14: =C14/估值系统!$B$7 -> 0.056939502 | F14: 已实施 | H14: 年度+中期预案合计收益率 | I14: =(I11+I12)/I10 -> 0.072597865 | J14: 并非已实现 LTM
A15: 2025 | B15: 0.78 | C15: 0.278 | D15: =C15/B15 -> 0.35641026 | E15: =C15/估值系统!$B$7 -> 0.049466192 | F15: 已实施
A16: 2026H1 | B16: 0.71 | C16: 0.13 | D16: =C16/B16 -> 0.18309859 | E16: =C16/估值系统!$B$7 -> 0.023131673 | F16: 董事会预案
A19: 两阶段股利折现模型（DDM） | B19: 两阶段股利折现模型（DDM） | C19: 两阶段股利折现模型（DDM） | D19: 两阶段股利折现模型（DDM） | E19: 两阶段股利折现模型（DDM） | F19: 两阶段股利折现模型（DDM） | G19: 两阶段股利折现模型（DDM） | H19: 两阶段股利折现模型（DDM） | I19: 两阶段股利折现模型（DDM） | K19: 资本约束 | L19: 资本约束 | M19: 资本约束 | N19: 资本约束
A20: 年份 | B20: 期初 EPS | C20: EPS 增速 | D20: 期末 EPS | E20: 支付率 | F20: DPS | G20: 折现因子 | H20: DPS 现值 | I20: 说明 | K20: 事实 | L20: CET1 8.91%，较年初回升 54bp，但仍低于多数可比城商行。
A21: 1 | B21: =估值敏感性!$B$8 -> 1.2 | C21: 0.05 | D21: =B21*(1+C21) -> 1.26 | E21: 0.3 | F21: =D21*E21 -> 0.378 | G21: =1/(1+估值敏感性!$B$6)^A21 -> 0.89686099 | H21: =F21*G21 -> 0.33901345 | I21: 盈利修复 | K21: 事实 | L21: 2026H1 已发行/计入其他一级资本，普通股分红仍要服从核心一级资本内生积累。
A22: 2 | B22: =D21 -> 1.26 | C22: 0.045 | D22: =B22*(1+C22) -> 1.3167 | E22: 0.31 | F22: =D22*E22 -> 0.408177 | G22: =1/(1+估值敏感性!$B$6)^A22 -> 0.80435963 | H22: =F22*G22 -> 0.3283211 | I22: 修复放缓 | K22: 判断 | L22: 基准支付率 32%；36% 仅在 CET1 不低于 8.8%、风险加权资产温和增长、资产质量不恶化时成立。
A23: 3 | B23: =D22 -> 1.3167 | C23: 0.04 | D23: =B23*(1+C23) -> 1.369368 | E23: 0.32 | F23: =D23*E23 -> 0.43819776 | G23: =1/(1+估值敏感性!$B$6)^A23 -> 0.72139877 | H23: =F23*G23 -> 0.31611533 | I23: 接近稳态 | K23: 风险 | L23: 信用成本 0.89%，同比上升；若继续走高，分红提升空间受限。
A24: 4 | B24: =D23 -> 1.369368 | C24: 0.035 | D24: =B24*(1+C24) -> 1.4172959 | E24: 0.33 | F24: =D24*E24 -> 0.46770764 | G24: =1/(1+估值敏感性!$B$6)^A24 -> 0.64699441 | H24: =F24*G24 -> 0.30260423 | I24: 资本约束仍在 | K24: 监控 | L24: CET1、RWA 增速、不良生成、核销与拨备覆盖率。
A25: 5 | B25: =D24 -> 1.4172959 | C25: 0.03 | D25: =B25*(1+C25) -> 1.4598148 | E25: 0.35 | F25: =D25*E25 -> 0.51093516 | G25: =1/(1+估值敏感性!$B$6)^A25 -> 0.58026405 | H25: =F25*G25 -> 0.29647731 | I25: 稳态过渡 | K25: 结论 | L25: 高股息有支撑，但预案股息不能与已实施股息混为一谈。
A27: 长期增长率 | B27: =估值敏感性!$B$7 -> 0.025
A28: 终值支付率 | B28: 0.38
A29: 第6年 DPS | B29: =D25*(1+B27)*B28 -> 0.56859785
A30: 终值 | B30: =B29/(估值敏感性!$B$6-B27) -> 6.3177539
A31: 终值现值 | B31: =B30/(1+估值敏感性!$B$6)^5 -> 3.6659654
A32: 前5年 DPS 现值 | B32: =SUM(H21:H25) -> 1.5825314
A33: DDM 每股价值 | B33: =B31+B32 -> 5.2484968

Sheet 财务十年
A2: 北京银行财务十年 | B2: 北京银行财务十年 | C2: 北京银行财务十年 | D2: 北京银行财务十年 | E2: 北京银行财务十年 | F2: 北京银行财务十年 | G2: 北京银行财务十年 | H2: 北京银行财务十年 | I2: 北京银行财务十年 | J2: 北京银行财务十年 | K2: 北京银行财务十年 | L2: 北京银行财务十年 | M2: 北京银行财务十年 | N2: 北京银行财务十年 | O2: 北京银行财务十年 | P2: 北京银行财务十年 | Q2: 北京银行财务十年 | R2: 北京银行财务十年 | S2: 北京银行财务十年
A3: 金额单位：亿元；2026H1 为半年度数据，ROE/ROA 为公司披露年化口径 | B3: 金额单位：亿元；2026H1 为半年度数据，ROE/ROA 为公司披露年化口径 | C3: 金额单位：亿元；2026H1 为半年度数据，ROE/ROA 为公司披露年化口径 | D3: 金额单位：亿元；2026H1 为半年度数据，ROE/ROA 为公司披露年化口径 | E3: 金额单位：亿元；2026H1 为半年度数据，ROE/ROA 为公司披露年化口径 | F3: 金额单位：亿元；2026H1 为半年度数据，ROE/ROA 为公司披露年化口径 | G3: 金额单位：亿元；2026H1 为半年度数据，ROE/ROA 为公司披露年化口径 | H3: 金额单位：亿元；2026H1 为半年度数据，ROE/ROA 为公司披露年化口径 | I3: 金额单位：亿元；2026H1 为半年度数据，ROE/ROA 为公司披露年化口径 | J3: 金额单位：亿元；2026H1 为半年度数据，ROE/ROA 为公司披露年化口径 | K3: 金额单位：亿元；2026H1 为半年度数据，ROE/ROA 为公司披露年化口径 | L3: 金额单位：亿元；2026H1 为半年度数据，ROE/ROA 为公司披露年化口径 | M3: 金额单位：亿元；2026H1 为半年度数据，ROE/ROA 为公司披露年化口径 | N3: 金额单位：亿元；2026H1 为半年度数据，ROE/ROA 为公司披露年化口径 | O3: 金额单位：亿元；2026H1 为半年度数据，ROE/ROA 为公司披露年化口径 | P3: 金额单位：亿元；2026H1 为半年度数据，ROE/ROA 为公司披露年化口径 | Q3: 金额单位：亿元；2026H1 为半年度数据，ROE/ROA 为公司披露年化口径 | R3: 金额单位：亿元；2026H1 为半年度数据，ROE/ROA 为公司披露年化口径 | S3: 金额单位：亿元；2026H1 为半年度数据，ROE/ROA 为公司披露年化口径
A4: 期间 | B4: 营业收入 | C4: 归母净利润 | D4: EPS | E4: BPS | F4: ROE | G4: ROA | H4: 净息差 | I4: 不良率 | J4: 拨备覆盖率 | K4: CET1 | L4: 成本收入比 | M4: 总资产 | N4: 贷款本金 | O4: 存款本金 | P4: DPS | Q4: 期末/当前价 | R4: PB | S4: PE
A5: 2016 | B5: 474.56 | C5: 178.02 | D5: 0.96 | E5: 8.17 | F5: 0.1492 | G5: 0.009 | H5: n.a. | I5: 0.0127 | J5: 2.5606 | K5: 0.0826 | L5: 0.2581 | M5: 21163.39 | N5: 8999.07 | O5: 11509.04 | P5: 0.25 | Q5: 9.76 | R5: =Q5/E5 -> 1.1946144 | S5: =Q5/D5 -> 10.166667
A6: 2017 | B6: 503.53 | C6: 187.33 | D6: 0.99 | E6: 7.43 | F6: 0.1377 | G6: 0.0085 | H6: n.a. | I6: 0.0124 | J6: 2.6557 | K6: 0.0892 | L6: 0.2685 | M6: 23298.05 | N6: 10771.01 | O6: 12686.98 | P6: 0.267 | Q6: 7.15 | R6: =Q6/E6 -> 0.96231494 | S6: =Q6/D6 -> 7.2222222
A7: 2018 | B7: 554.88 | C7: 200.02 | D7: 0.91 | E7: 8.26 | F7: 0.1089 | G7: 0.0082 | H7: 0.0188 | I7: 0.0146 | J7: 2.1751 | K7: 0.0893 | L7: 0.2519 | M7: 25728.65 | N7: 12618.11 | O7: 13860.06 | P7: 0.286 | Q7: 5.61 | R7: =Q7/E7 -> 0.67917676 | S7: =Q7/D7 -> 6.1648352
A8: 2019 | B8: 631.29 | C8: 214.41 | D8: 0.98 | E8: 8.95 | F8: 0.1145 | G8: 0.0081 | H8: 0.0196 | I8: 0.014 | J8: 2.2469 | K8: 0.0922 | L8: 0.2323 | M8: 27370.4 | N8: 14519.09 | O8: 15451.3 | P8: 0.305 | Q8: 5.68 | R8: =Q8/E8 -> 0.63463687 | S8: =Q8/D8 -> 5.7959184
A9: 2020 | B9: 642.99 | C9: 214.84 | D9: 0.98 | E9: 9.52 | F9: 0.1065 | G9: 0.0077 | H9: 0.0192 | I9: 0.0157 | J9: 2.1595 | K9: 0.0942 | L9: 0.2207 | M9: 29000.14 | N9: 15736.57 | O9: 16561.49 | P9: 0.3 | Q9: 4.84 | R9: =Q9/E9 -> 0.50840336 | S9: =Q9/D9 -> 4.9387755
A10: 2021 | B10: 662.75 | C10: 222.26 | D10: 1.02 | E10: 10.27 | F10: 0.1029 | G10: 0.0075 | H10: 0.0183 | I10: 0.0144 | J10: 2.1022 | K10: 0.0986 | L10: 0.2496 | M10: 30589.59 | N10: 16732.38 | O10: 16993.37 | P10: 0.305 | Q10: 4.44 | R10: =Q10/E10 -> 0.43232717 | S10: =Q10/D10 -> 4.3529412
A11: 2022 | B11: 662.76 | C11: 247.6 | D11: 1.02 | E11: 10.91 | F11: 0.096 | G11: 0.0077 | H11: 0.0176 | I11: 0.0143 | J11: 2.1004 | K11: 0.0954 | L11: 0.2655 | M11: 33879.52 | N11: 17973.19 | O11: 19133.58 | P11: 0.31 | Q11: 4.31 | R11: =Q11/E11 -> 0.39505041 | S11: =Q11/D11 -> 4.2254902
A12: 2023 | B12: 667.11 | C12: 256.24 | D12: 1.06 | E12: 11.78 | F12: 0.0932 | G12: 0.0072 | H12: 0.0154 | I12: 0.0132 | J12: 2.1678 | K12: 0.0921 | L12: 0.2888 | M12: 37486.79 | N12: 20155.52 | O12: 20697.91 | P12: 0.32 | Q12: 4.53 | R12: =Q12/E12 -> 0.38455008 | S12: =Q12/D12 -> 4.2735849
A13: 2024 | B13: 704.2 | C13: 263.34 | D13: 1.09 | E13: 12.73 | F13: 0.0865 | G13: 0.0066 | H13: 0.0147 | I13: 0.0131 | J13: 2.0875 | K13: 0.0895 | L13: 0.2893 | M13: 42191.86 | N13: 22099.75 | O13: 24494.25 | P13: 0.32 | Q13: 6.15 | R13: =Q13/E13 -> 0.48311076 | S13: =Q13/D13 -> 5.6422018
A14: 2025 | B14: 680.36 | C14: 200.86 | D14: 0.78 | E14: 12.97 | F14: 0.0611 | G14: 0.0044 | H14: 0.0127 | I14: 0.0129 | J14: 2.0021 | K14: 0.0837 | L14: 0.309 | M14: 49382.73 | N14: 23997.55 | O14: 26950 | P14: 0.278 | Q14: 5.48 | R14: =Q14/E14 -> 0.42251349 | S14: =Q14/D14 -> 7.025641
A15: 2026H1 | B15: 382.48 | C15: 159 | D15: 0.71 | E15: 13.48 | F15: 0.106 | G15: 0.0066 | H15: 0.0126 | I15: 0.013 | J15: 1.9959 | K15: 0.0891 | L15: 0.2347 | M15: 47429.66 | N15: 24020.57 | O15: 28199.58 | P15: 0.13 | Q15: 5.62 | R15: =Q15/E15 -> 0.41691395 | S15: 5.68
A17: 盈利与规模趋势 | B17: 盈利与规模趋势 | C17: 盈利与规模趋势 | D17: 盈利与规模趋势 | E17: 盈利与规模趋势 | F17: 盈利与规模趋势 | G17: 盈利与规模趋势 | H17: 盈利与规模趋势 | I17: 盈利与规模趋势 | J17: 收益率与息差趋势 | K17: 收益率与息差趋势 | L17: 收益率与息差趋势 | M17: 收益率与息差趋势 | N17: 收益率与息差趋势 | O17: 收益率与息差趋势 | P17: 收益率与息差趋势 | Q17: 收益率与息差趋势 | R17: 收益率与息差趋势 | S17: 收益率与息差趋势
A36: 口径说明 | B36: 2016—2025 为年度数据；2024 起保险合同准则导致比较数据有重述，采用最新披露口径。2026H1 不与全年金额直接相加或同比。
A37: 历史估值用途 | B37: 历史 PB/PE 主锚使用 2020—2025 六个年末快照，避免把更早股本变动直接混入中枢。

Sheet 资产质量
A2: 北京银行资产质量、资本与重点敞口 | B2: 北京银行资产质量、资本与重点敞口 | C2: 北京银行资产质量、资本与重点敞口 | D2: 北京银行资产质量、资本与重点敞口 | E2: 北京银行资产质量、资本与重点敞口 | F2: 北京银行资产质量、资本与重点敞口 | G2: 北京银行资产质量、资本与重点敞口 | H2: 北京银行资产质量、资本与重点敞口 | I2: 北京银行资产质量、资本与重点敞口 | J2: 北京银行资产质量、资本与重点敞口 | K2: 北京银行资产质量、资本与重点敞口 | L2: 北京银行资产质量、资本与重点敞口 | M2: 北京银行资产质量、资本与重点敞口 | N2: 北京银行资产质量、资本与重点敞口
A3: 经营数据截至 2026-06-30；金额单位：亿元 | B3: 经营数据截至 2026-06-30；金额单位：亿元 | C3: 经营数据截至 2026-06-30；金额单位：亿元 | D3: 经营数据截至 2026-06-30；金额单位：亿元 | E3: 经营数据截至 2026-06-30；金额单位：亿元 | F3: 经营数据截至 2026-06-30；金额单位：亿元 | G3: 经营数据截至 2026-06-30；金额单位：亿元 | H3: 经营数据截至 2026-06-30；金额单位：亿元 | I3: 经营数据截至 2026-06-30；金额单位：亿元 | J3: 经营数据截至 2026-06-30；金额单位：亿元 | K3: 经营数据截至 2026-06-30；金额单位：亿元 | L3: 经营数据截至 2026-06-30；金额单位：亿元 | M3: 经营数据截至 2026-06-30；金额单位：亿元 | N3: 经营数据截至 2026-06-30；金额单位：亿元
A4: 核心风险指标 | B4: 核心风险指标 | C4: 核心风险指标 | D4: 核心风险指标 | E4: 核心风险指标 | G4: 贷款结构与重点敞口 | H4: 贷款结构与重点敞口 | I4: 贷款结构与重点敞口 | J4: 贷款结构与重点敞口 | K4: 贷款结构与重点敞口 | L4: 贷款结构与重点敞口 | M4: 贷款结构与重点敞口 | N4: 贷款结构与重点敞口
A5: 指标 | B5: 2024A | C5: 2025A | D5: 2026H1 | E5: 变化/判断 | G5: 项目 | H5: 2025A | I5: 2026H1 | J5: 变动 | K5: 占贷款比 | L5: 风险含义 | M5: 口径 | N5: 备注
A6: 不良率 | B6: 0.0131 | C6: 0.0129 | D6: 0.013 | E6: 较年初 +1bp | G6: 公司贷款 | H6: 16808.76 | I6: 17120.67 | J6: 0.0186 | K6: 0.7128 | L6: 主体增长来源 | M6: 本金 | N6: 含一般贷款、贴现、福费廷
A7: 关注率 | C7: 0.0161 | D7: 0.0158 | E7: 较年初 -3bp | G7: 个人贷款 | H7: 7188.79 | I7: 6899.9 | J7: -0.0402 | K7: 0.2872 | L7: 零售收缩 | M7: 本金 | N7: 个人端需求与风险出清并存
A8: 逾期率 | C8: 0.0196 | D8: 0.0196 | E8: 持平 | G8: 住房按揭 | H8: 3301.89 | I8: 3256.12 | J8: -0.0139 | K8: 0.1356 | L8: 抵押类零售 | M8: 本金 | N8: 不等同于全部涉房敞口
A9: 90天以上逾期/不良 | C9: 0.8404 | D9: 0.8622 | E9: 较年初 +218bp | G9: 个人经营贷 | H9: 1677 | I9: 1566.55 | J9: -0.0659 | K9: 0.0652 | L9: 下降较快 | M9: 本金 | N9: 需关注小微还款能力
A10: 拨备覆盖率 | B10: 2.0875 | C10: 2.0021 | D10: 1.9959 | E10: 较年初 -62bp | G10: 个人消费贷 | H10: 2057.45 | I10: 1943.93 | J10: -0.0552 | K10: 0.0809 | L10: 下降 | M10: 本金 | N10: 收益较高但信用风险敏感
A11: 拨贷比 | B11: 0.0273 | C11: 0.0258 | D11: 0.0259 | E11: 较年初 +1bp | G11: 信用卡 | H11: 152.45 | I11: 133.3 | J11: -0.1256 | K11: 0.0055 | L11: 规模较小 | M11: 本金 | N11: 同比口径未披露
A12: 信用成本 | B12: 0.0087 | C12: 0.0075 | D12: 0.0089 | E12: 较2025全年 +14bp | G12: 房地产业贷款 | H12: 1211.6 | I12: 1114.71 | J12: -0.08 | K12: 0.0464 | L12: 对公口径下降 | M12: 行业分类 | N12: 不能代表承担信用风险涉房总敞口
A13: 核心一级资本充足率 | B13: 0.0895 | C13: 0.0837 | D13: 0.0891 | E13: 较年初 +54bp | G13: 关注贷款 | H13: 387.13 | I13: 380.05 | J13: -0.0183 | K13: 0.0158 | L13: 余额下降 | M13: 五级分类 | N13: 迁徙率升至 50.72%
A14: 资本充足率 | B14: 0.1306 | C14: 0.1288 | D14: 0.141 | E14: 较年初 +122bp | G14: 逾期贷款 | H14: 470.48 | I14: 470.95 | J14: 0.001 | K14: 0.0196 | L14: 总额基本持平 | M14: 本金逾期 | N14: 90天以上偏离度上升
A15: 流动性覆盖率 | B15: 1.3806 | C15: 1.7099 | D15: 1.823 | E15: 流动性充足
A18: 不良、拨备与处置 | B18: 不良、拨备与处置 | C18: 不良、拨备与处置 | D18: 不良、拨备与处置 | E18: 不良、拨备与处置 | F18: 不良、拨备与处置 | H18: 风险诊断 | I18: 风险诊断 | J18: 风险诊断 | K18: 风险诊断 | L18: 风险诊断 | M18: 风险诊断 | N18: 风险诊断
A19: 项目 | B19: 2025A | C19: 2026H1 | D19: 变化 | E19: 单位 | F19: 解读 | H19: 事实 | I19: 2026H1 信用减值损失 100.05 亿元，同比增加 11.49%。
A20: 正常类贷款 | B20: 23300.75 | C20: 23328.94 | D20: 28.19 | E20: 亿元 | F20: 贷款总量近乎不变 | H20: 事实 | I20: 关注率下降，但关注类迁徙率由 28.69% 升至 50.72%。
A21: 关注类贷款 | B21: 387.13 | C21: 380.05 | D21: -7.08 | E21: 亿元 | F21: 余额下降 | H21: 事实 | I21: 核销及转出 119.28 亿元，不良余额仅增加 1.91 亿元。
A22: 不良贷款 | B22: 309.67 | C22: 311.58 | D22: 1.91 | E22: 亿元 | F22: 余额小幅上升 | H22: 判断 | I22: 点时不良率稳定不能单独证明风险已彻底改善；处置与核销贡献较大。
A23: 贷款减值准备期初 | C23: 620 | E23: 亿元 | F23: 本行口径 | H23: 判断 | I23: 房地产业贷款占比 4.64%，但报告未完整拆分承担信用风险涉房业务总口径。
A24: 本期计提 | C24: 106.92 | E24: 亿元 | F24: 信用成本上行 | H24: 资本 | I24: CET1 回升至 8.91%，改善明显，但仍需约束增长和支付率假设。
A25: 收回已核销 | C25: 16.11 | E25: 亿元 | F25: 补充拨备 | H25: 监控 | I25: 信用成本>1%、关注率>1.7%、逾期率>2.1%、CET1<8.5% 为主要触发线。
A26: 本期核销及转出 | C26: -119.28 | E26: 亿元 | F26: 处置规模大于不良净增
A27: 贷款减值准备期末 | C27: 621.87 | E27: 亿元 | F27: 本行口径

Sheet 同业比较
A2: 北京银行同业比较 | B2: 北京银行同业比较 | C2: 北京银行同业比较 | D2: 北京银行同业比较 | E2: 北京银行同业比较 | F2: 北京银行同业比较 | G2: 北京银行同业比较 | H2: 北京银行同业比较 | I2: 北京银行同业比较 | J2: 北京银行同业比较 | K2: 北京银行同业比较 | L2: 北京银行同业比较 | M2: 北京银行同业比较
A3: 市场快照：2026-10-14 11:55；财务数据：2026H1；ROE 为半年值简单年化 | B3: 市场快照：2026-10-14 11:55；财务数据：2026H1；ROE 为半年值简单年化 | C3: 市场快照：2026-10-14 11:55；财务数据：2026H1；ROE 为半年值简单年化 | D3: 市场快照：2026-10-14 11:55；财务数据：2026H1；ROE 为半年值简单年化 | E3: 市场快照：2026-10-14 11:55；财务数据：2026H1；ROE 为半年值简单年化 | F3: 市场快照：2026-10-14 11:55；财务数据：2026H1；ROE 为半年值简单年化 | G3: 市场快照：2026-10-14 11:55；财务数据：2026H1；ROE 为半年值简单年化 | H3: 市场快照：2026-10-14 11:55；财务数据：2026H1；ROE 为半年值简单年化 | I3: 市场快照：2026-10-14 11:55；财务数据：2026H1；ROE 为半年值简单年化 | J3: 市场快照：2026-10-14 11:55；财务数据：2026H1；ROE 为半年值简单年化 | K3: 市场快照：2026-10-14 11:55；财务数据：2026H1；ROE 为半年值简单年化 | L3: 市场快照：2026-10-14 11:55；财务数据：2026H1；ROE 为半年值简单年化 | M3: 市场快照：2026-10-14 11:55；财务数据：2026H1；ROE 为半年值简单年化
A4: 银行 | B4: 代码 | C4: 股价 | D4: PE TTM | E4: PB | F4: ROE(年化) | G4: 净息差 | H4: 不良率 | I4: 拨备覆盖率 | J4: CET1 | K4: 营收增速 | L4: 净利增速 | M4: BPS
A5: 北京银行 | B5: 601169.SH | C5: 5.62 | D5: 5.68 | E5: 0.42 | F5: 0.106 | G5: 0.0126 | H5: 0.013 | I5: 1.9959 | J5: 0.0891 | K5: 0.056 | L5: 0.0563 | M5: 13.48
A6: 上海银行 | B6: 601229.SH | C6: 9.68 | D6: 5.71 | E6: 0.54 | F6: 0.105 | G6: 0.0115 | H6: 0.0142 | I6: 1.9825 | J6: 0.1068 | K6: 0.0548 | L6: 0.0051 | M6: 18.12
A7: 江苏银行 | B7: 600919.SH | C7: 12.46 | D7: 6.33 | E7: 0.84 | F7: 0.1572 | G7: 0.0164 | H7: 0.0081 | I7: 3.0483 | J7: 0.0867 | K7: 0.0911 | L7: 0.0809 | M7: 14.79
A8: 南京银行 | B8: 601009.SH | C8: 11.96 | D8: 6.47 | E8: 0.77 | F8: 0.145 | G8: 0.0179 | H8: 0.0082 | I8: 3.0611 | J8: 0.0937 | K8: 0.1094 | L8: 0.0817 | M8: 15.62
A9: 宁波银行 | B9: 002142.SZ | C9: 35.29 | D9: 7.49 | E9: 0.96 | F9: 0.1424 | G9: 0.017 | H9: 0.0076 | I9: 3.7335 | J9: 0.0953 | K9: 0.1154 | L9: 0.1212 | M9: 36.76
A10: 杭州银行 | B10: 600926.SH | C10: 17.08 | D10: 6.14 | E10: 0.88 | F10: 0.1774 | G10: 0.0139 | H10: 0.0076 | I10: 4.7196 | J10: 0.0952 | K10: 0.0475 | L10: 0.0987 | M10: 19.84
A11: 成都银行 | B11: 601838.SH | C11: 19.31 | D11: 6.03 | E11: 0.91 | F11: 0.1498 | G11: 0.0167 | H11: 0.0068 | I11: 4.2606 | J11: 0.0897 | K11: 0.0413 | L11: 0.0435 | M11: 21.76
A13: 同业中位数（不含北京银行） | C13: =MEDIAN(C6:C11) -> 14.77 | D13: =MEDIAN(D6:D11) -> 6.235 | E13: =MEDIAN(E6:E11) -> 0.86 | F13: =MEDIAN(F6:F11) -> 0.1474 | G13: =MEDIAN(G6:G11) -> 0.01655 | H13: =MEDIAN(H6:H11) -> 0.00785 | I13: =MEDIAN(I6:I11) -> 3.3973 | J13: =MEDIAN(J6:J11) -> 0.09445 | ... M13: =MEDIAN(M6:M11) -> 18.98
A15: 同业 ROE 调整 PB | B15: 同业 ROE 调整 PB | C15: 同业 ROE 调整 PB | D15: 同业 ROE 调整 PB | E15: 同业 ROE 调整 PB | F15: 同业 ROE 调整 PB | H15: 当前 PB 对比 | I15: 当前 PB 对比 | J15: 当前 PB 对比 | K15: 当前 PB 对比 | L15: 当前 PB 对比 | M15: 当前 PB 对比
A16: 同业 PB 中位数 | B16: =E13 -> 0.86 | D16: 计算说明
A17: 北京银行 ROE | B17: =F5 -> 0.106 | D17: 可比组 | E17: 城商行同业
A18: 同业 ROE 中位数 | B18: =F13 -> 0.1474 | D18: β | E18: ROE 差异向 PB 传导
A19: ROE 弹性 β | B19: 0.8 | D19: 额外折价 | E19: 北京银行 CET1 较低且资产质量弱于优质同业
A20: 质量与资本折价 | B20: 0.15 | D20: 目标每股价值 | E20: =B21*M5 -> 7.5692696
A21: 目标 PB | B21: =B16*(B17/B18)^B19*(1-B20) -> 0.56151852 | D21: 结果口径 | E21: 目标 PB × 北京银行 BPS
A24: 结论 | B24: 北京银行 PB 低于同业中位数，但 ROE、CET1 和不良率也弱于多数高质量城商行。折价并非全是误定价。
A25: 模型使用 | B25: 以 β=0.8 调整 ROE 差异，再追加 15% 质量与资本折价，结果进入组合估值。
A26: 局限 | B26: 市场数据来自同一时点第三方快照；各行会计和业务结构仍有差异。
A27: 监控 | B27: 若北京银行 ROE 提升且 CET1 保持 8.8%以上，额外折价可下调；反之应上调。

Sheet 巴菲特框架
A2: 北京银行长期质量框架 | B2: 北京银行长期质量框架 | C2: 北京银行长期质量框架 | D2: 北京银行长期质量框架 | E2: 北京银行长期质量框架 | F2: 北京银行长期质量框架 | G2: 北京银行长期质量框架 | H2: 北京银行长期质量框架
A3: 适用于银行的能力圈、负债优势、信贷文化、资本配置与价值陷阱检查 | B3: 适用于银行的能力圈、负债优势、信贷文化、资本配置与价值陷阱检查 | C3: 适用于银行的能力圈、负债优势、信贷文化、资本配置与价值陷阱检查 | D3: 适用于银行的能力圈、负债优势、信贷文化、资本配置与价值陷阱检查 | E3: 适用于银行的能力圈、负债优势、信贷文化、资本配置与价值陷阱检查 | F3: 适用于银行的能力圈、负债优势、信贷文化、资本配置与价值陷阱检查 | G3: 适用于银行的能力圈、负债优势、信贷文化、资本配置与价值陷阱检查 | H3: 适用于银行的能力圈、负债优势、信贷文化、资本配置与价值陷阱检查
A4: 维度 | B4: 客观证据 | C4: 判断 | D4: 支持因素 | E4: 反证/风险 | F4: 监控指标 | G4: 失效条件 | H4: 结论
A5: 能力圈 | B5: 扎根北京并覆盖京津冀、长三角等区域；北京贷款占 41.18%。 | C5: 可理解 | D5: 区域客户基础清晰 | E5: 区域与大客户集中度 | F5: 北京贷款占比、前十大客户 | G5: 区域信用风险明显抬升 | H5: 中性偏正面
A6: 商业模式 | B6: 利息净收入占营收 71.86%，存款占负债 65.07%。 | C6: 较稳定 | D6: 公司与政府客户基础 | E6: 息差仍处下行区间 | F6: NIM、存款成本 | G6: NIM 持续低于 1.15% | H6: 中性
A7: 存款成本优势 | B7: 负债成本率 1.45%，同比下降 27bp；企业活期存款增长 8.02%。 | C7: 改善 | D7: 高成本负债压降 | E7: 个人活期存款略降 | F7: 活期占比、存款成本 | G7: 存款成本重新上升 | H7: 正面
A8: 信贷文化 | B8: 不良率 1.30%，拨备覆盖率 199.59%。 | C8: 需验证 | D8: 拨备仍接近 200% | E8: 迁徙率和信用成本上升，核销规模大 | F8: 新生成不良、核销、迁徙率 | G8: 关注与逾期同步恶化 | H8: 谨慎
A9: 治理诚信 | B9: 定期披露较完整，2026 中报经审阅。 | C9: 可接受 | D9: 审计与监管披露 | E9: 政府股东与关联授信需持续观察 | F9: 关联交易、监管处罚 | G9: 重大内控或合规事件 | H9: 中性
A10: 资本配置 | B10: CET1 8.91%，总资本充足率 14.10%；提出中期分红。 | C10: 受约束 | D10: 资本指标回升 | E10: 核心一级资本低于优质同业 | F10: CET1、RWA、支付率 | G10: 高增长与高分红同时出现 | H10: 谨慎
A11: 股东回报 | B11: 2025 DPS 0.278 元；2026H1 拟派 0.13 元。 | C11: 稳定性提升 | D11: 连续分红并新增中期预案 | E11: 预案未实施，盈利需覆盖 | F11: DPS、普通股口径支付率 | G11: 资本下降而支付率上升 | H11: 中性偏正面
A12: 价值陷阱 | B12: 当前 PB 约 0.42x，明显低于同业中位数。 | C12: 不能排除 | D12: 盈利修复可带来重估 | E12: ROE 低、资本薄、信用成本上行 | F12: ROE、CET1、信用成本 | G12: ROE 长期低于 8% | H12: 需持续验证
A15: 总体判断 | B15: 总体判断 | C15: 总体判断 | D15: 总体判断 | E15: 总体判断 | F15: 总体判断 | G15: 总体判断 | H15: 总体判断
A16: 质量 | B16: 北京银行具备区域资源、存款基础和较强风险抵补，但 ROE 与核心一级资本仍弱于高质量城商行。
A17: 价格 | B17: 0.42x PB 提供估值缓冲；是否形成长期复利仍取决于 ROE 能否稳定在 8.5% 以上。
A18: 分红 | B18: 股息吸引力提升，但中期预案未实施，且提高支付率不能脱离 CET1 与信用成本。
A19: 结论 | B19: 属于“有折价、需验证”的银行股，而不是仅凭低 PB 就能确认的深度价值。

Sheet 数据与来源
A2: 北京银行估值数据与来源 | B2: 北京银行估值数据与来源 | C2: 北京银行估值数据与来源 | D2: 北京银行估值数据与来源 | E2: 北京银行估值数据与来源 | F2: 北京银行估值数据与来源 | G2: 北京银行估值数据与来源 | H2: 北京银行估值数据与来源 | I2: 北京银行估值数据与来源
A3: 优先使用交易所定期报告；市场与同业快照使用同一时点第三方数据并交叉核验 | B3: 优先使用交易所定期报告；市场与同业快照使用同一时点第三方数据并交叉核验 | C3: 优先使用交易所定期报告；市场与同业快照使用同一时点第三方数据并交叉核验 | D3: 优先使用交易所定期报告；市场与同业快照使用同一时点第三方数据并交叉核验 | E3: 优先使用交易所定期报告；市场与同业快照使用同一时点第三方数据并交叉核验 | F3: 优先使用交易所定期报告；市场与同业快照使用同一时点第三方数据并交叉核验 | G3: 优先使用交易所定期报告；市场与同业快照使用同一时点第三方数据并交叉核验 | H3: 优先使用交易所定期报告；市场与同业快照使用同一时点第三方数据并交叉核验 | I3: 优先使用交易所定期报告；市场与同业快照使用同一时点第三方数据并交叉核验
A4: 指标/表格 | B4: 数据值/范围 | C4: 口径与单位 | D4: 截至日期 | E4: 发布日期 | F4: 来源名称 | G4: URL | H4: 页码/表名 | I4: 备注
A5: 2026H1经营与风险 | B5: 营收、利润、ROE、NIM、资产质量、资本 | C5: 集团；百万元/比率 | D5: 46203 | E5: 46263 | F5: 北京银行2026年半年度报告 | G5: https://static.sse.com.cn/disclosure/listedinfo/announcement/c/new/2026-08-29/601169_20260829_PXP5.pdf | H5: 第12—17页、管理层讨论 | I5: 关键事实主来源
A6: 2025A经营与资本 | B6: 年度利润、BPS、NIM、不良、资本 | C6: 集团；百万元/比率 | D6: 46022 | E6: 46140 | F6: 北京银行2025年年度报告 | G6: https://file.finance.sina.com.cn/211.154.219.97%3A9494/MRGG/CNSESH_STOCK/2026/2026-4/2026-04-28/12226675.PDF | H6: 第23—31页 | I6: 交易所披露文件镜像
A7: 当前股价 | B7: 5.62元 | C7: 盘中延迟快照 | D7: 46309.164 | E7: 46309 | F7: 东方财富行情接口 | G7: https://push2.eastmoney.com/api/qt/stock/get?secid=1.601169&fields=f57,f58,f43,f60,f84,f116,f162,f164,f167,f86 | H7: 实时行情字段 | I7: 非收盘价
A8: 历史价格 | B8: 2016—2026日线 | C8: 不复权收盘价 | D8: 46309 | E8: 46309 | F8: 东方财富历史行情接口 | G8: https://push2his.eastmoney.com/api/qt/stock/kline/get?secid=1.601169&klt=101&fqt=0&beg=20160101&end=20261014&lmt=5000&fields1=f1,f2,f3,f4,f5,f6&fields2=f51,f52,f53,f54,f55,f56,f57,f58,f59,f60,f61 | H8: 年末最后交易日 | I8: 用于历史PB/PE
A9: 十年财务 | B9: 2016—2025年度，2026H1 | C9: 亿元/元/比率 | D9: 46203 | E9: 46263 | F9: 东方财富F10主财务数据 | G9: https://datacenter-web.eastmoney.com/api/data/v1/get?reportName=RPT_F10_FINANCE_MAINFINADATA&columns=ALL&filter=(SECUCODE%3D%22601169.SH%22)&sortColumns=REPORT_DATE&sortTypes=-1&pageSize=100&pageNumber=1 | H9: 主财务指标 | I9: 年度关键数与公司报告核对
A10: 分红历史 | B10: 2016—2026H1 | C10: 每10股税前现金分红 | D10: 46203 | E10: 46263 | F10: 东方财富分红数据 | G10: https://datacenter-web.eastmoney.com/api/data/v1/get?reportName=RPT_SHAREBONUS_DET&columns=ALL&filter=(SECURITY_CODE%3D%22601169%22)&sortColumns=REPORT_DATE&sortTypes=-1&pageSize=100&pageNumber=1 | H10: 分红实施/预案 | I10: 2026H1为董事会预案
A11: 同业快照 | B11: 7家城商行 | C11: 股价、PE、PB | D11: 46309.164 | E11: 46309 | F11: 东方财富行情接口 | G11: https://push2.eastmoney.com/api/qt/stock/get | H11: 同一时点字段 | I11: 第三方便利数据
A12: 同业财务 | B12: 7家城商行2026H1 | C12: ROE、NIM、不良、拨备、CET1 | D12: 46203 | E12: 46265 | F12: 东方财富F10主财务数据 | G12: https://datacenter-web.eastmoney.com/api/data/v1/get?reportName=RPT_F10_FINANCE_MAINFINADATA&columns=ALL | H12: 2026中报字段 | I12: 关键北京银行数据以公司报告为准
A13: 三季报边界 | B13: 预约2026-10-31披露 | C13: 上交所预约日期 | D13: 46309 | E13: 46309 | F13: 上交所定期报告预约情况 | G13: https://www.sse.com.cn/disclosure/listedinfo/periodic/ | H13: 2026年三季报 | I13: 尚未披露，不纳入
A14: 监管最低资本 | B14: CET1 5%、一级6%、总资本8%基础线 | C14: 不含附加与缓冲 | D14: 46309 | E14: 45292 | F14: 商业银行资本管理办法 | G14: https://www.gov.cn/zhengce/zhengceku/202311/content_6915944.htm | H14: 资本要求 | I14: 实际监管要求还含储备与系统重要性附加
A17: 关键模型假设 | B17: 关键模型假设 | C17: 关键模型假设 | D17: 关键模型假设 | E17: 关键模型假设 | F17: 关键模型假设
A18: 假设 | B18: 数值 | C18: 类型 | D18: 理由 | E18: 可编辑位置 | F18: 版本
A19: 归一化EPS | B19: 1.2 | C19: 分析假设 | D19: 2026H1年化后考虑季节性与风险成本 | E19: 估值敏感性!B8 | F19: 2026-10-14
A20: 归一化ROE | B20: 0.085 | C20: 分析假设 | D20: 低于2026H1年化ROE，接近资本约束下稳态 | E20: 估值敏感性!B5 | F20: 2026-10-14
A21: 股权成本Ke | B21: 0.115 | C21: 分析假设 | D21: 城商行风险、资本与资产质量溢价 | E21: 估值敏感性!B6 | F21: 2026-10-14
A22: 长期增长率 | B22: 0.025 | C22: 分析假设 | D22: 低于长期名义经济增速的审慎取值 | E22: 估值敏感性!B7 | F22: 2026-10-14
A23: 基准支付率 | B23: 0.32 | C23: 分析假设 | D23: 参考历史约30%并考虑中期分红 | E23: 估值敏感性!B9 | F23: 2026-10-14
A24: PB–ROE模型折价 | B24: 0.05 | C24: 分析假设 | D24: 公式稳定期假设偏强 | E24: 估值系统!B12 | F24: 2026-10-14
A25: 同业ROE弹性β | B25: 0.8 | C25: 分析假设 | D25: PB对ROE差异非线性传导 | E25: 同业比较!B19 | F25: 2026-10-14
A26: 同业额外折价 | B26: 0.15 | C26: 分析假设 | D26: CET1、NPL与业务结构差异 | E26: 同业比较!B20 | F26: 2026-10-14
A27: 估值权重 | B27: 15/15/10/10/20/30% | C27: 分析假设 | D27: 提高DDM权重，降低历史倍数权重 | E27: 估值系统!D17:D22 | F27: 2026-10-14
A29: 限制 | B29: 股价为盘中延迟快照，后续交易会改变安全边际。
A30: 限制 | B30: 2026Q3 未披露；截至报告制作日，最新经营数据仍为 2026H1。
A31: 限制 | B31: 半年度报告未完整拆分承担信用风险的涉房业务总口径，不能用对公房地产贷款代替。
A32: 限制 | B32: 同业数据采用统一第三方字段，仍可能存在会计与业务结构差异。
A33: 说明 | B33: 本工作簿用于研究与信息整理，不构成个性化投资建议。
